Workbook

Sheet 202604工资表
A1: 2026年04月份薪资表
A2: 序号 | B2: 姓名 | C2: 公司 | D2: 起薪时间 | E2: 花名册薪资 | F2: EG差额 | G2: 月薪基数 | H2: GI差额2 | I2: 月薪资总额 | J2: 岗位 | K2: 基本薪资 | L2: 绩效薪资基数 | M2: 绩效等级 | N2: 绩效薪资 | O2: 应发薪资 | P2: 补发扣 | Q2: 实际应发薪资 | R2: 月薪资总额和应发差异 | S2: 列1 | T2: 列2
A3: =ROW(A3)-2 -> 1 | B3: 一 | C3: 尚诚能源 | D3: 44713 | E3: 10000 | F3: =E3-G3 -> 0 | G3: 10000 | H3: =G3-I3 -> 0 | I3: =G3 -> 10000 | J3: 南京大学 | K3: {=ROUND(_xlfn.IFS(OR(J3="南京大学",J3="BOSS",J3="实习生",J3="人力劳务"),I3,J3="部门负责人",I3*0.6,J3="员工",I3*0.7),2)} -> 10000 | L3: {=ROUND(_xlfn.IFS(OR(J3="南京大学",J3="BOSS",J3="实习生",J3="人力劳务"),I3*0,J3="部门负责人",I3*0.4,J3="员工",I3*0.3),2)} -> 0 | M3: 无等级 | N3: {=ROUND(_xlfn.IFS(M3="A",L3*1.5,M3="B",L3*1.2,M3="C",L3*1,M3="D",L3*0.8,M3="E",L3*0.6,M3="无等级",L3*0),2)} -> 0 | O3: =ROUND(K3+N3,2) -> 10000 | P3: 0 | Q3: =ROUND(O3+P3,2) -> 10000 | R3: =O3-I3 -> 0
A4: =ROW(A4)-2 -> 2 | B4: 二 | C4: 尚诚能源 | D4: 44805 | E4: 10000 | F4: =E4-G4 -> 0 | G4: 10000 | H4: =G4-I4 -> 0 | I4: =G4 -> 10000 | J4: 南京大学 | K4: {=ROUND(_xlfn.IFS(OR(J4="南京大学",J4="BOSS",J4="实习生",J4="人力劳务"),I4,J4="部门负责人",I4*0.6,J4="员工",I4*0.7),2)} -> 10000 | L4: {=ROUND(_xlfn.IFS(OR(J4="南京大学",J4="BOSS",J4="实习生",J4="人力劳务"),I4*0,J4="部门负责人",I4*0.4,J4="员工",I4*0.3),2)} -> 0 | M4: 无等级 | N4: {=ROUND(_xlfn.IFS(M4="A",L4*1.5,M4="B",L4*1.2,M4="C",L4*1,M4="D",L4*0.8,M4="E",L4*0.6,M4="无等级",L4*0),2)} -> 0 | O4: =ROUND(K4+N4,2) -> 10000 | P4: 0 | Q4: =ROUND(O4+P4,2) -> 10000 | R4: =O4-I4 -> 0
A5: =ROW(A5)-2 -> 3 | B5: 三 | C5: 尚诚能源 | D5: 44958 | E5: 10000 | F5: =E5-G5 -> 0 | G5: 10000 | H5: =G5-I5 -> 0 | I5: =G5 -> 10000 | J5: 南京大学 | K5: {=ROUND(_xlfn.IFS(OR(J5="南京大学",J5="BOSS",J5="实习生",J5="人力劳务"),I5,J5="部门负责人",I5*0.6,J5="员工",I5*0.7),2)} -> 10000 | L5: {=ROUND(_xlfn.IFS(OR(J5="南京大学",J5="BOSS",J5="实习生",J5="人力劳务"),I5*0,J5="部门负责人",I5*0.4,J5="员工",I5*0.3),2)} -> 0 | M5: 无等级 | N5: {=ROUND(_xlfn.IFS(M5="A",L5*1.5,M5="B",L5*1.2,M5="C",L5*1,M5="D",L5*0.8,M5="E",L5*0.6,M5="无等级",L5*0),2)} -> 0 | O5: =ROUND(K5+N5,2) -> 10000 | P5: 0 | Q5: =ROUND(O5+P5,2) -> 10000 | R5: =O5-I5 -> 0
A6: =ROW(A6)-2 -> 4 | B6: 四 | C6: 尚诚能源 | D6: 44986 | E6: 10000 | F6: =E6-G6 -> 0 | G6: 10000 | H6: =G6-I6 -> 0 | I6: =G6 -> 10000 | J6: 南京大学 | K6: {=ROUND(_xlfn.IFS(OR(J6="南京大学",J6="BOSS",J6="实习生",J6="人力劳务"),I6,J6="部门负责人",I6*0.6,J6="员工",I6*0.7),2)} -> 10000 | L6: {=ROUND(_xlfn.IFS(OR(J6="南京大学",J6="BOSS",J6="实习生",J6="人力劳务"),I6*0,J6="部门负责人",I6*0.4,J6="员工",I6*0.3),2)} -> 0 | M6: 无等级 | N6: {=ROUND(_xlfn.IFS(M6="A",L6*1.5,M6="B",L6*1.2,M6="C",L6*1,M6="D",L6*0.8,M6="E",L6*0.6,M6="无等级",L6*0),2)} -> 0 | O6: =ROUND(K6+N6,2) -> 10000 | P6: 0 | Q6: =ROUND(O6+P6,2) -> 10000 | R6: =O6-I6 -> 0
A7: =ROW(A7)-2 -> 5 | B7: 五 | C7: 尚诚能源 | D7: 45231 | E7: 10000 | F7: =E7-G7 -> 0 | G7: 10000 | H7: =G7-I7 -> 0 | I7: =G7 -> 10000 | J7: 南京大学 | K7: {=ROUND(_xlfn.IFS(OR(J7="南京大学",J7="BOSS",J7="实习生",J7="人力劳务"),I7,J7="部门负责人",I7*0.6,J7="员工",I7*0.7),2)} -> 10000 | L7: {=ROUND(_xlfn.IFS(OR(J7="南京大学",J7="BOSS",J7="实习生",J7="人力劳务"),I7*0,J7="部门负责人",I7*0.4,J7="员工",I7*0.3),2)} -> 0 | M7: 无等级 | N7: {=ROUND(_xlfn.IFS(M7="A",L7*1.5,M7="B",L7*1.2,M7="C",L7*1,M7="D",L7*0.8,M7="E",L7*0.6,M7="无等级",L7*0),2)} -> 0 | O7: =ROUND(K7+N7,2) -> 10000 | P7: 0 | Q7: =ROUND(O7+P7,2) -> 10000 | R7: =O7-I7 -> 0
A8: =ROW(A8)-2 -> 6 | B8: 六 | C8: 尚诚能源 | D8: 45658 | E8: 10000 | F8: =E8-G8 -> 0 | G8: 10000 | H8: =G8-I8 -> 0 | I8: =G8 -> 10000 | J8: 南京大学 | K8: {=ROUND(_xlfn.IFS(OR(J8="南京大学",J8="BOSS",J8="实习生",J8="人力劳务"),I8,J8="部门负责人",I8*0.6,J8="员工",I8*0.7),2)} -> 10000 | L8: {=ROUND(_xlfn.IFS(OR(J8="南京大学",J8="BOSS",J8="实习生",J8="人力劳务"),I8*0,J8="部门负责人",I8*0.4,J8="员工",I8*0.3),2)} -> 0 | M8: 无等级 | N8: {=ROUND(_xlfn.IFS(M8="A",L8*1.5,M8="B",L8*1.2,M8="C",L8*1,M8="D",L8*0.8,M8="E",L8*0.6,M8="无等级",L8*0),2)} -> 0 | O8: =ROUND(K8+N8,2) -> 10000 | P8: 0 | Q8: =ROUND(O8+P8,2) -> 10000 | R8: =O8-I8 -> 0
A9: =ROW(A9)-2 -> 7 | B9: 七 | C9: 尚诚能源 | D9: 45658 | E9: 10000 | F9: =E9-G9 -> 0 | G9: 10000 | H9: =G9-I9 -> 0 | I9: =G9 -> 10000 | J9: 南京大学 | K9: {=ROUND(_xlfn.IFS(OR(J9="南京大学",J9="BOSS",J9="实习生",J9="人力劳务"),I9,J9="部门负责人",I9*0.6,J9="员工",I9*0.7),2)} -> 10000 | L9: {=ROUND(_xlfn.IFS(OR(J9="南京大学",J9="BOSS",J9="实习生",J9="人力劳务"),I9*0,J9="部门负责人",I9*0.4,J9="员工",I9*0.3),2)} -> 0 | M9: 无等级 | N9: {=ROUND(_xlfn.IFS(M9="A",L9*1.5,M9="B",L9*1.2,M9="C",L9*1,M9="D",L9*0.8,M9="E",L9*0.6,M9="无等级",L9*0),2)} -> 0 | O9: =ROUND(K9+N9,2) -> 10000 | P9: 0 | Q9: =ROUND(O9+P9,2) -> 10000 | R9: =O9-I9 -> 0
A10: =ROW(A10)-2 -> 8 | B10: 八 | C10: 尚诚能源 | D10: 45809 | E10: 10000 | F10: =E10-G10 -> 0 | G10: 10000 | H10: =G10-I10 -> 0 | I10: =G10 -> 10000 | J10: 南京大学 | K10: {=ROUND(_xlfn.IFS(OR(J10="南京大学",J10="BOSS",J10="实习生",J10="人力劳务"),I10,J10="部门负责人",I10*0.6,J10="员工",I10*0.7),2)} -> 10000 | L10: {=ROUND(_xlfn.IFS(OR(J10="南京大学",J10="BOSS",J10="实习生",J10="人力劳务"),I10*0,J10="部门负责人",I10*0.4,J10="员工",I10*0.3),2)} -> 0 | M10: 无等级 | N10: {=ROUND(_xlfn.IFS(M10="A",L10*1.5,M10="B",L10*1.2,M10="C",L10*1,M10="D",L10*0.8,M10="E",L10*0.6,M10="无等级",L10*0),2)} -> 0 | O10: =ROUND(K10+N10,2) -> 10000 | P10: 0 | Q10: =ROUND(O10+P10,2) -> 10000 | R10: =O10-I10 -> 0
A11: =ROW(A11)-2 -> 9 | B11: 九 | C11: 尚诚能源 | D11: 45809 | E11: 10000 | F11: =E11-G11 -> 0 | G11: 10000 | H11: =G11-I11 -> 0 | I11: =G11 -> 10000 | J11: 南京大学 | K11: {=ROUND(_xlfn.IFS(OR(J11="南京大学",J11="BOSS",J11="实习生",J11="人力劳务"),I11,J11="部门负责人",I11*0.6,J11="员工",I11*0.7),2)} -> 10000 | L11: {=ROUND(_xlfn.IFS(OR(J11="南京大学",J11="BOSS",J11="实习生",J11="人力劳务"),I11*0,J11="部门负责人",I11*0.4,J11="员工",I11*0.3),2)} -> 0 | M11: 无等级 | N11: {=ROUND(_xlfn.IFS(M11="A",L11*1.5,M11="B",L11*1.2,M11="C",L11*1,M11="D",L11*0.8,M11="E",L11*0.6,M11="无等级",L11*0),2)} -> 0 | O11: =ROUND(K11+N11,2) -> 10000 | P11: 0 | Q11: =ROUND(O11+P11,2) -> 10000 | R11: =O11-I11 -> 0
A12: =ROW(A12)-2 -> 10 | B12: 一十 | C12: 尚诚能源 | D12: 45870 | E12: 10000 | F12: =E12-G12 -> 0 | G12: 10000 | H12: =G12-I12 -> 0 | I12: =G12 -> 10000 | J12: 南京大学 | K12: {=ROUND(_xlfn.IFS(OR(J12="南京大学",J12="BOSS",J12="实习生",J12="人力劳务"),I12,J12="部门负责人",I12*0.6,J12="员工",I12*0.7),2)} -> 10000 | L12: {=ROUND(_xlfn.IFS(OR(J12="南京大学",J12="BOSS",J12="实习生",J12="人力劳务"),I12*0,J12="部门负责人",I12*0.4,J12="员工",I12*0.3),2)} -> 0 | M12: 无等级 | N12: {=ROUND(_xlfn.IFS(M12="A",L12*1.5,M12="B",L12*1.2,M12="C",L12*1,M12="D",L12*0.8,M12="E",L12*0.6,M12="无等级",L12*0),2)} -> 0 | O12: =ROUND(K12+N12,2) -> 10000 | P12: 0 | Q12: =ROUND(O12+P12,2) -> 10000 | R12: =O12-I12 -> 0
A13: =ROW(A13)-2 -> 11 | B13: 一十一 | C13: 尚诚能源 | D13: 45901 | E13: 10000 | F13: =E13-G13 -> 0 | G13: 10000 | H13: =G13-I13 -> 0 | I13: =G13 -> 10000 | J13: 南京大学 | K13: {=ROUND(_xlfn.IFS(OR(J13="南京大学",J13="BOSS",J13="实习生",J13="人力劳务"),I13,J13="部门负责人",I13*0.6,J13="员工",I13*0.7),2)} -> 10000 | L13: {=ROUND(_xlfn.IFS(OR(J13="南京大学",J13="BOSS",J13="实习生",J13="人力劳务"),I13*0,J13="部门负责人",I13*0.4,J13="员工",I13*0.3),2)} -> 0 | M13: 无等级 | N13: {=ROUND(_xlfn.IFS(M13="A",L13*1.5,M13="B",L13*1.2,M13="C",L13*1,M13="D",L13*0.8,M13="E",L13*0.6,M13="无等级",L13*0),2)} -> 0 | O13: =ROUND(K13+N13,2) -> 10000 | P13: 0 | Q13: =ROUND(O13+P13,2) -> 10000 | R13: =O13-I13 -> 0
A14: =ROW(A14)-2 -> 12 | B14: 一十二 | C14: 尚诚能源 | D14: 46023 | E14: 10000 | F14: =E14-G14 -> 0 | G14: 10000 | H14: =G14-I14 -> 0 | I14: =G14 -> 10000 | J14: 南京大学 | K14: {=ROUND(_xlfn.IFS(OR(J14="南京大学",J14="BOSS",J14="实习生",J14="人力劳务"),I14,J14="部门负责人",I14*0.6,J14="员工",I14*0.7),2)} -> 10000 | L14: {=ROUND(_xlfn.IFS(OR(J14="南京大学",J14="BOSS",J14="实习生",J14="人力劳务"),I14*0,J14="部门负责人",I14*0.4,J14="员工",I14*0.3),2)} -> 0 | M14: 无等级 | N14: {=ROUND(_xlfn.IFS(M14="A",L14*1.5,M14="B",L14*1.2,M14="C",L14*1,M14="D",L14*0.8,M14="E",L14*0.6,M14="无等级",L14*0),2)} -> 0 | O14: =ROUND(K14+N14,2) -> 10000 | P14: 0 | Q14: =ROUND(O14+P14,2) -> 10000 | R14: =O14-I14 -> 0
A15: =ROW(A15)-2 -> 13 | B15: 一十三 | C15: 尚诚能源 | D15: 46054 | E15: 10000 | F15: =E15-G15 -> 0 | G15: 10000 | H15: =G15-I15 -> 0 | I15: =G15 -> 10000 | J15: 南京大学 | K15: {=ROUND(_xlfn.IFS(OR(J15="南京大学",J15="BOSS",J15="实习生",J15="人力劳务"),I15,J15="部门负责人",I15*0.6,J15="员工",I15*0.7),2)} -> 10000 | L15: {=ROUND(_xlfn.IFS(OR(J15="南京大学",J15="BOSS",J15="实习生",J15="人力劳务"),I15*0,J15="部门负责人",I15*0.4,J15="员工",I15*0.3),2)} -> 0 | M15: 无等级 | N15: {=ROUND(_xlfn.IFS(M15="A",L15*1.5,M15="B",L15*1.2,M15="C",L15*1,M15="D",L15*0.8,M15="E",L15*0.6,M15="无等级",L15*0),2)} -> 0 | O15: =ROUND(K15+N15,2) -> 10000 | P15: 0 | Q15: =ROUND(O15+P15,2) -> 10000 | R15: =O15-I15 -> 0
A16: =ROW(A16)-15 -> 1 | B16: 一 | C16: 南大尚诚 | D16: 44713 | E16: 10000 | F16: =E16-G16 -> 0 | G16: 10000 | H16: =G16-I16 -> 0 | I16: =IF(G16="120元/天",_xlfn.XLOOKUP(B16,'202604考勤'!B:B,'202604考勤'!AI:AI,"无")*120,IF(S16="转正",ROUND(G16/DAY(EOMONTH(T16,0))*(DAY(EOMONTH(T16,0))-DAY(T16)+1)+(G16*0.8)/DAY(EOMONTH(T16,0))*(DAY(T16)-1),2),IF(OR(AND(S16="入职",DAY(T16)=1),AND(S16="离职",T16=EOMONTH(T16,0))),G16,IF(OR(S16="离职",S16="入职"),ROUND(G16/21.75*_xlfn.XLOOKUP(B16,'202604考勤'!B:B,'202604考勤'!AI:AI,0),2),G16)))) -> 10000 | J16: BOSS | K16: {=ROUND(_xlfn.IFS(OR(J16="南京大学",J16="BOSS",J16="实习生",J16="人力劳务"),I16,J16="部门负责人",I16*0.6,J16="员工",I16*0.7),2)} -> 10000 | L16: {=ROUND(_xlfn.IFS(OR(J16="南京大学",J16="BOSS",J16="实习生",J16="人力劳务"),I16*0,J16="部门负责人",I16*0.4,J16="员工",I16*0.3),2)} -> 0 | M16: 无等级 | N16: {=ROUND(_xlfn.IFS(M16="A",L16*1.5,M16="B",L16*1.2,M16="C",L16*1,M16="D",L16*0.8,M16="E",L16*0.6,M16="无等级",L16*0),2)} -> 0 | O16: =ROUND(K16+N16,2) -> 10000 | P16: 0 | Q16: =ROUND(O16+P16,2) -> 10000 | R16: =O16-I16 -> 0
A17: =ROW(A17)-15 -> 2 | B17: 二 | C17: 尚诚能源 | D17: 45512 | E17: 10000 | F17: =E17-G17 -> 0 | G17: 10000 | H17: =G17-I17 -> 0 | I17: =IF(G17="120元/天",_xlfn.XLOOKUP(B17,'202604考勤'!B:B,'202604考勤'!AI:AI,"无")*120,IF(S17="转正",ROUND(G17/DAY(EOMONTH(T17,0))*(DAY(EOMONTH(T17,0))-DAY(T17)+1)+(G17*0.8)/DAY(EOMONTH(T17,0))*(DAY(T17)-1),2),IF(OR(AND(S17="入职",DAY(T17)=1),AND(S17="离职",T17=EOMONTH(T17,0))),G17,IF(OR(S17="离职",S17="入职"),ROUND(G17/21.75*_xlfn.XLOOKUP(B17,'202604考勤'!B:B,'202604考勤'!AI:AI,0),2),G17)))) -> 10000 | J17: BOSS | K17: {=ROUND(_xlfn.IFS(OR(J17="南京大学",J17="BOSS",J17="实习生",J17="人力劳务"),I17,J17="部门负责人",I17*0.6,J17="员工",I17*0.7),2)} -> 10000 | L17: {=ROUND(_xlfn.IFS(OR(J17="南京大学",J17="BOSS",J17="实习生",J17="人力劳务"),I17*0,J17="部门负责人",I17*0.4,J17="员工",I17*0.3),2)} -> 0 | M17: 无等级 | N17: {=ROUND(_xlfn.IFS(M17="A",L17*1.5,M17="B",L17*1.2,M17="C",L17*1,M17="D",L17*0.8,M17="E",L17*0.6,M17="无等级",L17*0),2)} -> 0 | O17: =ROUND(K17+N17,2) -> 10000 | P17: 0 | Q17: =ROUND(O17+P17,2) -> 10000 | R17: =O17-I17 -> 0
A18: =ROW(A18)-15 -> 3 | B18: 三 | C18: 尚诚能源 | D18: 44713 | E18: 10000 | F18: =E18-G18 -> 0 | G18: 10000 | H18: =G18-I18 -> 0 | I18: =IF(G18="120元/天",_xlfn.XLOOKUP(B18,'202604考勤'!B:B,'202604考勤'!AI:AI,"无")*120,IF(S18="转正",ROUND(G18/DAY(EOMONTH(T18,0))*(DAY(EOMONTH(T18,0))-DAY(T18)+1)+(G18*0.8)/DAY(EOMONTH(T18,0))*(DAY(T18)-1),2),IF(OR(AND(S18="入职",DAY(T18)=1),AND(S18="离职",T18=EOMONTH(T18,0))),G18,IF(OR(S18="离职",S18="入职"),ROUND(G18/21.75*_xlfn.XLOOKUP(B18,'202604考勤'!B:B,'202604考勤'!AI:AI,0),2),G18)))) -> 10000 | J18: 员工 | K18: {=ROUND(_xlfn.IFS(OR(J18="南京大学",J18="BOSS",J18="实习生",J18="人力劳务"),I18,J18="部门负责人",I18*0.6,J18="员工",I18*0.7),2)} -> 7000 | L18: {=ROUND(_xlfn.IFS(OR(J18="南京大学",J18="BOSS",J18="实习生",J18="人力劳务"),I18*0,J18="部门负责人",I18*0.4,J18="员工",I18*0.3),2)} -> 3000 | M18: C | N18: {=ROUND(_xlfn.IFS(M18="A",L18*1.5,M18="B",L18*1.2,M18="C",L18*1,M18="D",L18*0.8,M18="E",L18*0.6,M18="无等级",L18*0),2)} -> 3000 | O18: =ROUND(K18+N18,2) -> 10000 | P18: 0 | Q18: =ROUND(O18+P18,2) -> 10000 | R18: =O18-I18 -> 0
A19: =ROW(A19)-15 -> 4 | B19: 四 | C19: 南大尚诚 | D19: 44713 | E19: 10000 | F19: =E19-G19 -> 0 | G19: 10000 | H19: =G19-I19 -> 0 | I19: =IF(G19="120元/天",_xlfn.XLOOKUP(B19,'202604考勤'!B:B,'202604考勤'!AI:AI,"无")*120,IF(S19="转正",ROUND(G19/DAY(EOMONTH(T19,0))*(DAY(EOMONTH(T19,0))-DAY(T19)+1)+(G19*0.8)/DAY(EOMONTH(T19,0))*(DAY(T19)-1),2),IF(OR(AND(S19="入职",DAY(T19)=1),AND(S19="离职",T19=EOMONTH(T19,0))),G19,IF(OR(S19="离职",S19="入职"),ROUND(G19/21.75*_xlfn.XLOOKUP(B19,'202604考勤'!B:B,'202604考勤'!AI:AI,0),2),G19)))) -> 10000 | J19: 部门负责人 | K19: {=ROUND(_xlfn.IFS(OR(J19="南京大学",J19="BOSS",J19="实习生",J19="人力劳务"),I19,J19="部门负责人",I19*0.6,J19="员工",I19*0.7),2)} -> 6000 | L19: {=ROUND(_xlfn.IFS(OR(J19="南京大学",J19="BOSS",J19="实习生",J19="人力劳务"),I19*0,J19="部门负责人",I19*0.4,J19="员工",I19*0.3),2)} -> 4000 | M19: C | N19: {=ROUND(_xlfn.IFS(M19="A",L19*1.5,M19="B",L19*1.2,M19="C",L19*1,M19="D",L19*0.8,M19="E",L19*0.6,M19="无等级",L19*0),2)} -> 4000 | O19: =ROUND(K19+N19,2) -> 10000 | P19: 0 | Q19: =ROUND(O19+P19,2) -> 10000 | R19: =O19-I19 -> 0
A20: =ROW(A20)-15 -> 5 | B20: 五 | C20: 南大尚诚 | D20: 44713 | E20: 10000 | F20: =E20-G20 -> 0 | G20: 10000 | H20: =G20-I20 -> 0 | I20: =IF(G20="120元/天",_xlfn.XLOOKUP(B20,'202604考勤'!B:B,'202604考勤'!AI:AI,"无")*120,IF(S20="转正",ROUND(G20/DAY(EOMONTH(T20,0))*(DAY(EOMONTH(T20,0))-DAY(T20)+1)+(G20*0.8)/DAY(EOMONTH(T20,0))*(DAY(T20)-1),2),IF(OR(AND(S20="入职",DAY(T20)=1),AND(S20="离职",T20=EOMONTH(T20,0))),G20,IF(OR(S20="离职",S20="入职"),ROUND(G20/21.75*_xlfn.XLOOKUP(B20,'202604考勤'!B:B,'202604考勤'!AI:AI,0),2),G20)))) -> 10000 | J20: 员工 | K20: {=ROUND(_xlfn.IFS(OR(J20="南京大学",J20="BOSS",J20="实习生",J20="人力劳务"),I20,J20="部门负责人",I20*0.6,J20="员工",I20*0.7),2)} -> 7000 | L20: {=ROUND(_xlfn.IFS(OR(J20="南京大学",J20="BOSS",J20="实习生",J20="人力劳务"),I20*0,J20="部门负责人",I20*0.4,J20="员工",I20*0.3),2)} -> 3000 | M20: C | N20: {=ROUND(_xlfn.IFS(M20="A",L20*1.5,M20="B",L20*1.2,M20="C",L20*1,M20="D",L20*0.8,M20="E",L20*0.6,M20="无等级",L20*0),2)} -> 3000 | O20: =ROUND(K20+N20,2) -> 10000 | P20: 0 | Q20: =ROUND(O20+P20,2) -> 10000 | R20: =O20-I20 -> 0
A21: =ROW(A21)-15 -> 6 | B21: 六 | C21: 南大尚诚 | D21: 44713 | E21: 10000 | F21: =E21-G21 -> 0 | G21: 10000 | H21: =G21-I21 -> 0 | I21: =IF(G21="120元/天",_xlfn.XLOOKUP(B21,'202604考勤'!B:B,'202604考勤'!AI:AI,"无")*120,IF(S21="转正",ROUND(G21/DAY(EOMONTH(T21,0))*(DAY(EOMONTH(T21,0))-DAY(T21)+1)+(G21*0.8)/DAY(EOMONTH(T21,0))*(DAY(T21)-1),2),IF(OR(AND(S21="入职",DAY(T21)=1),AND(S21="离职",T21=EOMONTH(T21,0))),G21,IF(OR(S21="离职",S21="入职"),ROUND(G21/21.75*_xlfn.XLOOKUP(B21,'202604考勤'!B:B,'202604考勤'!AI:AI,0),2),G21)))) -> 10000 | J21: 员工 | K21: {=ROUND(_xlfn.IFS(OR(J21="南京大学",J21="BOSS",J21="实习生",J21="人力劳务"),I21,J21="部门负责人",I21*0.6,J21="员工",I21*0.7),2)} -> 7000 | L21: {=ROUND(_xlfn.IFS(OR(J21="南京大学",J21="BOSS",J21="实习生",J21="人力劳务"),I21*0,J21="部门负责人",I21*0.4,J21="员工",I21*0.3),2)} -> 3000 | M21: C | N21: {=ROUND(_xlfn.IFS(M21="A",L21*1.5,M21="B",L21*1.2,M21="C",L21*1,M21="D",L21*0.8,M21="E",L21*0.6,M21="无等级",L21*0),2)} -> 3000 | O21: =ROUND(K21+N21,2) -> 10000 | P21: 0 | Q21: =ROUND(O21+P21,2) -> 10000 | R21: =O21-I21 -> 0
A22: =ROW(A22)-15 -> 7 | B22: 七 | C22: 南大尚诚 | D22: 44713 | E22: 10000 | F22: =E22-G22 -> 0 | G22: 10000 | H22: =G22-I22 -> 0 | I22: =IF(G22="120元/天",_xlfn.XLOOKUP(B22,'202604考勤'!B:B,'202604考勤'!AI:AI,"无")*120,IF(S22="转正",ROUND(G22/DAY(EOMONTH(T22,0))*(DAY(EOMONTH(T22,0))-DAY(T22)+1)+(G22*0.8)/DAY(EOMONTH(T22,0))*(DAY(T22)-1),2),IF(OR(AND(S22="入职",DAY(T22)=1),AND(S22="离职",T22=EOMONTH(T22,0))),G22,IF(OR(S22="离职",S22="入职"),ROUND(G22/21.75*_xlfn.XLOOKUP(B22,'202604考勤'!B:B,'202604考勤'!AI:AI,0),2),G22)))) -> 10000 | J22: 员工 | K22: {=ROUND(_xlfn.IFS(OR(J22="南京大学",J22="BOSS",J22="实习生",J22="人力劳务"),I22,J22="部门负责人",I22*0.6,J22="员工",I22*0.7),2)} -> 7000 | L22: {=ROUND(_xlfn.IFS(OR(J22="南京大学",J22="BOSS",J22="实习生",J22="人力劳务"),I22*0,J22="部门负责人",I22*0.4,J22="员工",I22*0.3),2)} -> 3000 | M22: C | N22: {=ROUND(_xlfn.IFS(M22="A",L22*1.5,M22="B",L22*1.2,M22="C",L22*1,M22="D",L22*0.8,M22="E",L22*0.6,M22="无等级",L22*0),2)} -> 3000 | O22: =ROUND(K22+N22,2) -> 10000 | P22: 0 | Q22: =ROUND(O22+P22,2) -> 10000 | R22: =O22-I22 -> 0
A23: =ROW(A23)-15 -> 8 | B23: 八 | C23: 南大尚诚 | D23: 44713 | E23: 10000 | F23: =E23-G23 -> 0 | G23: 10000 | H23: =G23-I23 -> 0 | I23: =IF(G23="120元/天",_xlfn.XLOOKUP(B23,'202604考勤'!B:B,'202604考勤'!AI:AI,"无")*120,IF(S23="转正",ROUND(G23/DAY(EOMONTH(T23,0))*(DAY(EOMONTH(T23,0))-DAY(T23)+1)+(G23*0.8)/DAY(EOMONTH(T23,0))*(DAY(T23)-1),2),IF(OR(AND(S23="入职",DAY(T23)=1),AND(S23="离职",T23=EOMONTH(T23,0))),G23,IF(OR(S23="离职",S23="入职"),ROUND(G23/21.75*_xlfn.XLOOKUP(B23,'202604考勤'!B:B,'202604考勤'!AI:AI,0),2),G23)))) -> 10000 | J23: 员工 | K23: {=ROUND(_xlfn.IFS(OR(J23="南京大学",J23="BOSS",J23="实习生",J23="人力劳务"),I23,J23="部门负责人",I23*0.6,J23="员工",I23*0.7),2)} -> 7000 | L23: {=ROUND(_xlfn.IFS(OR(J23="南京大学",J23="BOSS",J23="实习生",J23="人力劳务"),I23*0,J23="部门负责人",I23*0.4,J23="员工",I23*0.3),2)} -> 3000 | M23: C | N23: {=ROUND(_xlfn.IFS(M23="A",L23*1.5,M23="B",L23*1.2,M23="C",L23*1,M23="D",L23*0.8,M23="E",L23*0.6,M23="无等级",L23*0),2)} -> 3000 | O23: =ROUND(K23+N23,2) -> 10000 | P23: 0 | Q23: =ROUND(O23+P23,2) -> 10000 | R23: =O23-I23 -> 0
A24: =ROW(A24)-15 -> 9 | B24: 九 | C24: 南大尚诚 | D24: 44713 | E24: 10000 | F24: =E24-G24 -> 0 | G24: 10000 | H24: =G24-I24 -> 0 | I24: =IF(G24="120元/天",_xlfn.XLOOKUP(B24,'202604考勤'!B:B,'202604考勤'!AI:AI,"无")*120,IF(S24="转正",ROUND(G24/DAY(EOMONTH(T24,0))*(DAY(EOMONTH(T24,0))-DAY(T24)+1)+(G24*0.8)/DAY(EOMONTH(T24,0))*(DAY(T24)-1),2),IF(OR(AND(S24="入职",DAY(T24)=1),AND(S24="离职",T24=EOMONTH(T24,0))),G24,IF(OR(S24="离职",S24="入职"),ROUND(G24/21.75*_xlfn.XLOOKUP(B24,'202604考勤'!B:B,'202604考勤'!AI:AI,0),2),G24)))) -> 10000 | J24: 部门负责人 | K24: {=ROUND(_xlfn.IFS(OR(J24="南京大学",J24="BOSS",J24="实习生",J24="人力劳务"),I24,J24="部门负责人",I24*0.6,J24="员工",I24*0.7),2)} -> 6000 | L24: {=ROUND(_xlfn.IFS(OR(J24="南京大学",J24="BOSS",J24="实习生",J24="人力劳务"),I24*0,J24="部门负责人",I24*0.4,J24="员工",I24*0.3),2)} -> 4000 | M24: C | N24: {=ROUND(_xlfn.IFS(M24="A",L24*1.5,M24="B",L24*1.2,M24="C",L24*1,M24="D",L24*0.8,M24="E",L24*0.6,M24="无等级",L24*0),2)} -> 4000 | O24: =ROUND(K24+N24,2) -> 10000 | P24: 0 | Q24: =ROUND(O24+P24,2) -> 10000 | R24: =O24-I24 -> 0
A25: =ROW(A25)-15 -> 10 | B25: 一十 | C25: 南大尚诚 | D25: 44732 | E25: 10000 | F25: =E25-G25 -> 0 | G25: 10000 | H25: =G25-I25 -> 0 | I25: =IF(G25="120元/天",_xlfn.XLOOKUP(B25,'202604考勤'!B:B,'202604考勤'!AI:AI,"无")*120,IF(S25="转正",ROUND(G25/DAY(EOMONTH(T25,0))*(DAY(EOMONTH(T25,0))-DAY(T25)+1)+(G25*0.8)/DAY(EOMONTH(T25,0))*(DAY(T25)-1),2),IF(OR(AND(S25="入职",DAY(T25)=1),AND(S25="离职",T25=EOMONTH(T25,0))),G25,IF(OR(S25="离职",S25="入职"),ROUND(G25/21.75*_xlfn.XLOOKUP(B25,'202604考勤'!B:B,'202604考勤'!AI:AI,0),2),G25)))) -> 10000 | J25: 部门负责人 | K25: {=ROUND(_xlfn.IFS(OR(J25="南京大学",J25="BOSS",J25="实习生",J25="人力劳务"),I25,J25="部门负责人",I25*0.6,J25="员工",I25*0.7),2)} -> 6000 | L25: {=ROUND(_xlfn.IFS(OR(J25="南京大学",J25="BOSS",J25="实习生",J25="人力劳务"),I25*0,J25="部门负责人",I25*0.4,J25="员工",I25*0.3),2)} -> 4000 | M25: C | N25: {=ROUND(_xlfn.IFS(M25="A",L25*1.5,M25="B",L25*1.2,M25="C",L25*1,M25="D",L25*0.8,M25="E",L25*0.6,M25="无等级",L25*0),2)} -> 4000 | O25: =ROUND(K25+N25,2) -> 10000 | P25: 0 | Q25: =ROUND(O25+P25,2) -> 10000 | R25: =O25-I25 -> 0
A26: =ROW(A26)-15 -> 11 | B26: 一十一 | C26: 南大尚诚 | D26: 44743 | E26: 10000 | F26: =E26-G26 -> 0 | G26: 10000 | H26: =G26-I26 -> 0 | I26: =IF(G26="120元/天",_xlfn.XLOOKUP(B26,'202604考勤'!B:B,'202604考勤'!AI:AI,"无")*120,IF(S26="转正",ROUND(G26/DAY(EOMONTH(T26,0))*(DAY(EOMONTH(T26,0))-DAY(T26)+1)+(G26*0.8)/DAY(EOMONTH(T26,0))*(DAY(T26)-1),2),IF(OR(AND(S26="入职",DAY(T26)=1),AND(S26="离职",T26=EOMONTH(T26,0))),G26,IF(OR(S26="离职",S26="入职"),ROUND(G26/21.75*_xlfn.XLOOKUP(B26,'202604考勤'!B:B,'202604考勤'!AI:AI,0),2),G26)))) -> 10000 | J26: 员工 | K26: {=ROUND(_xlfn.IFS(OR(J26="南京大学",J26="BOSS",J26="实习生",J26="人力劳务"),I26,J26="部门负责人",I26*0.6,J26="员工",I26*0.7),2)} -> 7000 | L26: {=ROUND(_xlfn.IFS(OR(J26="南京大学",J26="BOSS",J26="实习生",J26="人力劳务"),I26*0,J26="部门负责人",I26*0.4,J26="员工",I26*0.3),2)} -> 3000 | M26: C | N26: {=ROUND(_xlfn.IFS(M26="A",L26*1.5,M26="B",L26*1.2,M26="C",L26*1,M26="D",L26*0.8,M26="E",L26*0.6,M26="无等级",L26*0),2)} -> 3000 | O26: =ROUND(K26+N26,2) -> 10000 | P26: 0 | Q26: =ROUND(O26+P26,2) -> 10000 | R26: =O26-I26 -> 0
A27: =ROW(A27)-15 -> 12 | B27: 一十二 | C27: 尚诚能源 | D27: 44746 | E27: 10000 | F27: =E27-G27 -> 0 | G27: 10000 | H27: =G27-I27 -> 0 | I27: =IF(G27="120元/天",_xlfn.XLOOKUP(B27,'202604考勤'!B:B,'202604考勤'!AI:AI,"无")*120,IF(S27="转正",ROUND(G27/DAY(EOMONTH(T27,0))*(DAY(EOMONTH(T27,0))-DAY(T27)+1)+(G27*0.8)/DAY(EOMONTH(T27,0))*(DAY(T27)-1),2),IF(OR(AND(S27="入职",DAY(T27)=1),AND(S27="离职",T27=EOMONTH(T27,0))),G27,IF(OR(S27="离职",S27="入职"),ROUND(G27/21.75*_xlfn.XLOOKUP(B27,'202604考勤'!B:B,'202604考勤'!AI:AI,0),2),G27)))) -> 10000 | J27: 部门负责人 | K27: {=ROUND(_xlfn.IFS(OR(J27="南京大学",J27="BOSS",J27="实习生",J27="人力劳务"),I27,J27="部门负责人",I27*0.6,J27="员工",I27*0.7),2)} -> 6000 | L27: {=ROUND(_xlfn.IFS(OR(J27="南京大学",J27="BOSS",J27="实习生",J27="人力劳务"),I27*0,J27="部门负责人",I27*0.4,J27="员工",I27*0.3),2)} -> 4000 | M27: C | N27: {=ROUND(_xlfn.IFS(M27="A",L27*1.5,M27="B",L27*1.2,M27="C",L27*1,M27="D",L27*0.8,M27="E",L27*0.6,M27="无等级",L27*0),2)} -> 4000 | O27: =ROUND(K27+N27,2) -> 10000 | P27: 0 | Q27: =ROUND(O27+P27,2) -> 10000 | R27: =O27-I27 -> 0
... A29: =ROW(A29)-15 -> 14 | B29: 一十四 | C29: 尚诚能源 | D29: 44774 | E29: 10000 | F29: =E29-G29 -> 0 | G29: 10000 | H29: =G29-I29 -> 0 | I29: =IF(G29="120元/天",_xlfn.XLOOKUP(B29,'202604考勤'!B:B,'202604考勤'!AI:AI,"无")*120,IF(S29="转正",ROUND(G29/DAY(EOMONTH(T29,0))*(DAY(EOMONTH(T29,0))-DAY(T29)+1)+(G29*0.8)/DAY(EOMONTH(T29,0))*(DAY(T29)-1),2),IF(OR(AND(S29="入职",DAY(T29)=1),AND(S29="离职",T29=EOMONTH(T29,0))),G29,IF(OR(S29="离职",S29="入职"),ROUND(G29/21.75*_xlfn.XLOOKUP(B29,'202604考勤'!B:B,'202604考勤'!AI:AI,0),2),G29)))) -> 10000 | J29: 员工 | K29: {=ROUND(_xlfn.IFS(OR(J29="南京大学",J29="BOSS",J29="实习生",J29="人力劳务"),I29,J29="部门负责人",I29*0.6,J29="员工",I29*0.7),2)} -> 7000 | L29: {=ROUND(_xlfn.IFS(OR(J29="南京大学",J29="BOSS",J29="实习生",J29="人力劳务"),I29*0,J29="部门负责人",I29*0.4,J29="员工",I29*0.3),2)} -> 3000 | M29: C | N29: {=ROUND(_xlfn.IFS(M29="A",L29*1.5,M29="B",L29*1.2,M29="C",L29*1,M29="D",L29*0.8,M29="E",L29*0.6,M29="无等级",L29*0),2)} -> 3000 | O29: =ROUND(K29+N29,2) -> 10000 | P29: 0 | Q29: =ROUND(O29+P29,2) -> 10000 | R29: =O29-I29 -> 0
A30: =ROW(A30)-15 -> 15 | B30: 一十五 | C30: 尚诚能源 | D30: 44774 | E30: 10000 | F30: =E30-G30 -> 0 | G30: 10000 | H30: =G30-I30 -> 0 | I30: =IF(G30="120元/天",_xlfn.XLOOKUP(B30,'202604考勤'!B:B,'202604考勤'!AI:AI,"无")*120,IF(S30="转正",ROUND(G30/DAY(EOMONTH(T30,0))*(DAY(EOMONTH(T30,0))-DAY(T30)+1)+(G30*0.8)/DAY(EOMONTH(T30,0))*(DAY(T30)-1),2),IF(OR(AND(S30="入职",DAY(T30)=1),AND(S30="离职",T30=EOMONTH(T30,0))),G30,IF(OR(S30="离职",S30="入职"),ROUND(G30/21.75*_xlfn.XLOOKUP(B30,'202604考勤'!B:B,'202604考勤'!AI:AI,0),2),G30)))) -> 10000 | J30: 员工 | K30: {=ROUND(_xlfn.IFS(OR(J30="南京大学",J30="BOSS",J30="实习生",J30="人力劳务"),I30,J30="部门负责人",I30*0.6,J30="员工",I30*0.7),2)} -> 7000 | L30: {=ROUND(_xlfn.IFS(OR(J30="南京大学",J30="BOSS",J30="实习生",J30="人力劳务"),I30*0,J30="部门负责人",I30*0.4,J30="员工",I30*0.3),2)} -> 3000 | M30: C | N30: {=ROUND(_xlfn.IFS(M30="A",L30*1.5,M30="B",L30*1.2,M30="C",L30*1,M30="D",L30*0.8,M30="E",L30*0.6,M30="无等级",L30*0),2)} -> 3000 | O30: =ROUND(K30+N30,2) -> 10000 | P30: =-(K30/21.75*1) -> -321.83908 | Q30: =ROUND(O30+P30,2) -> 9678.16 | R30: =O30-I30 -> 0 | S30: 事假 | T30: 1
A31: =ROW(A31)-15 -> 16 | B31: 一十六 | C31: 南大尚诚 | D31: 44774 | E31: 10000 | F31: =E31-G31 -> 0 | G31: 10000 | H31: =G31-I31 -> 0 | I31: =IF(G31="120元/天",_xlfn.XLOOKUP(B31,'202604考勤'!B:B,'202604考勤'!AI:AI,"无")*120,IF(S31="转正",ROUND(G31/DAY(EOMONTH(T31,0))*(DAY(EOMONTH(T31,0))-DAY(T31)+1)+(G31*0.8)/DAY(EOMONTH(T31,0))*(DAY(T31)-1),2),IF(OR(AND(S31="入职",DAY(T31)=1),AND(S31="离职",T31=EOMONTH(T31,0))),G31,IF(OR(S31="离职",S31="入职"),ROUND(G31/21.75*_xlfn.XLOOKUP(B31,'202604考勤'!B:B,'202604考勤'!AI:AI,0),2),G31)))) -> 10000 | J31: 员工 | K31: {=ROUND(_xlfn.IFS(OR(J31="南京大学",J31="BOSS",J31="实习生",J31="人力劳务"),I31,J31="部门负责人",I31*0.6,J31="员工",I31*0.7),2)} -> 7000 | L31: {=ROUND(_xlfn.IFS(OR(J31="南京大学",J31="BOSS",J31="实习生",J31="人力劳务"),I31*0,J31="部门负责人",I31*0.4,J31="员工",I31*0.3),2)} -> 3000 | M31: C | N31: {=ROUND(_xlfn.IFS(M31="A",L31*1.5,M31="B",L31*1.2,M31="C",L31*1,M31="D",L31*0.8,M31="E",L31*0.6,M31="无等级",L31*0),2)} -> 3000 | O31: =ROUND(K31+N31,2) -> 10000 | P31: 0 | Q31: =ROUND(O31+P31,2) -> 10000 | R31: =O31-I31 -> 0
A32: =ROW(A32)-15 -> 17 | B32: 一十七 | C32: 基石 | D32: 44774 | E32: 10000 | F32: =E32-G32 -> 0 | G32: 10000 | H32: =G32-I32 -> 0 | I32: =IF(G32="120元/天",_xlfn.XLOOKUP(B32,'202604考勤'!B:B,'202604考勤'!AI:AI,"无")*120,IF(S32="转正",ROUND(G32/DAY(EOMONTH(T32,0))*(DAY(EOMONTH(T32,0))-DAY(T32)+1)+(G32*0.8)/DAY(EOMONTH(T32,0))*(DAY(T32)-1),2),IF(OR(AND(S32="入职",DAY(T32)=1),AND(S32="离职",T32=EOMONTH(T32,0))),G32,IF(OR(S32="离职",S32="入职"),ROUND(G32/21.75*_xlfn.XLOOKUP(B32,'202604考勤'!B:B,'202604考勤'!AI:AI,0),2),G32)))) -> 10000 | J32: 部门负责人 | K32: {=ROUND(_xlfn.IFS(OR(J32="南京大学",J32="BOSS",J32="实习生",J32="人力劳务"),I32,J32="部门负责人",I32*0.6,J32="员工",I32*0.7),2)} -> 6000 | L32: {=ROUND(_xlfn.IFS(OR(J32="南京大学",J32="BOSS",J32="实习生",J32="人力劳务"),I32*0,J32="部门负责人",I32*0.4,J32="员工",I32*0.3),2)} -> 4000 | M32: C | N32: {=ROUND(_xlfn.IFS(M32="A",L32*1.5,M32="B",L32*1.2,M32="C",L32*1,M32="D",L32*0.8,M32="E",L32*0.6,M32="无等级",L32*0),2)} -> 4000 | O32: =ROUND(K32+N32,2) -> 10000 | P32: 0 | Q32: =ROUND(O32+P32,2) -> 10000 | R32: =O32-I32 -> 0
A33: =ROW(A33)-15 -> 18 | B33: 一十八 | C33: 南大尚诚 | D33: 44781 | E33: 10000 | F33: =E33-G33 -> 0 | G33: 10000 | H33: =G33-I33 -> 0 | I33: =IF(G33="120元/天",_xlfn.XLOOKUP(B33,'202604考勤'!B:B,'202604考勤'!AI:AI,"无")*120,IF(S33="转正",ROUND(G33/DAY(EOMONTH(T33,0))*(DAY(EOMONTH(T33,0))-DAY(T33)+1)+(G33*0.8)/DAY(EOMONTH(T33,0))*(DAY(T33)-1),2),IF(OR(AND(S33="入职",DAY(T33)=1),AND(S33="离职",T33=EOMONTH(T33,0))),G33,IF(OR(S33="离职",S33="入职"),ROUND(G33/21.75*_xlfn.XLOOKUP(B33,'202604考勤'!B:B,'202604考勤'!AI:AI,0),2),G33)))) -> 10000 | J33: 员工 | K33: {=ROUND(_xlfn.IFS(OR(J33="南京大学",J33="BOSS",J33="实习生",J33="人力劳务"),I33,J33="部门负责人",I33*0.6,J33="员工",I33*0.7),2)} -> 7000 | L33: {=ROUND(_xlfn.IFS(OR(J33="南京大学",J33="BOSS",J33="实习生",J33="人力劳务"),I33*0,J33="部门负责人",I33*0.4,J33="员工",I33*0.3),2)} -> 3000 | M33: C | N33: {=ROUND(_xlfn.IFS(M33="A",L33*1.5,M33="B",L33*1.2,M33="C",L33*1,M33="D",L33*0.8,M33="E",L33*0.6,M33="无等级",L33*0),2)} -> 3000 | O33: =ROUND(K33+N33,2) -> 10000 | P33: 0 | Q33: =ROUND(O33+P33,2) -> 10000 | R33: =O33-I33 -> 0
A34: =ROW(A34)-15 -> 19 | B34: 一十九 | C34: 南大尚诚 | D34: 44788 | E34: 10000 | F34: =E34-G34 -> 0 | G34: 10000 | H34: =G34-I34 -> 0 | I34: =IF(G34="120元/天",_xlfn.XLOOKUP(B34,'202604考勤'!B:B,'202604考勤'!AI:AI,"无")*120,IF(S34="转正",ROUND(G34/DAY(EOMONTH(T34,0))*(DAY(EOMONTH(T34,0))-DAY(T34)+1)+(G34*0.8)/DAY(EOMONTH(T34,0))*(DAY(T34)-1),2),IF(OR(AND(S34="入职",DAY(T34)=1),AND(S34="离职",T34=EOMONTH(T34,0))),G34,IF(OR(S34="离职",S34="入职"),ROUND(G34/21.75*_xlfn.XLOOKUP(B34,'202604考勤'!B:B,'202604考勤'!AI:AI,0),2),G34)))) -> 10000 | J34: 员工 | K34: {=ROUND(_xlfn.IFS(OR(J34="南京大学",J34="BOSS",J34="实习生",J34="人力劳务"),I34,J34="部门负责人",I34*0.6,J34="员工",I34*0.7),2)} -> 7000 | L34: {=ROUND(_xlfn.IFS(OR(J34="南京大学",J34="BOSS",J34="实习生",J34="人力劳务"),I34*0,J34="部门负责人",I34*0.4,J34="员工",I34*0.3),2)} -> 3000 | M34: C | N34: {=ROUND(_xlfn.IFS(M34="A",L34*1.5,M34="B",L34*1.2,M34="C",L34*1,M34="D",L34*0.8,M34="E",L34*0.6,M34="无等级",L34*0),2)} -> 3000 | O34: =ROUND(K34+N34,2) -> 10000 | P34: 0 | Q34: =ROUND(O34+P34,2) -> 10000 | R34: =O34-I34 -> 0
A35: =ROW(A35)-15 -> 20 | B35: 二十 | C35: 南大尚诚 | D35: 45047 | E35: 10000 | F35: =E35-G35 -> 0 | G35: 10000 | H35: =G35-I35 -> 0 | I35: =IF(G35="120元/天",_xlfn.XLOOKUP(B35,'202604考勤'!B:B,'202604考勤'!AI:AI,"无")*120,IF(S35="转正",ROUND(G35/DAY(EOMONTH(T35,0))*(DAY(EOMONTH(T35,0))-DAY(T35)+1)+(G35*0.8)/DAY(EOMONTH(T35,0))*(DAY(T35)-1),2),IF(OR(AND(S35="入职",DAY(T35)=1),AND(S35="离职",T35=EOMONTH(T35,0))),G35,IF(OR(S35="离职",S35="入职"),ROUND(G35/21.75*_xlfn.XLOOKUP(B35,'202604考勤'!B:B,'202604考勤'!AI:AI,0),2),G35)))) -> 10000 | J35: 员工 | K35: {=ROUND(_xlfn.IFS(OR(J35="南京大学",J35="BOSS",J35="实习生",J35="人力劳务"),I35,J35="部门负责人",I35*0.6,J35="员工",I35*0.7),2)} -> 7000 | L35: {=ROUND(_xlfn.IFS(OR(J35="南京大学",J35="BOSS",J35="实习生",J35="人力劳务"),I35*0,J35="部门负责人",I35*0.4,J35="员工",I35*0.3),2)} -> 3000 | M35: C | N35: {=ROUND(_xlfn.IFS(M35="A",L35*1.5,M35="B",L35*1.2,M35="C",L35*1,M35="D",L35*0.8,M35="E",L35*0.6,M35="无等级",L35*0),2)} -> 3000 | O35: =ROUND(K35+N35,2) -> 10000 | P35: 0 | Q35: =ROUND(O35+P35,2) -> 10000 | R35: =O35-I35 -> 0
A36: =ROW(A36)-15 -> 21 | B36: 二十一 | C36: 尚诚能源 | D36: 44805 | E36: 10000 | F36: =E36-G36 -> 0 | G36: 10000 | H36: =G36-I36 -> 0 | I36: =IF(G36="120元/天",_xlfn.XLOOKUP(B36,'202604考勤'!B:B,'202604考勤'!AI:AI,"无")*120,IF(S36="转正",ROUND(G36/DAY(EOMONTH(T36,0))*(DAY(EOMONTH(T36,0))-DAY(T36)+1)+(G36*0.8)/DAY(EOMONTH(T36,0))*(DAY(T36)-1),2),IF(OR(AND(S36="入职",DAY(T36)=1),AND(S36="离职",T36=EOMONTH(T36,0))),G36,IF(OR(S36="离职",S36="入职"),ROUND(G36/21.75*_xlfn.XLOOKUP(B36,'202604考勤'!B:B,'202604考勤'!AI:AI,0),2),G36)))) -> 10000 | J36: 员工 | K36: {=ROUND(_xlfn.IFS(OR(J36="南京大学",J36="BOSS",J36="实习生",J36="人力劳务"),I36,J36="部门负责人",I36*0.6,J36="员工",I36*0.7),2)} -> 7000 | L36: {=ROUND(_xlfn.IFS(OR(J36="南京大学",J36="BOSS",J36="实习生",J36="人力劳务"),I36*0,J36="部门负责人",I36*0.4,J36="员工",I36*0.3),2)} -> 3000 | M36: C | N36: {=ROUND(_xlfn.IFS(M36="A",L36*1.5,M36="B",L36*1.2,M36="C",L36*1,M36="D",L36*0.8,M36="E",L36*0.6,M36="无等级",L36*0),2)} -> 3000 | O36: =ROUND(K36+N36,2) -> 10000 | P36: 0 | Q36: =ROUND(O36+P36,2) -> 10000 | R36: =O36-I36 -> 0
A37: =ROW(A37)-15 -> 22 | B37: 二十二 | C37: 南大尚诚 | D37: 44805 | E37: 10000 | F37: =E37-G37 -> 0 | G37: 10000 | H37: =G37-I37 -> 0 | I37: =IF(G37="120元/天",_xlfn.XLOOKUP(B37,'202604考勤'!B:B,'202604考勤'!AI:AI,"无")*120,IF(S37="转正",ROUND(G37/DAY(EOMONTH(T37,0))*(DAY(EOMONTH(T37,0))-DAY(T37)+1)+(G37*0.8)/DAY(EOMONTH(T37,0))*(DAY(T37)-1),2),IF(OR(AND(S37="入职",DAY(T37)=1),AND(S37="离职",T37=EOMONTH(T37,0))),G37,IF(OR(S37="离职",S37="入职"),ROUND(G37/21.75*_xlfn.XLOOKUP(B37,'202604考勤'!B:B,'202604考勤'!AI:AI,0),2),G37)))) -> 10000 | J37: 员工 | K37: {=ROUND(_xlfn.IFS(OR(J37="南京大学",J37="BOSS",J37="实习生",J37="人力劳务"),I37,J37="部门负责人",I37*0.6,J37="员工",I37*0.7),2)} -> 7000 | L37: {=ROUND(_xlfn.IFS(OR(J37="南京大学",J37="BOSS",J37="实习生",J37="人力劳务"),I37*0,J37="部门负责人",I37*0.4,J37="员工",I37*0.3),2)} -> 3000 | M37: C | N37: {=ROUND(_xlfn.IFS(M37="A",L37*1.5,M37="B",L37*1.2,M37="C",L37*1,M37="D",L37*0.8,M37="E",L37*0.6,M37="无等级",L37*0),2)} -> 3000 | O37: =ROUND(K37+N37,2) -> 10000 | P37: 0 | Q37: =ROUND(O37+P37,2) -> 10000 | R37: =O37-I37 -> 0
A38: =ROW(A38)-15 -> 23 | B38: 二十三 | C38: 南大尚诚 | D38: 44811 | E38: 10000 | F38: =E38-G38 -> 0 | G38: 10000 | H38: =G38-I38 -> 0 | I38: =IF(G38="120元/天",_xlfn.XLOOKUP(B38,'202604考勤'!B:B,'202604考勤'!AI:AI,"无")*120,IF(S38="转正",ROUND(G38/DAY(EOMONTH(T38,0))*(DAY(EOMONTH(T38,0))-DAY(T38)+1)+(G38*0.8)/DAY(EOMONTH(T38,0))*(DAY(T38)-1),2),IF(OR(AND(S38="入职",DAY(T38)=1),AND(S38="离职",T38=EOMONTH(T38,0))),G38,IF(OR(S38="离职",S38="入职"),ROUND(G38/21.75*_xlfn.XLOOKUP(B38,'202604考勤'!B:B,'202604考勤'!AI:AI,0),2),G38)))) -> 10000 | J38: 员工 | K38: {=ROUND(_xlfn.IFS(OR(J38="南京大学",J38="BOSS",J38="实习生",J38="人力劳务"),I38,J38="部门负责人",I38*0.6,J38="员工",I38*0.7),2)} -> 7000 | L38: {=ROUND(_xlfn.IFS(OR(J38="南京大学",J38="BOSS",J38="实习生",J38="人力劳务"),I38*0,J38="部门负责人",I38*0.4,J38="员工",I38*0.3),2)} -> 3000 | M38: C | N38: {=ROUND(_xlfn.IFS(M38="A",L38*1.5,M38="B",L38*1.2,M38="C",L38*1,M38="D",L38*0.8,M38="E",L38*0.6,M38="无等级",L38*0),2)} -> 3000 | O38: =ROUND(K38+N38,2) -> 10000 | P38: 0 | Q38: =ROUND(O38+P38,2) -> 10000 | R38: =O38-I38 -> 0
A39: =ROW(A39)-15 -> 24 | B39: 二十四 | C39: 南大尚诚 | D39: 44817 | E39: 10000 | F39: =E39-G39 -> 0 | G39: 10000 | H39: =G39-I39 -> 0 | I39: =IF(G39="120元/天",_xlfn.XLOOKUP(B39,'202604考勤'!B:B,'202604考勤'!AI:AI,"无")*120,IF(S39="转正",ROUND(G39/DAY(EOMONTH(T39,0))*(DAY(EOMONTH(T39,0))-DAY(T39)+1)+(G39*0.8)/DAY(EOMONTH(T39,0))*(DAY(T39)-1),2),IF(OR(AND(S39="入职",DAY(T39)=1),AND(S39="离职",T39=EOMONTH(T39,0))),G39,IF(OR(S39="离职",S39="入职"),ROUND(G39/21.75*_xlfn.XLOOKUP(B39,'202604考勤'!B:B,'202604考勤'!AI:AI,0),2),G39)))) -> 10000 | J39: 员工 | K39: {=ROUND(_xlfn.IFS(OR(J39="南京大学",J39="BOSS",J39="实习生",J39="人力劳务"),I39,J39="部门负责人",I39*0.6,J39="员工",I39*0.7),2)} -> 7000 | L39: {=ROUND(_xlfn.IFS(OR(J39="南京大学",J39="BOSS",J39="实习生",J39="人力劳务"),I39*0,J39="部门负责人",I39*0.4,J39="员工",I39*0.3),2)} -> 3000 | M39: C | N39: {=ROUND(_xlfn.IFS(M39="A",L39*1.5,M39="B",L39*1.2,M39="C",L39*1,M39="D",L39*0.8,M39="E",L39*0.6,M39="无等级",L39*0),2)} -> 3000 | O39: =ROUND(K39+N39,2) -> 10000 | P39: 0 | Q39: =ROUND(O39+P39,2) -> 10000 | R39: =O39-I39 -> 0
A40: =ROW(A40)-15 -> 25 | B40: 二十五 | C40: 南大尚诚 | D40: 44823 | E40: 10000 | F40: =E40-G40 -> 0 | G40: 10000 | H40: =G40-I40 -> 0 | I40: =IF(G40="120元/天",_xlfn.XLOOKUP(B40,'202604考勤'!B:B,'202604考勤'!AI:AI,"无")*120,IF(S40="转正",ROUND(G40/DAY(EOMONTH(T40,0))*(DAY(EOMONTH(T40,0))-DAY(T40)+1)+(G40*0.8)/DAY(EOMONTH(T40,0))*(DAY(T40)-1),2),IF(OR(AND(S40="入职",DAY(T40)=1),AND(S40="离职",T40=EOMONTH(T40,0))),G40,IF(OR(S40="离职",S40="入职"),ROUND(G40/21.75*_xlfn.XLOOKUP(B40,'202604考勤'!B:B,'202604考勤'!AI:AI,0),2),G40)))) -> 10000 | J40: 员工 | K40: {=ROUND(_xlfn.IFS(OR(J40="南京大学",J40="BOSS",J40="实习生",J40="人力劳务"),I40,J40="部门负责人",I40*0.6,J40="员工",I40*0.7),2)} -> 7000 | L40: {=ROUND(_xlfn.IFS(OR(J40="南京大学",J40="BOSS",J40="实习生",J40="人力劳务"),I40*0,J40="部门负责人",I40*0.4,J40="员工",I40*0.3),2)} -> 3000 | M40: B | N40: {=ROUND(_xlfn.IFS(M40="A",L40*1.5,M40="B",L40*1.2,M40="C",L40*1,M40="D",L40*0.8,M40="E",L40*0.6,M40="无等级",L40*0),2)} -> 3600 | O40: =ROUND(K40+N40,2) -> 10600 | P40: 0 | Q40: =ROUND(O40+P40,2) -> 10600 | R40: =O40-I40 -> 600
A41: =ROW(A41)-15 -> 26 | B41: 二十六 | C41: 南大尚诚 | D41: 44823 | E41: 10000 | F41: =E41-G41 -> 0 | G41: 10000 | H41: =G41-I41 -> 0 | I41: =IF(G41="120元/天",_xlfn.XLOOKUP(B41,'202604考勤'!B:B,'202604考勤'!AI:AI,"无")*120,IF(S41="转正",ROUND(G41/DAY(EOMONTH(T41,0))*(DAY(EOMONTH(T41,0))-DAY(T41)+1)+(G41*0.8)/DAY(EOMONTH(T41,0))*(DAY(T41)-1),2),IF(OR(AND(S41="入职",DAY(T41)=1),AND(S41="离职",T41=EOMONTH(T41,0))),G41,IF(OR(S41="离职",S41="入职"),ROUND(G41/21.75*_xlfn.XLOOKUP(B41,'202604考勤'!B:B,'202604考勤'!AI:AI,0),2),G41)))) -> 10000 | J41: 员工 | K41: {=ROUND(_xlfn.IFS(OR(J41="南京大学",J41="BOSS",J41="实习生",J41="人力劳务"),I41,J41="部门负责人",I41*0.6,J41="员工",I41*0.7),2)} -> 7000 | L41: {=ROUND(_xlfn.IFS(OR(J41="南京大学",J41="BOSS",J41="实习生",J41="人力劳务"),I41*0,J41="部门负责人",I41*0.4,J41="员工",I41*0.3),2)} -> 3000 | M41: C | N41: {=ROUND(_xlfn.IFS(M41="A",L41*1.5,M41="B",L41*1.2,M41="C",L41*1,M41="D",L41*0.8,M41="E",L41*0.6,M41="无等级",L41*0),2)} -> 3000 | O41: =ROUND(K41+N41,2) -> 10000 | P41: 0 | Q41: =ROUND(O41+P41,2) -> 10000 | R41: =O41-I41 -> 0
A42: =ROW(A42)-15 -> 27 | B42: 二十七 | C42: 南大尚诚 | D42: 44835 | E42: 10000 | F42: =E42-G42 -> 0 | G42: 10000 | H42: =G42-I42 -> 0 | I42: =IF(G42="120元/天",_xlfn.XLOOKUP(B42,'202604考勤'!B:B,'202604考勤'!AI:AI,"无")*120,IF(S42="转正",ROUND(G42/DAY(EOMONTH(T42,0))*(DAY(EOMONTH(T42,0))-DAY(T42)+1)+(G42*0.8)/DAY(EOMONTH(T42,0))*(DAY(T42)-1),2),IF(OR(AND(S42="入职",DAY(T42)=1),AND(S42="离职",T42=EOMONTH(T42,0))),G42,IF(OR(S42="离职",S42="入职"),ROUND(G42/21.75*_xlfn.XLOOKUP(B42,'202604考勤'!B:B,'202604考勤'!AI:AI,0),2),G42)))) -> 10000 | J42: 员工 | K42: {=ROUND(_xlfn.IFS(OR(J42="南京大学",J42="BOSS",J42="实习生",J42="人力劳务"),I42,J42="部门负责人",I42*0.6,J42="员工",I42*0.7),2)} -> 7000 | L42: {=ROUND(_xlfn.IFS(OR(J42="南京大学",J42="BOSS",J42="实习生",J42="人力劳务"),I42*0,J42="部门负责人",I42*0.4,J42="员工",I42*0.3),2)} -> 3000 | M42: C | N42: {=ROUND(_xlfn.IFS(M42="A",L42*1.5,M42="B",L42*1.2,M42="C",L42*1,M42="D",L42*0.8,M42="E",L42*0.6,M42="无等级",L42*0),2)} -> 3000 | O42: =ROUND(K42+N42,2) -> 10000 | P42: 0 | Q42: =ROUND(O42+P42,2) -> 10000 | R42: =O42-I42 -> 0
... A90: =ROW(A90)-15 -> 75 | B90: 七十五 | C90: 南大尚诚 | D90: 45524 | E90: 10000 | F90: =E90-G90 -> 0 | G90: 10000 | H90: =G90-I90 -> 0 | I90: =IF(G90="120元/天",_xlfn.XLOOKUP(B90,'202604考勤'!B:B,'202604考勤'!AI:AI,"无")*120,IF(S90="转正",ROUND(G90/DAY(EOMONTH(T90,0))*(DAY(EOMONTH(T90,0))-DAY(T90)+1)+(G90*0.8)/DAY(EOMONTH(T90,0))*(DAY(T90)-1),2),IF(OR(AND(S90="入职",DAY(T90)=1),AND(S90="离职",T90=EOMONTH(T90,0))),G90,IF(OR(S90="离职",S90="入职"),ROUND(G90/21.75*_xlfn.XLOOKUP(B90,'202604考勤'!B:B,'202604考勤'!AI:AI,0),2),G90)))) -> 10000 | J90: 员工 | K90: {=ROUND(_xlfn.IFS(OR(J90="南京大学",J90="BOSS",J90="实习生",J90="人力劳务"),I90,J90="部门负责人",I90*0.6,J90="员工",I90*0.7),2)} -> 7000 | L90: {=ROUND(_xlfn.IFS(OR(J90="南京大学",J90="BOSS",J90="实习生",J90="人力劳务"),I90*0,J90="部门负责人",I90*0.4,J90="员工",I90*0.3),2)} -> 3000 | M90: C | N90: {=ROUND(_xlfn.IFS(M90="A",L90*1.5,M90="B",L90*1.2,M90="C",L90*1,M90="D",L90*0.8,M90="E",L90*0.6,M90="无等级",L90*0),2)} -> 3000 | O90: =ROUND(K90+N90,2) -> 10000 | P90: 0 | Q90: =ROUND(O90+P90,2) -> 10000 | R90: =O90-I90 -> 0
A91: =ROW(A91)-15 -> 76 | B91: 七十六 | C91: 南大尚诚 | D91: 45537 | E91: 10000 | F91: =E91-G91 -> 0 | G91: 10000 | H91: =G91-I91 -> 0 | I91: =IF(G91="120元/天",_xlfn.XLOOKUP(B91,'202604考勤'!B:B,'202604考勤'!AI:AI,"无")*120,IF(S91="转正",ROUND(G91/DAY(EOMONTH(T91,0))*(DAY(EOMONTH(T91,0))-DAY(T91)+1)+(G91*0.8)/DAY(EOMONTH(T91,0))*(DAY(T91)-1),2),IF(OR(AND(S91="入职",DAY(T91)=1),AND(S91="离职",T91=EOMONTH(T91,0))),G91,IF(OR(S91="离职",S91="入职"),ROUND(G91/21.75*_xlfn.XLOOKUP(B91,'202604考勤'!B:B,'202604考勤'!AI:AI,0),2),G91)))) -> 10000 | J91: 员工 | K91: {=ROUND(_xlfn.IFS(OR(J91="南京大学",J91="BOSS",J91="实习生",J91="人力劳务"),I91,J91="部门负责人",I91*0.6,J91="员工",I91*0.7),2)} -> 7000 | L91: {=ROUND(_xlfn.IFS(OR(J91="南京大学",J91="BOSS",J91="实习生",J91="人力劳务"),I91*0,J91="部门负责人",I91*0.4,J91="员工",I91*0.3),2)} -> 3000 | M91: C | N91: {=ROUND(_xlfn.IFS(M91="A",L91*1.5,M91="B",L91*1.2,M91="C",L91*1,M91="D",L91*0.8,M91="E",L91*0.6,M91="无等级",L91*0),2)} -> 3000 | O91: =ROUND(K91+N91,2) -> 10000 | P91: =ROUND(I91/21.75*5,2) -> 2298.85 | Q91: =ROUND(O91+P91,2) -> 12298.85 | R91: =O91-I91 -> 0 | S91: 离职 | T91: 46142
A92: =ROW(A92)-15 -> 77 | B92: 七十七 | C92: 南大尚诚 | D92: 45537 | E92: 10000 | F92: =E92-G92 -> 0 | G92: 10000 | H92: =G92-I92 -> 0 | I92: =IF(G92="120元/天",_xlfn.XLOOKUP(B92,'202604考勤'!B:B,'202604考勤'!AI:AI,"无")*120,IF(S92="转正",ROUND(G92/DAY(EOMONTH(T92,0))*(DAY(EOMONTH(T92,0))-DAY(T92)+1)+(G92*0.8)/DAY(EOMONTH(T92,0))*(DAY(T92)-1),2),IF(OR(AND(S92="入职",DAY(T92)=1),AND(S92="离职",T92=EOMONTH(T92,0))),G92,IF(OR(S92="离职",S92="入职"),ROUND(G92/21.75*_xlfn.XLOOKUP(B92,'202604考勤'!B:B,'202604考勤'!AI:AI,0),2),G92)))) -> 10000 | J92: 员工 | K92: {=ROUND(_xlfn.IFS(OR(J92="南京大学",J92="BOSS",J92="实习生",J92="人力劳务"),I92,J92="部门负责人",I92*0.6,J92="员工",I92*0.7),2)} -> 7000 | L92: {=ROUND(_xlfn.IFS(OR(J92="南京大学",J92="BOSS",J92="实习生",J92="人力劳务"),I92*0,J92="部门负责人",I92*0.4,J92="员工",I92*0.3),2)} -> 3000 | M92: C | N92: {=ROUND(_xlfn.IFS(M92="A",L92*1.5,M92="B",L92*1.2,M92="C",L92*1,M92="D",L92*0.8,M92="E",L92*0.6,M92="无等级",L92*0),2)} -> 3000 | O92: =ROUND(K92+N92,2) -> 10000 | P92: 0 | Q92: =ROUND(O92+P92,2) -> 10000 | R92: =O92-I92 -> 0
A93: =ROW(A93)-15 -> 78 | B93: 七十八 | C93: 南大尚诚 | D93: 45554 | E93: 10000 | F93: =E93-G93 -> 0 | G93: 10000 | H93: =G93-I93 -> 0 | I93: =IF(G93="120元/天",_xlfn.XLOOKUP(B93,'202604考勤'!B:B,'202604考勤'!AI:AI,"无")*120,IF(S93="转正",ROUND(G93/DAY(EOMONTH(T93,0))*(DAY(EOMONTH(T93,0))-DAY(T93)+1)+(G93*0.8)/DAY(EOMONTH(T93,0))*(DAY(T93)-1),2),IF(OR(AND(S93="入职",DAY(T93)=1),AND(S93="离职",T93=EOMONTH(T93,0))),G93,IF(OR(S93="离职",S93="入职"),ROUND(G93/21.75*_xlfn.XLOOKUP(B93,'202604考勤'!B:B,'202604考勤'!AI:AI,0),2),G93)))) -> 10000 | J93: 员工 | K93: {=ROUND(_xlfn.IFS(OR(J93="南京大学",J93="BOSS",J93="实习生",J93="人力劳务"),I93,J93="部门负责人",I93*0.6,J93="员工",I93*0.7),2)} -> 7000 | L93: {=ROUND(_xlfn.IFS(OR(J93="南京大学",J93="BOSS",J93="实习生",J93="人力劳务"),I93*0,J93="部门负责人",I93*0.4,J93="员工",I93*0.3),2)} -> 3000 | M93: C | N93: {=ROUND(_xlfn.IFS(M93="A",L93*1.5,M93="B",L93*1.2,M93="C",L93*1,M93="D",L93*0.8,M93="E",L93*0.6,M93="无等级",L93*0),2)} -> 3000 | O93: =ROUND(K93+N93,2) -> 10000 | P93: 0 | Q93: =ROUND(O93+P93,2) -> 10000 | R93: =O93-I93 -> 0
A94: =ROW(A94)-15 -> 79 | B94: 七十九 | C94: 南大尚诚 | D94: 45579 | E94: 10000 | F94: =E94-G94 -> 0 | G94: 10000 | H94: =G94-I94 -> 0 | I94: =IF(G94="120元/天",_xlfn.XLOOKUP(B94,'202604考勤'!B:B,'202604考勤'!AI:AI,"无")*120,IF(S94="转正",ROUND(G94/DAY(EOMONTH(T94,0))*(DAY(EOMONTH(T94,0))-DAY(T94)+1)+(G94*0.8)/DAY(EOMONTH(T94,0))*(DAY(T94)-1),2),IF(OR(AND(S94="入职",DAY(T94)=1),AND(S94="离职",T94=EOMONTH(T94,0))),G94,IF(OR(S94="离职",S94="入职"),ROUND(G94/21.75*_xlfn.XLOOKUP(B94,'202604考勤'!B:B,'202604考勤'!AI:AI,0),2),G94)))) -> 10000 | J94: 员工 | K94: {=ROUND(_xlfn.IFS(OR(J94="南京大学",J94="BOSS",J94="实习生",J94="人力劳务"),I94,J94="部门负责人",I94*0.6,J94="员工",I94*0.7),2)} -> 7000 | L94: {=ROUND(_xlfn.IFS(OR(J94="南京大学",J94="BOSS",J94="实习生",J94="人力劳务"),I94*0,J94="部门负责人",I94*0.4,J94="员工",I94*0.3),2)} -> 3000 | M94: C | N94: {=ROUND(_xlfn.IFS(M94="A",L94*1.5,M94="B",L94*1.2,M94="C",L94*1,M94="D",L94*0.8,M94="E",L94*0.6,M94="无等级",L94*0),2)} -> 3000 | O94: =ROUND(K94+N94,2) -> 10000 | P94: 0 | Q94: =ROUND(O94+P94,2) -> 10000 | R94: =O94-I94 -> 0
A95: =ROW(A95)-15 -> 80 | B95: 八十 | C95: 南大尚诚 | D95: 45597 | E95: 10000 | F95: =E95-G95 -> 0 | G95: 10000 | H95: =G95-I95 -> 0 | I95: =IF(G95="120元/天",_xlfn.XLOOKUP(B95,'202604考勤'!B:B,'202604考勤'!AI:AI,"无")*120,IF(S95="转正",ROUND(G95/DAY(EOMONTH(T95,0))*(DAY(EOMONTH(T95,0))-DAY(T95)+1)+(G95*0.8)/DAY(EOMONTH(T95,0))*(DAY(T95)-1),2),IF(OR(AND(S95="入职",DAY(T95)=1),AND(S95="离职",T95=EOMONTH(T95,0))),G95,IF(OR(S95="离职",S95="入职"),ROUND(G95/21.75*_xlfn.XLOOKUP(B95,'202604考勤'!B:B,'202604考勤'!AI:AI,0),2),G95)))) -> 10000 | J95: 员工 | K95: {=ROUND(_xlfn.IFS(OR(J95="南京大学",J95="BOSS",J95="实习生",J95="人力劳务"),I95,J95="部门负责人",I95*0.6,J95="员工",I95*0.7),2)} -> 7000 | L95: {=ROUND(_xlfn.IFS(OR(J95="南京大学",J95="BOSS",J95="实习生",J95="人力劳务"),I95*0,J95="部门负责人",I95*0.4,J95="员工",I95*0.3),2)} -> 3000 | M95: C | N95: {=ROUND(_xlfn.IFS(M95="A",L95*1.5,M95="B",L95*1.2,M95="C",L95*1,M95="D",L95*0.8,M95="E",L95*0.6,M95="无等级",L95*0),2)} -> 3000 | O95: =ROUND(K95+N95,2) -> 10000 | P95: 0 | Q95: =ROUND(O95+P95,2) -> 10000 | R95: =O95-I95 -> 0
A96: =ROW(A96)-15 -> 81 | B96: 八十一 | C96: 南大尚诚 | D96: 45600 | E96: 10000 | F96: =E96-G96 -> 0 | G96: 10000 | H96: =G96-I96 -> 0 | I96: =IF(G96="120元/天",_xlfn.XLOOKUP(B96,'202604考勤'!B:B,'202604考勤'!AI:AI,"无")*120,IF(S96="转正",ROUND(G96/DAY(EOMONTH(T96,0))*(DAY(EOMONTH(T96,0))-DAY(T96)+1)+(G96*0.8)/DAY(EOMONTH(T96,0))*(DAY(T96)-1),2),IF(OR(AND(S96="入职",DAY(T96)=1),AND(S96="离职",T96=EOMONTH(T96,0))),G96,IF(OR(S96="离职",S96="入职"),ROUND(G96/21.75*_xlfn.XLOOKUP(B96,'202604考勤'!B:B,'202604考勤'!AI:AI,0),2),G96)))) -> 10000 | J96: 员工 | K96: {=ROUND(_xlfn.IFS(OR(J96="南京大学",J96="BOSS",J96="实习生",J96="人力劳务"),I96,J96="部门负责人",I96*0.6,J96="员工",I96*0.7),2)} -> 7000 | L96: {=ROUND(_xlfn.IFS(OR(J96="南京大学",J96="BOSS",J96="实习生",J96="人力劳务"),I96*0,J96="部门负责人",I96*0.4,J96="员工",I96*0.3),2)} -> 3000 | M96: C | N96: {=ROUND(_xlfn.IFS(M96="A",L96*1.5,M96="B",L96*1.2,M96="C",L96*1,M96="D",L96*0.8,M96="E",L96*0.6,M96="无等级",L96*0),2)} -> 3000 | O96: =ROUND(K96+N96,2) -> 10000 | P96: 0 | Q96: =ROUND(O96+P96,2) -> 10000 | R96: =O96-I96 -> 0
A97: =ROW(A97)-15 -> 82 | B97: 八十二 | C97: 南大尚诚 | D97: 45607 | E97: 10000 | F97: =E97-G97 -> 0 | G97: 10000 | H97: =G97-I97 -> 0 | I97: =IF(G97="120元/天",_xlfn.XLOOKUP(B97,'202604考勤'!B:B,'202604考勤'!AI:AI,"无")*120,IF(S97="转正",ROUND(G97/DAY(EOMONTH(T97,0))*(DAY(EOMONTH(T97,0))-DAY(T97)+1)+(G97*0.8)/DAY(EOMONTH(T97,0))*(DAY(T97)-1),2),IF(OR(AND(S97="入职",DAY(T97)=1),AND(S97="离职",T97=EOMONTH(T97,0))),G97,IF(OR(S97="离职",S97="入职"),ROUND(G97/21.75*_xlfn.XLOOKUP(B97,'202604考勤'!B:B,'202604考勤'!AI:AI,0),2),G97)))) -> 10000 | J97: 员工 | K97: {=ROUND(_xlfn.IFS(OR(J97="南京大学",J97="BOSS",J97="实习生",J97="人力劳务"),I97,J97="部门负责人",I97*0.6,J97="员工",I97*0.7),2)} -> 7000 | L97: {=ROUND(_xlfn.IFS(OR(J97="南京大学",J97="BOSS",J97="实习生",J97="人力劳务"),I97*0,J97="部门负责人",I97*0.4,J97="员工",I97*0.3),2)} -> 3000 | M97: C | N97: {=ROUND(_xlfn.IFS(M97="A",L97*1.5,M97="B",L97*1.2,M97="C",L97*1,M97="D",L97*0.8,M97="E",L97*0.6,M97="无等级",L97*0),2)} -> 3000 | O97: =ROUND(K97+N97,2) -> 10000 | P97: 0 | Q97: =ROUND(O97+P97,2) -> 10000 | R97: =O97-I97 -> 0
A98: =ROW(A98)-15 -> 83 | B98: 八十三 | C98: 尚诚能源 | D98: 45607 | E98: 10000 | F98: =E98-G98 -> 0 | G98: 10000 | H98: =G98-I98 -> 0 | I98: =IF(G98="120元/天",_xlfn.XLOOKUP(B98,'202604考勤'!B:B,'202604考勤'!AI:AI,"无")*120,IF(S98="转正",ROUND(G98/DAY(EOMONTH(T98,0))*(DAY(EOMONTH(T98,0))-DAY(T98)+1)+(G98*0.8)/DAY(EOMONTH(T98,0))*(DAY(T98)-1),2),IF(OR(AND(S98="入职",DAY(T98)=1),AND(S98="离职",T98=EOMONTH(T98,0))),G98,IF(OR(S98="离职",S98="入职"),ROUND(G98/21.75*_xlfn.XLOOKUP(B98,'202604考勤'!B:B,'202604考勤'!AI:AI,0),2),G98)))) -> 10000 | J98: 员工 | K98: {=ROUND(_xlfn.IFS(OR(J98="南京大学",J98="BOSS",J98="实习生",J98="人力劳务"),I98,J98="部门负责人",I98*0.6,J98="员工",I98*0.7),2)} -> 7000 | L98: {=ROUND(_xlfn.IFS(OR(J98="南京大学",J98="BOSS",J98="实习生",J98="人力劳务"),I98*0,J98="部门负责人",I98*0.4,J98="员工",I98*0.3),2)} -> 3000 | M98: C | N98: {=ROUND(_xlfn.IFS(M98="A",L98*1.5,M98="B",L98*1.2,M98="C",L98*1,M98="D",L98*0.8,M98="E",L98*0.6,M98="无等级",L98*0),2)} -> 3000 | O98: =ROUND(K98+N98,2) -> 10000 | P98: =-(K98/21.75*0.5) -> -160.91954 | Q98: =ROUND(O98+P98,2) -> 9839.08 | R98: =O98-I98 -> 0 | S98: 事假 | T98: 0.5
A99: =ROW(A99)-15 -> 84 | B99: 八十四 | C99: 南大尚诚 | D99: 45628 | E99: 10000 | F99: =E99-G99 -> 0 | G99: 10000 | H99: =G99-I99 -> 0 | I99: =IF(G99="120元/天",_xlfn.XLOOKUP(B99,'202604考勤'!B:B,'202604考勤'!AI:AI,"无")*120,IF(S99="转正",ROUND(G99/DAY(EOMONTH(T99,0))*(DAY(EOMONTH(T99,0))-DAY(T99)+1)+(G99*0.8)/DAY(EOMONTH(T99,0))*(DAY(T99)-1),2),IF(OR(AND(S99="入职",DAY(T99)=1),AND(S99="离职",T99=EOMONTH(T99,0))),G99,IF(OR(S99="离职",S99="入职"),ROUND(G99/21.75*_xlfn.XLOOKUP(B99,'202604考勤'!B:B,'202604考勤'!AI:AI,0),2),G99)))) -> 10000 | J99: 员工 | K99: {=ROUND(_xlfn.IFS(OR(J99="南京大学",J99="BOSS",J99="实习生",J99="人力劳务"),I99,J99="部门负责人",I99*0.6,J99="员工",I99*0.7),2)} -> 7000 | L99: {=ROUND(_xlfn.IFS(OR(J99="南京大学",J99="BOSS",J99="实习生",J99="人力劳务"),I99*0,J99="部门负责人",I99*0.4,J99="员工",I99*0.3),2)} -> 3000 | M99: C | N99: {=ROUND(_xlfn.IFS(M99="A",L99*1.5,M99="B",L99*1.2,M99="C",L99*1,M99="D",L99*0.8,M99="E",L99*0.6,M99="无等级",L99*0),2)} -> 3000 | O99: =ROUND(K99+N99,2) -> 10000 | P99: 0 | Q99: =ROUND(O99+P99,2) -> 10000 | R99: =O99-I99 -> 0
A100: =ROW(A100)-15 -> 85 | B100: 八十五 | C100: 尚诚能源 | D100: 45629 | E100: 10000 | F100: =E100-G100 -> 0 | G100: 10000 | H100: =G100-I100 -> 0 | I100: =IF(G100="120元/天",_xlfn.XLOOKUP(B100,'202604考勤'!B:B,'202604考勤'!AI:AI,"无")*120,IF(S100="转正",ROUND(G100/DAY(EOMONTH(T100,0))*(DAY(EOMONTH(T100,0))-DAY(T100)+1)+(G100*0.8)/DAY(EOMONTH(T100,0))*(DAY(T100)-1),2),IF(OR(AND(S100="入职",DAY(T100)=1),AND(S100="离职",T100=EOMONTH(T100,0))),G100,IF(OR(S100="离职",S100="入职"),ROUND(G100/21.75*_xlfn.XLOOKUP(B100,'202604考勤'!B:B,'202604考勤'!AI:AI,0),2),G100)))) -> 10000 | J100: 员工 | K100: {=ROUND(_xlfn.IFS(OR(J100="南京大学",J100="BOSS",J100="实习生",J100="人力劳务"),I100,J100="部门负责人",I100*0.6,J100="员工",I100*0.7),2)} -> 7000 | L100: {=ROUND(_xlfn.IFS(OR(J100="南京大学",J100="BOSS",J100="实习生",J100="人力劳务"),I100*0,J100="部门负责人",I100*0.4,J100="员工",I100*0.3),2)} -> 3000 | M100: C | N100: {=ROUND(_xlfn.IFS(M100="A",L100*1.5,M100="B",L100*1.2,M100="C",L100*1,M100="D",L100*0.8,M100="E",L100*0.6,M100="无等级",L100*0),2)} -> 3000 | O100: =ROUND(K100+N100,2) -> 10000 | P100: 0 | Q100: =ROUND(O100+P100,2) -> 10000 | R100: =O100-I100 -> 0
A101: =ROW(A101)-15 -> 86 | B101: 八十六 | C101: 南大尚诚 | D101: 45642 | E101: 10000 | F101: =E101-G101 -> 0 | G101: 10000 | H101: =G101-I101 -> 0 | I101: =IF(G101="120元/天",_xlfn.XLOOKUP(B101,'202604考勤'!B:B,'202604考勤'!AI:AI,"无")*120,IF(S101="转正",ROUND(G101/DAY(EOMONTH(T101,0))*(DAY(EOMONTH(T101,0))-DAY(T101)+1)+(G101*0.8)/DAY(EOMONTH(T101,0))*(DAY(T101)-1),2),IF(OR(AND(S101="入职",DAY(T101)=1),AND(S101="离职",T101=EOMONTH(T101,0))),G101,IF(OR(S101="离职",S101="入职"),ROUND(G101/21.75*_xlfn.XLOOKUP(B101,'202604考勤'!B:B,'202604考勤'!AI:AI,0),2),G101)))) -> 10000 | J101: 员工 | K101: {=ROUND(_xlfn.IFS(OR(J101="南京大学",J101="BOSS",J101="实习生",J101="人力劳务"),I101,J101="部门负责人",I101*0.6,J101="员工",I101*0.7),2)} -> 7000 | L101: {=ROUND(_xlfn.IFS(OR(J101="南京大学",J101="BOSS",J101="实习生",J101="人力劳务"),I101*0,J101="部门负责人",I101*0.4,J101="员工",I101*0.3),2)} -> 3000 | M101: C | N101: {=ROUND(_xlfn.IFS(M101="A",L101*1.5,M101="B",L101*1.2,M101="C",L101*1,M101="D",L101*0.8,M101="E",L101*0.6,M101="无等级",L101*0),2)} -> 3000 | O101: =ROUND(K101+N101,2) -> 10000 | P101: 0 | Q101: =ROUND(O101+P101,2) -> 10000 | R101: =O101-I101 -> 0
A102: =ROW(A102)-15 -> 87 | B102: 八十七 | C102: 南大尚诚 | D102: 45659 | E102: 10000 | F102: =E102-G102 -> 0 | G102: 10000 | H102: =G102-I102 -> 0 | I102: =IF(G102="120元/天",_xlfn.XLOOKUP(B102,'202604考勤'!B:B,'202604考勤'!AI:AI,"无")*120,IF(S102="转正",ROUND(G102/DAY(EOMONTH(T102,0))*(DAY(EOMONTH(T102,0))-DAY(T102)+1)+(G102*0.8)/DAY(EOMONTH(T102,0))*(DAY(T102)-1),2),IF(OR(AND(S102="入职",DAY(T102)=1),AND(S102="离职",T102=EOMONTH(T102,0))),G102,IF(OR(S102="离职",S102="入职"),ROUND(G102/21.75*_xlfn.XLOOKUP(B102,'202604考勤'!B:B,'202604考勤'!AI:AI,0),2),G102)))) -> 10000 | J102: 员工 | K102: {=ROUND(_xlfn.IFS(OR(J102="南京大学",J102="BOSS",J102="实习生",J102="人力劳务"),I102,J102="部门负责人",I102*0.6,J102="员工",I102*0.7),2)} -> 7000 | L102: {=ROUND(_xlfn.IFS(OR(J102="南京大学",J102="BOSS",J102="实习生",J102="人力劳务"),I102*0,J102="部门负责人",I102*0.4,J102="员工",I102*0.3),2)} -> 3000 | M102: C | N102: {=ROUND(_xlfn.IFS(M102="A",L102*1.5,M102="B",L102*1.2,M102="C",L102*1,M102="D",L102*0.8,M102="E",L102*0.6,M102="无等级",L102*0),2)} -> 3000 | O102: =ROUND(K102+N102,2) -> 10000 | P102: 0 | Q102: =ROUND(O102+P102,2) -> 10000 | R102: =O102-I102 -> 0
A103: =ROW(A103)-15 -> 88 | B103: 八十八 | C103: 南大尚诚 | D103: 45663 | E103: 10000 | F103: =E103-G103 -> 0 | G103: 10000 | H103: =G103-I103 -> 0 | I103: =IF(G103="120元/天",_xlfn.XLOOKUP(B103,'202604考勤'!B:B,'202604考勤'!AI:AI,"无")*120,IF(S103="转正",ROUND(G103/DAY(EOMONTH(T103,0))*(DAY(EOMONTH(T103,0))-DAY(T103)+1)+(G103*0.8)/DAY(EOMONTH(T103,0))*(DAY(T103)-1),2),IF(OR(AND(S103="入职",DAY(T103)=1),AND(S103="离职",T103=EOMONTH(T103,0))),G103,IF(OR(S103="离职",S103="入职"),ROUND(G103/21.75*_xlfn.XLOOKUP(B103,'202604考勤'!B:B,'202604考勤'!AI:AI,0),2),G103)))) -> 10000 | J103: 部门负责人 | K103: {=ROUND(_xlfn.IFS(OR(J103="南京大学",J103="BOSS",J103="实习生",J103="人力劳务"),I103,J103="部门负责人",I103*0.6,J103="员工",I103*0.7),2)} -> 6000 | L103: {=ROUND(_xlfn.IFS(OR(J103="南京大学",J103="BOSS",J103="实习生",J103="人力劳务"),I103*0,J103="部门负责人",I103*0.4,J103="员工",I103*0.3),2)} -> 4000 | M103: C | N103: {=ROUND(_xlfn.IFS(M103="A",L103*1.5,M103="B",L103*1.2,M103="C",L103*1,M103="D",L103*0.8,M103="E",L103*0.6,M103="无等级",L103*0),2)} -> 4000 | O103: =ROUND(K103+N103,2) -> 10000 | P103: 0 | Q103: =ROUND(O103+P103,2) -> 10000 | R103: =O103-I103 -> 0
A104: =ROW(A104)-15 -> 89 | B104: 八十九 | C104: 基石 | D104: 45666 | E104: 10000 | F104: =E104-G104 -> 0 | G104: 10000 | H104: =G104-I104 -> 0 | I104: =IF(G104="120元/天",_xlfn.XLOOKUP(B104,'202604考勤'!B:B,'202604考勤'!AI:AI,"无")*120,IF(S104="转正",ROUND(G104/DAY(EOMONTH(T104,0))*(DAY(EOMONTH(T104,0))-DAY(T104)+1)+(G104*0.8)/DAY(EOMONTH(T104,0))*(DAY(T104)-1),2),IF(OR(AND(S104="入职",DAY(T104)=1),AND(S104="离职",T104=EOMONTH(T104,0))),G104,IF(OR(S104="离职",S104="入职"),ROUND(G104/21.75*_xlfn.XLOOKUP(B104,'202604考勤'!B:B,'202604考勤'!AI:AI,0),2),G104)))) -> 10000 | J104: 员工 | K104: {=ROUND(_xlfn.IFS(OR(J104="南京大学",J104="BOSS",J104="实习生",J104="人力劳务"),I104,J104="部门负责人",I104*0.6,J104="员工",I104*0.7),2)} -> 7000 | L104: {=ROUND(_xlfn.IFS(OR(J104="南京大学",J104="BOSS",J104="实习生",J104="人力劳务"),I104*0,J104="部门负责人",I104*0.4,J104="员工",I104*0.3),2)} -> 3000 | M104: C | N104: {=ROUND(_xlfn.IFS(M104="A",L104*1.5,M104="B",L104*1.2,M104="C",L104*1,M104="D",L104*0.8,M104="E",L104*0.6,M104="无等级",L104*0),2)} -> 3000 | O104: =ROUND(K104+N104,2) -> 10000 | P104: 0 | Q104: =ROUND(O104+P104,2) -> 10000 | R104: =O104-I104 -> 0
A105: =ROW(A105)-15 -> 90 | B105: 九十 | C105: 南大尚诚 | D105: 45726 | E105: 10000 | F105: =E105-G105 -> 0 | G105: 10000 | H105: =G105-I105 -> 0 | I105: =IF(G105="120元/天",_xlfn.XLOOKUP(B105,'202604考勤'!B:B,'202604考勤'!AI:AI,"无")*120,IF(S105="转正",ROUND(G105/DAY(EOMONTH(T105,0))*(DAY(EOMONTH(T105,0))-DAY(T105)+1)+(G105*0.8)/DAY(EOMONTH(T105,0))*(DAY(T105)-1),2),IF(OR(AND(S105="入职",DAY(T105)=1),AND(S105="离职",T105=EOMONTH(T105,0))),G105,IF(OR(S105="离职",S105="入职"),ROUND(G105/21.75*_xlfn.XLOOKUP(B105,'202604考勤'!B:B,'202604考勤'!AI:AI,0),2),G105)))) -> 10000 | J105: 员工 | K105: {=ROUND(_xlfn.IFS(OR(J105="南京大学",J105="BOSS",J105="实习生",J105="人力劳务"),I105,J105="部门负责人",I105*0.6,J105="员工",I105*0.7),2)} -> 7000 | L105: {=ROUND(_xlfn.IFS(OR(J105="南京大学",J105="BOSS",J105="实习生",J105="人力劳务"),I105*0,J105="部门负责人",I105*0.4,J105="员工",I105*0.3),2)} -> 3000 | M105: C | N105: {=ROUND(_xlfn.IFS(M105="A",L105*1.5,M105="B",L105*1.2,M105="C",L105*1,M105="D",L105*0.8,M105="E",L105*0.6,M105="无等级",L105*0),2)} -> 3000 | O105: =ROUND(K105+N105,2) -> 10000 | P105: 0 | Q105: =ROUND(O105+P105,2) -> 10000 | R105: =O105-I105 -> 0
A106: =ROW(A106)-15 -> 91 | B106: 九十一 | C106: 南大尚诚 | D106: 45726 | E106: 10000 | F106: =E106-G106 -> 0 | G106: 10000 | H106: =G106-I106 -> 0 | I106: =IF(G106="120元/天",_xlfn.XLOOKUP(B106,'202604考勤'!B:B,'202604考勤'!AI:AI,"无")*120,IF(S106="转正",ROUND(G106/DAY(EOMONTH(T106,0))*(DAY(EOMONTH(T106,0))-DAY(T106)+1)+(G106*0.8)/DAY(EOMONTH(T106,0))*(DAY(T106)-1),2),IF(OR(AND(S106="入职",DAY(T106)=1),AND(S106="离职",T106=EOMONTH(T106,0))),G106,IF(OR(S106="离职",S106="入职"),ROUND(G106/21.75*_xlfn.XLOOKUP(B106,'202604考勤'!B:B,'202604考勤'!AI:AI,0),2),G106)))) -> 10000 | J106: 员工 | K106: {=ROUND(_xlfn.IFS(OR(J106="南京大学",J106="BOSS",J106="实习生",J106="人力劳务"),I106,J106="部门负责人",I106*0.6,J106="员工",I106*0.7),2)} -> 7000 | L106: {=ROUND(_xlfn.IFS(OR(J106="南京大学",J106="BOSS",J106="实习生",J106="人力劳务"),I106*0,J106="部门负责人",I106*0.4,J106="员工",I106*0.3),2)} -> 3000 | M106: C | N106: {=ROUND(_xlfn.IFS(M106="A",L106*1.5,M106="B",L106*1.2,M106="C",L106*1,M106="D",L106*0.8,M106="E",L106*0.6,M106="无等级",L106*0),2)} -> 3000 | O106: =ROUND(K106+N106,2) -> 10000 | P106: 0 | Q106: =ROUND(O106+P106,2) -> 10000 | R106: =O106-I106 -> 0
A107: =ROW(A107)-15 -> 92 | B107: 九十二 | C107: 尚诚能源 | D107: 2025/3/17 | E107: 10000 | F107: =E107-G107 -> 0 | G107: 10000 | H107: =G107-I107 -> 0 | I107: =IF(G107="120元/天",_xlfn.XLOOKUP(B107,'202604考勤'!B:B,'202604考勤'!AI:AI,"无")*120,IF(S107="转正",ROUND(G107/DAY(EOMONTH(T107,0))*(DAY(EOMONTH(T107,0))-DAY(T107)+1)+(G107*0.8)/DAY(EOMONTH(T107,0))*(DAY(T107)-1),2),IF(OR(AND(S107="入职",DAY(T107)=1),AND(S107="离职",T107=EOMONTH(T107,0))),G107,IF(OR(S107="离职",S107="入职"),ROUND(G107/21.75*_xlfn.XLOOKUP(B107,'202604考勤'!B:B,'202604考勤'!AI:AI,0),2),G107)))) -> 10000 | J107: 员工 | K107: {=ROUND(_xlfn.IFS(OR(J107="南京大学",J107="BOSS",J107="实习生",J107="人力劳务"),I107,J107="部门负责人",I107*0.6,J107="员工",I107*0.7),2)} -> 7000 | L107: {=ROUND(_xlfn.IFS(OR(J107="南京大学",J107="BOSS",J107="实习生",J107="人力劳务"),I107*0,J107="部门负责人",I107*0.4,J107="员工",I107*0.3),2)} -> 3000 | M107: C | N107: {=ROUND(_xlfn.IFS(M107="A",L107*1.5,M107="B",L107*1.2,M107="C",L107*1,M107="D",L107*0.8,M107="E",L107*0.6,M107="无等级",L107*0),2)} -> 3000 | O107: =ROUND(K107+N107,2) -> 10000 | P107: 0 | Q107: =ROUND(O107+P107,2) -> 10000 | R107: =O107-I107 -> 0
A108: =ROW(A108)-15 -> 93 | B108: 九十三 | C108: 南大尚诚 | D108: 45735 | E108: 10000 | F108: =E108-G108 -> 0 | G108: 10000 | H108: =G108-I108 -> 0 | I108: =IF(G108="120元/天",_xlfn.XLOOKUP(B108,'202604考勤'!B:B,'202604考勤'!AI:AI,"无")*120,IF(S108="转正",ROUND(G108/DAY(EOMONTH(T108,0))*(DAY(EOMONTH(T108,0))-DAY(T108)+1)+(G108*0.8)/DAY(EOMONTH(T108,0))*(DAY(T108)-1),2),IF(OR(AND(S108="入职",DAY(T108)=1),AND(S108="离职",T108=EOMONTH(T108,0))),G108,IF(OR(S108="离职",S108="入职"),ROUND(G108/21.75*_xlfn.XLOOKUP(B108,'202604考勤'!B:B,'202604考勤'!AI:AI,0),2),G108)))) -> 10000 | J108: 员工 | K108: {=ROUND(_xlfn.IFS(OR(J108="南京大学",J108="BOSS",J108="实习生",J108="人力劳务"),I108,J108="部门负责人",I108*0.6,J108="员工",I108*0.7),2)} -> 7000 | L108: {=ROUND(_xlfn.IFS(OR(J108="南京大学",J108="BOSS",J108="实习生",J108="人力劳务"),I108*0,J108="部门负责人",I108*0.4,J108="员工",I108*0.3),2)} -> 3000 | M108: D | N108: {=ROUND(_xlfn.IFS(M108="A",L108*1.5,M108="B",L108*1.2,M108="C",L108*1,M108="D",L108*0.8,M108="E",L108*0.6,M108="无等级",L108*0),2)} -> 2400 | O108: =ROUND(K108+N108,2) -> 9400 | P108: 0 | Q108: =ROUND(O108+P108,2) -> 9400 | R108: =O108-I108 -> -600
A109: =ROW(A109)-15 -> 94 | B109: 九十四 | C109: 南大尚诚 | D109: 45735 | E109: 10000 | F109: =E109-G109 -> 0 | G109: 10000 | H109: =G109-I109 -> 0 | I109: =IF(G109="120元/天",_xlfn.XLOOKUP(B109,'202604考勤'!B:B,'202604考勤'!AI:AI,"无")*120,IF(S109="转正",ROUND(G109/DAY(EOMONTH(T109,0))*(DAY(EOMONTH(T109,0))-DAY(T109)+1)+(G109*0.8)/DAY(EOMONTH(T109,0))*(DAY(T109)-1),2),IF(OR(AND(S109="入职",DAY(T109)=1),AND(S109="离职",T109=EOMONTH(T109,0))),G109,IF(OR(S109="离职",S109="入职"),ROUND(G109/21.75*_xlfn.XLOOKUP(B109,'202604考勤'!B:B,'202604考勤'!AI:AI,0),2),G109)))) -> 10000 | J109: 员工 | K109: {=ROUND(_xlfn.IFS(OR(J109="南京大学",J109="BOSS",J109="实习生",J109="人力劳务"),I109,J109="部门负责人",I109*0.6,J109="员工",I109*0.7),2)} -> 7000 | L109: {=ROUND(_xlfn.IFS(OR(J109="南京大学",J109="BOSS",J109="实习生",J109="人力劳务"),I109*0,J109="部门负责人",I109*0.4,J109="员工",I109*0.3),2)} -> 3000 | M109: C | N109: {=ROUND(_xlfn.IFS(M109="A",L109*1.5,M109="B",L109*1.2,M109="C",L109*1,M109="D",L109*0.8,M109="E",L109*0.6,M109="无等级",L109*0),2)} -> 3000 | O109: =ROUND(K109+N109,2) -> 10000 | P109: 0 | Q109: =ROUND(O109+P109,2) -> 10000 | R109: =O109-I109 -> 0
A110: =ROW(A110)-15 -> 95 | B110: 九十五 | C110: 南大尚诚 | D110: 45735 | E110: 10000 | F110: =E110-G110 -> 0 | G110: 10000 | H110: =G110-I110 -> 0 | I110: =IF(G110="120元/天",_xlfn.XLOOKUP(B110,'202604考勤'!B:B,'202604考勤'!AI:AI,"无")*120,IF(S110="转正",ROUND(G110/DAY(EOMONTH(T110,0))*(DAY(EOMONTH(T110,0))-DAY(T110)+1)+(G110*0.8)/DAY(EOMONTH(T110,0))*(DAY(T110)-1),2),IF(OR(AND(S110="入职",DAY(T110)=1),AND(S110="离职",T110=EOMONTH(T110,0))),G110,IF(OR(S110="离职",S110="入职"),ROUND(G110/21.75*_xlfn.XLOOKUP(B110,'202604考勤'!B:B,'202604考勤'!AI:AI,0),2),G110)))) -> 10000 | J110: 员工 | K110: {=ROUND(_xlfn.IFS(OR(J110="南京大学",J110="BOSS",J110="实习生",J110="人力劳务"),I110,J110="部门负责人",I110*0.6,J110="员工",I110*0.7),2)} -> 7000 | L110: {=ROUND(_xlfn.IFS(OR(J110="南京大学",J110="BOSS",J110="实习生",J110="人力劳务"),I110*0,J110="部门负责人",I110*0.4,J110="员工",I110*0.3),2)} -> 3000 | M110: C | N110: {=ROUND(_xlfn.IFS(M110="A",L110*1.5,M110="B",L110*1.2,M110="C",L110*1,M110="D",L110*0.8,M110="E",L110*0.6,M110="无等级",L110*0),2)} -> 3000 | O110: =ROUND(K110+N110,2) -> 10000 | P110: 0 | Q110: =ROUND(O110+P110,2) -> 10000 | R110: =O110-I110 -> 0
A111: =ROW(A111)-15 -> 96 | B111: 九十六 | C111: 南大尚诚 | D111: 45748 | E111: 10000 | F111: =E111-G111 -> 0 | G111: 10000 | H111: =G111-I111 -> 0 | I111: =IF(G111="120元/天",_xlfn.XLOOKUP(B111,'202604考勤'!B:B,'202604考勤'!AI:AI,"无")*120,IF(S111="转正",ROUND(G111/DAY(EOMONTH(T111,0))*(DAY(EOMONTH(T111,0))-DAY(T111)+1)+(G111*0.8)/DAY(EOMONTH(T111,0))*(DAY(T111)-1),2),IF(OR(AND(S111="入职",DAY(T111)=1),AND(S111="离职",T111=EOMONTH(T111,0))),G111,IF(OR(S111="离职",S111="入职"),ROUND(G111/21.75*_xlfn.XLOOKUP(B111,'202604考勤'!B:B,'202604考勤'!AI:AI,0),2),G111)))) -> 10000 | J111: 员工 | K111: {=ROUND(_xlfn.IFS(OR(J111="南京大学",J111="BOSS",J111="实习生",J111="人力劳务"),I111,J111="部门负责人",I111*0.6,J111="员工",I111*0.7),2)} -> 7000 | L111: {=ROUND(_xlfn.IFS(OR(J111="南京大学",J111="BOSS",J111="实习生",J111="人力劳务"),I111*0,J111="部门负责人",I111*0.4,J111="员工",I111*0.3),2)} -> 3000 | M111: C | N111: {=ROUND(_xlfn.IFS(M111="A",L111*1.5,M111="B",L111*1.2,M111="C",L111*1,M111="D",L111*0.8,M111="E",L111*0.6,M111="无等级",L111*0),2)} -> 3000 | O111: =ROUND(K111+N111,2) -> 10000 | P111: 0 | Q111: =ROUND(O111+P111,2) -> 10000 | R111: =O111-I111 -> 0
A112: =ROW(A112)-15 -> 97 | B112: 九十七 | C112: 尚诚能源 | D112: 45774 | E112: 10000 | F112: =E112-G112 -> 0 | G112: 10000 | H112: =G112-I112 -> 0 | I112: =IF(G112="120元/天",_xlfn.XLOOKUP(B112,'202604考勤'!B:B,'202604考勤'!AI:AI,"无")*120,IF(S112="转正",ROUND(G112/DAY(EOMONTH(T112,0))*(DAY(EOMONTH(T112,0))-DAY(T112)+1)+(G112*0.8)/DAY(EOMONTH(T112,0))*(DAY(T112)-1),2),IF(OR(AND(S112="入职",DAY(T112)=1),AND(S112="离职",T112=EOMONTH(T112,0))),G112,IF(OR(S112="离职",S112="入职"),ROUND(G112/21.75*_xlfn.XLOOKUP(B112,'202604考勤'!B:B,'202604考勤'!AI:AI,0),2),G112)))) -> 10000 | J112: 员工 | K112: {=ROUND(_xlfn.IFS(OR(J112="南京大学",J112="BOSS",J112="实习生",J112="人力劳务"),I112,J112="部门负责人",I112*0.6,J112="员工",I112*0.7),2)} -> 7000 | L112: {=ROUND(_xlfn.IFS(OR(J112="南京大学",J112="BOSS",J112="实习生",J112="人力劳务"),I112*0,J112="部门负责人",I112*0.4,J112="员工",I112*0.3),2)} -> 3000 | M112: C | N112: {=ROUND(_xlfn.IFS(M112="A",L112*1.5,M112="B",L112*1.2,M112="C",L112*1,M112="D",L112*0.8,M112="E",L112*0.6,M112="无等级",L112*0),2)} -> 3000 | O112: =ROUND(K112+N112,2) -> 10000 | P112: 0 | Q112: =ROUND(O112+P112,2) -> 10000 | R112: =O112-I112 -> 0
A113: =ROW(A113)-15 -> 98 | B113: 九十八 | C113: 南大尚诚 | D113: 45783 | E113: 10000 | F113: =E113-G113 -> 0 | G113: 10000 | H113: =G113-I113 -> 0 | I113: =IF(G113="120元/天",_xlfn.XLOOKUP(B113,'202604考勤'!B:B,'202604考勤'!AI:AI,"无")*120,IF(S113="转正",ROUND(G113/DAY(EOMONTH(T113,0))*(DAY(EOMONTH(T113,0))-DAY(T113)+1)+(G113*0.8)/DAY(EOMONTH(T113,0))*(DAY(T113)-1),2),IF(OR(AND(S113="入职",DAY(T113)=1),AND(S113="离职",T113=EOMONTH(T113,0))),G113,IF(OR(S113="离职",S113="入职"),ROUND(G113/21.75*_xlfn.XLOOKUP(B113,'202604考勤'!B:B,'202604考勤'!AI:AI,0),2),G113)))) -> 10000 | J113: 员工 | K113: {=ROUND(_xlfn.IFS(OR(J113="南京大学",J113="BOSS",J113="实习生",J113="人力劳务"),I113,J113="部门负责人",I113*0.6,J113="员工",I113*0.7),2)} -> 7000 | L113: {=ROUND(_xlfn.IFS(OR(J113="南京大学",J113="BOSS",J113="实习生",J113="人力劳务"),I113*0,J113="部门负责人",I113*0.4,J113="员工",I113*0.3),2)} -> 3000 | M113: C | N113: {=ROUND(_xlfn.IFS(M113="A",L113*1.5,M113="B",L113*1.2,M113="C",L113*1,M113="D",L113*0.8,M113="E",L113*0.6,M113="无等级",L113*0),2)} -> 3000 | O113: =ROUND(K113+N113,2) -> 10000 | P113: 0 | Q113: =ROUND(O113+P113,2) -> 10000 | R113: =O113-I113 -> 0
A114: =ROW(A114)-15 -> 99 | B114: 九十九 | C114: 南大尚诚 | D114: 45783 | E114: 10000 | F114: =E114-G114 -> 0 | G114: 10000 | H114: =G114-I114 -> 0 | I114: =IF(G114="120元/天",_xlfn.XLOOKUP(B114,'202604考勤'!B:B,'202604考勤'!AI:AI,"无")*120,IF(S114="转正",ROUND(G114/DAY(EOMONTH(T114,0))*(DAY(EOMONTH(T114,0))-DAY(T114)+1)+(G114*0.8)/DAY(EOMONTH(T114,0))*(DAY(T114)-1),2),IF(OR(AND(S114="入职",DAY(T114)=1),AND(S114="离职",T114=EOMONTH(T114,0))),G114,IF(OR(S114="离职",S114="入职"),ROUND(G114/21.75*_xlfn.XLOOKUP(B114,'202604考勤'!B:B,'202604考勤'!AI:AI,0),2),G114)))) -> 10000 | J114: 员工 | K114: {=ROUND(_xlfn.IFS(OR(J114="南京大学",J114="BOSS",J114="实习生",J114="人力劳务"),I114,J114="部门负责人",I114*0.6,J114="员工",I114*0.7),2)} -> 7000 | L114: {=ROUND(_xlfn.IFS(OR(J114="南京大学",J114="BOSS",J114="实习生",J114="人力劳务"),I114*0,J114="部门负责人",I114*0.4,J114="员工",I114*0.3),2)} -> 3000 | M114: C | N114: {=ROUND(_xlfn.IFS(M114="A",L114*1.5,M114="B",L114*1.2,M114="C",L114*1,M114="D",L114*0.8,M114="E",L114*0.6,M114="无等级",L114*0),2)} -> 3000 | O114: =ROUND(K114+N114,2) -> 10000 | P114: 0 | Q114: =ROUND(O114+P114,2) -> 10000 | R114: =O114-I114 -> 0
A115: =ROW(A115)-15 -> 100 | B115: 一百 | C115: 南大尚诚 | D115: 45784 | E115: 10000 | F115: =E115-G115 -> 0 | G115: 10000 | H115: =G115-I115 -> 0 | I115: =IF(G115="120元/天",_xlfn.XLOOKUP(B115,'202604考勤'!B:B,'202604考勤'!AI:AI,"无")*120,IF(S115="转正",ROUND(G115/DAY(EOMONTH(T115,0))*(DAY(EOMONTH(T115,0))-DAY(T115)+1)+(G115*0.8)/DAY(EOMONTH(T115,0))*(DAY(T115)-1),2),IF(OR(AND(S115="入职",DAY(T115)=1),AND(S115="离职",T115=EOMONTH(T115,0))),G115,IF(OR(S115="离职",S115="入职"),ROUND(G115/21.75*_xlfn.XLOOKUP(B115,'202604考勤'!B:B,'202604考勤'!AI:AI,0),2),G115)))) -> 10000 | J115: 员工 | K115: {=ROUND(_xlfn.IFS(OR(J115="南京大学",J115="BOSS",J115="实习生",J115="人力劳务"),I115,J115="部门负责人",I115*0.6,J115="员工",I115*0.7),2)} -> 7000 | L115: {=ROUND(_xlfn.IFS(OR(J115="南京大学",J115="BOSS",J115="实习生",J115="人力劳务"),I115*0,J115="部门负责人",I115*0.4,J115="员工",I115*0.3),2)} -> 3000 | M115: C | N115: {=ROUND(_xlfn.IFS(M115="A",L115*1.5,M115="B",L115*1.2,M115="C",L115*1,M115="D",L115*0.8,M115="E",L115*0.6,M115="无等级",L115*0),2)} -> 3000 | O115: =ROUND(K115+N115,2) -> 10000 | P115: 0 | Q115: =ROUND(O115+P115,2) -> 10000 | R115: =O115-I115 -> 0
A116: =ROW(A116)-15 -> 101 | B116: 一百〇一 | C116: 南大尚诚 | D116: 45789 | E116: 10000 | F116: =E116-G116 -> 0 | G116: 10000 | H116: =G116-I116 -> 0 | I116: =IF(G116="120元/天",_xlfn.XLOOKUP(B116,'202604考勤'!B:B,'202604考勤'!AI:AI,"无")*120,IF(S116="转正",ROUND(G116/DAY(EOMONTH(T116,0))*(DAY(EOMONTH(T116,0))-DAY(T116)+1)+(G116*0.8)/DAY(EOMONTH(T116,0))*(DAY(T116)-1),2),IF(OR(AND(S116="入职",DAY(T116)=1),AND(S116="离职",T116=EOMONTH(T116,0))),G116,IF(OR(S116="离职",S116="入职"),ROUND(G116/21.75*_xlfn.XLOOKUP(B116,'202604考勤'!B:B,'202604考勤'!AI:AI,0),2),G116)))) -> 10000 | J116: 员工 | K116: {=ROUND(_xlfn.IFS(OR(J116="南京大学",J116="BOSS",J116="实习生",J116="人力劳务"),I116,J116="部门负责人",I116*0.6,J116="员工",I116*0.7),2)} -> 7000 | L116: {=ROUND(_xlfn.IFS(OR(J116="南京大学",J116="BOSS",J116="实习生",J116="人力劳务"),I116*0,J116="部门负责人",I116*0.4,J116="员工",I116*0.3),2)} -> 3000 | M116: D | N116: {=ROUND(_xlfn.IFS(M116="A",L116*1.5,M116="B",L116*1.2,M116="C",L116*1,M116="D",L116*0.8,M116="E",L116*0.6,M116="无等级",L116*0),2)} -> 2400 | O116: =ROUND(K116+N116,2) -> 9400 | P116: 0 | Q116: =ROUND(O116+P116,2) -> 9400 | R116: =O116-I116 -> -600
A117: =ROW(A117)-15 -> 102 | B117: 一百〇二 | C117: 南大尚诚 | D117: 45797 | E117: 10000 | F117: =E117-G117 -> 0 | G117: 10000 | H117: =G117-I117 -> 0 | I117: =IF(G117="120元/天",_xlfn.XLOOKUP(B117,'202604考勤'!B:B,'202604考勤'!AI:AI,"无")*120,IF(S117="转正",ROUND(G117/DAY(EOMONTH(T117,0))*(DAY(EOMONTH(T117,0))-DAY(T117)+1)+(G117*0.8)/DAY(EOMONTH(T117,0))*(DAY(T117)-1),2),IF(OR(AND(S117="入职",DAY(T117)=1),AND(S117="离职",T117=EOMONTH(T117,0))),G117,IF(OR(S117="离职",S117="入职"),ROUND(G117/21.75*_xlfn.XLOOKUP(B117,'202604考勤'!B:B,'202604考勤'!AI:AI,0),2),G117)))) -> 10000 | J117: 员工 | K117: {=ROUND(_xlfn.IFS(OR(J117="南京大学",J117="BOSS",J117="实习生",J117="人力劳务"),I117,J117="部门负责人",I117*0.6,J117="员工",I117*0.7),2)} -> 7000 | L117: {=ROUND(_xlfn.IFS(OR(J117="南京大学",J117="BOSS",J117="实习生",J117="人力劳务"),I117*0,J117="部门负责人",I117*0.4,J117="员工",I117*0.3),2)} -> 3000 | M117: C | N117: {=ROUND(_xlfn.IFS(M117="A",L117*1.5,M117="B",L117*1.2,M117="C",L117*1,M117="D",L117*0.8,M117="E",L117*0.6,M117="无等级",L117*0),2)} -> 3000 | O117: =ROUND(K117+N117,2) -> 10000 | P117: 0 | Q117: =ROUND(O117+P117,2) -> 10000 | R117: =O117-I117 -> 0
A118: =ROW(A118)-15 -> 103 | B118: 一百〇三 | C118: 南大尚诚 | D118: 45798 | E118: 10000 | F118: =E118-G118 -> 0 | G118: 10000 | H118: =G118-I118 -> 0 | I118: =IF(G118="120元/天",_xlfn.XLOOKUP(B118,'202604考勤'!B:B,'202604考勤'!AI:AI,"无")*120,IF(S118="转正",ROUND(G118/DAY(EOMONTH(T118,0))*(DAY(EOMONTH(T118,0))-DAY(T118)+1)+(G118*0.8)/DAY(EOMONTH(T118,0))*(DAY(T118)-1),2),IF(OR(AND(S118="入职",DAY(T118)=1),AND(S118="离职",T118=EOMONTH(T118,0))),G118,IF(OR(S118="离职",S118="入职"),ROUND(G118/21.75*_xlfn.XLOOKUP(B118,'202604考勤'!B:B,'202604考勤'!AI:AI,0),2),G118)))) -> 10000 | J118: 员工 | K118: {=ROUND(_xlfn.IFS(OR(J118="南京大学",J118="BOSS",J118="实习生",J118="人力劳务"),I118,J118="部门负责人",I118*0.6,J118="员工",I118*0.7),2)} -> 7000 | L118: {=ROUND(_xlfn.IFS(OR(J118="南京大学",J118="BOSS",J118="实习生",J118="人力劳务"),I118*0,J118="部门负责人",I118*0.4,J118="员工",I118*0.3),2)} -> 3000 | M118: C | N118: {=ROUND(_xlfn.IFS(M118="A",L118*1.5,M118="B",L118*1.2,M118="C",L118*1,M118="D",L118*0.8,M118="E",L118*0.6,M118="无等级",L118*0),2)} -> 3000 | O118: =ROUND(K118+N118,2) -> 10000 | P118: 0 | Q118: =ROUND(O118+P118,2) -> 10000 | R118: =O118-I118 -> 0
A119: =ROW(A119)-15 -> 104 | B119: 一百〇四 | C119: 南大尚诚 | D119: 45799 | E119: 10000 | F119: =E119-G119 -> 0 | G119: 10000 | H119: =G119-I119 -> 0 | I119: =IF(G119="120元/天",_xlfn.XLOOKUP(B119,'202604考勤'!B:B,'202604考勤'!AI:AI,"无")*120,IF(S119="转正",ROUND(G119/DAY(EOMONTH(T119,0))*(DAY(EOMONTH(T119,0))-DAY(T119)+1)+(G119*0.8)/DAY(EOMONTH(T119,0))*(DAY(T119)-1),2),IF(OR(AND(S119="入职",DAY(T119)=1),AND(S119="离职",T119=EOMONTH(T119,0))),G119,IF(OR(S119="离职",S119="入职"),ROUND(G119/21.75*_xlfn.XLOOKUP(B119,'202604考勤'!B:B,'202604考勤'!AI:AI,0),2),G119)))) -> 10000 | J119: 员工 | K119: {=ROUND(_xlfn.IFS(OR(J119="南京大学",J119="BOSS",J119="实习生",J119="人力劳务"),I119,J119="部门负责人",I119*0.6,J119="员工",I119*0.7),2)} -> 7000 | L119: {=ROUND(_xlfn.IFS(OR(J119="南京大学",J119="BOSS",J119="实习生",J119="人力劳务"),I119*0,J119="部门负责人",I119*0.4,J119="员工",I119*0.3),2)} -> 3000 | M119: C | N119: {=ROUND(_xlfn.IFS(M119="A",L119*1.5,M119="B",L119*1.2,M119="C",L119*1,M119="D",L119*0.8,M119="E",L119*0.6,M119="无等级",L119*0),2)} -> 3000 | O119: =ROUND(K119+N119,2) -> 10000 | P119: 0 | Q119: =ROUND(O119+P119,2) -> 10000 | R119: =O119-I119 -> 0
... A134: =ROW(A134)-15 -> 119 | B134: 一百一十九 | C134: 南大尚诚 | D134: 45881 | E134: 10000 | F134: =E134-G134 -> 0 | G134: 10000 | H134: =G134-I134 -> 0 | I134: =IF(G134="120元/天",_xlfn.XLOOKUP(B134,'202604考勤'!B:B,'202604考勤'!AI:AI,"无")*120,IF(S134="转正",ROUND(G134/DAY(EOMONTH(T134,0))*(DAY(EOMONTH(T134,0))-DAY(T134)+1)+(G134*0.8)/DAY(EOMONTH(T134,0))*(DAY(T134)-1),2),IF(OR(AND(S134="入职",DAY(T134)=1),AND(S134="离职",T134=EOMONTH(T134,0))),G134,IF(OR(S134="离职",S134="入职"),ROUND(G134/21.75*_xlfn.XLOOKUP(B134,'202604考勤'!B:B,'202604考勤'!AI:AI,0),2),G134)))) -> 10000 | J134: 员工 | K134: {=ROUND(_xlfn.IFS(OR(J134="南京大学",J134="BOSS",J134="实习生",J134="人力劳务"),I134,J134="部门负责人",I134*0.6,J134="员工",I134*0.7),2)} -> 7000 | L134: {=ROUND(_xlfn.IFS(OR(J134="南京大学",J134="BOSS",J134="实习生",J134="人力劳务"),I134*0,J134="部门负责人",I134*0.4,J134="员工",I134*0.3),2)} -> 3000 | M134: C | N134: {=ROUND(_xlfn.IFS(M134="A",L134*1.5,M134="B",L134*1.2,M134="C",L134*1,M134="D",L134*0.8,M134="E",L134*0.6,M134="无等级",L134*0),2)} -> 3000 | O134: =ROUND(K134+N134,2) -> 10000 | P134: 0 | Q134: =ROUND(O134+P134,2) -> 10000 | R134: =O134-I134 -> 0
A135: =ROW(A135)-15 -> 120 | B135: 一百二十 | C135: 南大尚诚 | D135: 45882 | E135: 10000 | F135: =E135-G135 -> 0 | G135: 10000 | H135: =G135-I135 -> 0 | I135: =IF(G135="120元/天",_xlfn.XLOOKUP(B135,'202604考勤'!B:B,'202604考勤'!AI:AI,"无")*120,IF(S135="转正",ROUND(G135/DAY(EOMONTH(T135,0))*(DAY(EOMONTH(T135,0))-DAY(T135)+1)+(G135*0.8)/DAY(EOMONTH(T135,0))*(DAY(T135)-1),2),IF(OR(AND(S135="入职",DAY(T135)=1),AND(S135="离职",T135=EOMONTH(T135,0))),G135,IF(OR(S135="离职",S135="入职"),ROUND(G135/21.75*_xlfn.XLOOKUP(B135,'202604考勤'!B:B,'202604考勤'!AI:AI,0),2),G135)))) -> 10000 | J135: 员工 | K135: {=ROUND(_xlfn.IFS(OR(J135="南京大学",J135="BOSS",J135="实习生",J135="人力劳务"),I135,J135="部门负责人",I135*0.6,J135="员工",I135*0.7),2)} -> 7000 | L135: {=ROUND(_xlfn.IFS(OR(J135="南京大学",J135="BOSS",J135="实习生",J135="人力劳务"),I135*0,J135="部门负责人",I135*0.4,J135="员工",I135*0.3),2)} -> 3000 | M135: C | N135: {=ROUND(_xlfn.IFS(M135="A",L135*1.5,M135="B",L135*1.2,M135="C",L135*1,M135="D",L135*0.8,M135="E",L135*0.6,M135="无等级",L135*0),2)} -> 3000 | O135: =ROUND(K135+N135,2) -> 10000 | P135: =-(K135/21.75*2.5) -> -804.5977 | Q135: =ROUND(O135+P135,2) -> 9195.4 | R135: =O135-I135 -> 0 | S135: 事假 | T135: 2.5
A136: =ROW(A136)-15 -> 121 | B136: 一百二十一 | C136: 南大尚诚 | D136: 45882 | E136: 10000 | F136: =E136-G136 -> 0 | G136: 10000 | H136: =G136-I136 -> 0 | I136: =IF(G136="120元/天",_xlfn.XLOOKUP(B136,'202604考勤'!B:B,'202604考勤'!AI:AI,"无")*120,IF(S136="转正",ROUND(G136/DAY(EOMONTH(T136,0))*(DAY(EOMONTH(T136,0))-DAY(T136)+1)+(G136*0.8)/DAY(EOMONTH(T136,0))*(DAY(T136)-1),2),IF(OR(AND(S136="入职",DAY(T136)=1),AND(S136="离职",T136=EOMONTH(T136,0))),G136,IF(OR(S136="离职",S136="入职"),ROUND(G136/21.75*_xlfn.XLOOKUP(B136,'202604考勤'!B:B,'202604考勤'!AI:AI,0),2),G136)))) -> 10000 | J136: 员工 | K136: {=ROUND(_xlfn.IFS(OR(J136="南京大学",J136="BOSS",J136="实习生",J136="人力劳务"),I136,J136="部门负责人",I136*0.6,J136="员工",I136*0.7),2)} -> 7000 | L136: {=ROUND(_xlfn.IFS(OR(J136="南京大学",J136="BOSS",J136="实习生",J136="人力劳务"),I136*0,J136="部门负责人",I136*0.4,J136="员工",I136*0.3),2)} -> 3000 | M136: C | N136: {=ROUND(_xlfn.IFS(M136="A",L136*1.5,M136="B",L136*1.2,M136="C",L136*1,M136="D",L136*0.8,M136="E",L136*0.6,M136="无等级",L136*0),2)} -> 3000 | O136: =ROUND(K136+N136,2) -> 10000 | P136: 0 | Q136: =ROUND(O136+P136,2) -> 10000 | R136: =O136-I136 -> 0
A137: =ROW(A137)-15 -> 122 | B137: 一百二十二 | C137: 南大尚诚 | D137: 45884 | E137: 10000 | F137: =E137-G137 -> 0 | G137: 10000 | H137: =G137-I137 -> 0 | I137: =IF(G137="120元/天",_xlfn.XLOOKUP(B137,'202604考勤'!B:B,'202604考勤'!AI:AI,"无")*120,IF(S137="转正",ROUND(G137/DAY(EOMONTH(T137,0))*(DAY(EOMONTH(T137,0))-DAY(T137)+1)+(G137*0.8)/DAY(EOMONTH(T137,0))*(DAY(T137)-1),2),IF(OR(AND(S137="入职",DAY(T137)=1),AND(S137="离职",T137=EOMONTH(T137,0))),G137,IF(OR(S137="离职",S137="入职"),ROUND(G137/21.75*_xlfn.XLOOKUP(B137,'202604考勤'!B:B,'202604考勤'!AI:AI,0),2),G137)))) -> 10000 | J137: 员工 | K137: {=ROUND(_xlfn.IFS(OR(J137="南京大学",J137="BOSS",J137="实习生",J137="人力劳务"),I137,J137="部门负责人",I137*0.6,J137="员工",I137*0.7),2)} -> 7000 | L137: {=ROUND(_xlfn.IFS(OR(J137="南京大学",J137="BOSS",J137="实习生",J137="人力劳务"),I137*0,J137="部门负责人",I137*0.4,J137="员工",I137*0.3),2)} -> 3000 | M137: C | N137: {=ROUND(_xlfn.IFS(M137="A",L137*1.5,M137="B",L137*1.2,M137="C",L137*1,M137="D",L137*0.8,M137="E",L137*0.6,M137="无等级",L137*0),2)} -> 3000 | O137: =ROUND(K137+N137,2) -> 10000 | P137: 0 | Q137: =ROUND(O137+P137,2) -> 10000 | R137: =O137-I137 -> 0
A138: =ROW(A138)-15 -> 123 | B138: 一百二十三 | C138: 南大尚诚 | D138: 45887 | E138: 10000 | F138: =E138-G138 -> 0 | G138: 10000 | H138: =G138-I138 -> 0 | I138: =IF(G138="120元/天",_xlfn.XLOOKUP(B138,'202604考勤'!B:B,'202604考勤'!AI:AI,"无")*120,IF(S138="转正",ROUND(G138/DAY(EOMONTH(T138,0))*(DAY(EOMONTH(T138,0))-DAY(T138)+1)+(G138*0.8)/DAY(EOMONTH(T138,0))*(DAY(T138)-1),2),IF(OR(AND(S138="入职",DAY(T138)=1),AND(S138="离职",T138=EOMONTH(T138,0))),G138,IF(OR(S138="离职",S138="入职"),ROUND(G138/21.75*_xlfn.XLOOKUP(B138,'202604考勤'!B:B,'202604考勤'!AI:AI,0),2),G138)))) -> 10000 | J138: 员工 | K138: {=ROUND(_xlfn.IFS(OR(J138="南京大学",J138="BOSS",J138="实习生",J138="人力劳务"),I138,J138="部门负责人",I138*0.6,J138="员工",I138*0.7),2)} -> 7000 | L138: {=ROUND(_xlfn.IFS(OR(J138="南京大学",J138="BOSS",J138="实习生",J138="人力劳务"),I138*0,J138="部门负责人",I138*0.4,J138="员工",I138*0.3),2)} -> 3000 | M138: C | N138: {=ROUND(_xlfn.IFS(M138="A",L138*1.5,M138="B",L138*1.2,M138="C",L138*1,M138="D",L138*0.8,M138="E",L138*0.6,M138="无等级",L138*0),2)} -> 3000 | O138: =ROUND(K138+N138,2) -> 10000 | P138: 0 | Q138: =ROUND(O138+P138,2) -> 10000 | R138: =O138-I138 -> 0
A139: =ROW(A139)-15 -> 124 | B139: 一百二十四 | C139: 南大尚诚 | D139: 45889 | E139: 10000 | F139: =E139-G139 -> 0 | G139: 10000 | H139: =G139-I139 -> 0 | I139: =IF(G139="120元/天",_xlfn.XLOOKUP(B139,'202604考勤'!B:B,'202604考勤'!AI:AI,"无")*120,IF(S139="转正",ROUND(G139/DAY(EOMONTH(T139,0))*(DAY(EOMONTH(T139,0))-DAY(T139)+1)+(G139*0.8)/DAY(EOMONTH(T139,0))*(DAY(T139)-1),2),IF(OR(AND(S139="入职",DAY(T139)=1),AND(S139="离职",T139=EOMONTH(T139,0))),G139,IF(OR(S139="离职",S139="入职"),ROUND(G139/21.75*_xlfn.XLOOKUP(B139,'202604考勤'!B:B,'202604考勤'!AI:AI,0),2),G139)))) -> 10000 | J139: 员工 | K139: {=ROUND(_xlfn.IFS(OR(J139="南京大学",J139="BOSS",J139="实习生",J139="人力劳务"),I139,J139="部门负责人",I139*0.6,J139="员工",I139*0.7),2)} -> 7000 | L139: {=ROUND(_xlfn.IFS(OR(J139="南京大学",J139="BOSS",J139="实习生",J139="人力劳务"),I139*0,J139="部门负责人",I139*0.4,J139="员工",I139*0.3),2)} -> 3000 | M139: C | N139: {=ROUND(_xlfn.IFS(M139="A",L139*1.5,M139="B",L139*1.2,M139="C",L139*1,M139="D",L139*0.8,M139="E",L139*0.6,M139="无等级",L139*0),2)} -> 3000 | O139: =ROUND(K139+N139,2) -> 10000 | P139: 0 | Q139: =ROUND(O139+P139,2) -> 10000 | R139: =O139-I139 -> 0
A140: =ROW(A140)-15 -> 125 | B140: 一百二十五 | C140: 南大尚诚 | D140: 45894 | E140: 10000 | F140: =E140-G140 -> 0 | G140: 10000 | H140: =G140-I140 -> 0 | I140: =IF(G140="120元/天",_xlfn.XLOOKUP(B140,'202604考勤'!B:B,'202604考勤'!AI:AI,"无")*120,IF(S140="转正",ROUND(G140/DAY(EOMONTH(T140,0))*(DAY(EOMONTH(T140,0))-DAY(T140)+1)+(G140*0.8)/DAY(EOMONTH(T140,0))*(DAY(T140)-1),2),IF(OR(AND(S140="入职",DAY(T140)=1),AND(S140="离职",T140=EOMONTH(T140,0))),G140,IF(OR(S140="离职",S140="入职"),ROUND(G140/21.75*_xlfn.XLOOKUP(B140,'202604考勤'!B:B,'202604考勤'!AI:AI,0),2),G140)))) -> 10000 | J140: 员工 | K140: {=ROUND(_xlfn.IFS(OR(J140="南京大学",J140="BOSS",J140="实习生",J140="人力劳务"),I140,J140="部门负责人",I140*0.6,J140="员工",I140*0.7),2)} -> 7000 | L140: {=ROUND(_xlfn.IFS(OR(J140="南京大学",J140="BOSS",J140="实习生",J140="人力劳务"),I140*0,J140="部门负责人",I140*0.4,J140="员工",I140*0.3),2)} -> 3000 | M140: C | N140: {=ROUND(_xlfn.IFS(M140="A",L140*1.5,M140="B",L140*1.2,M140="C",L140*1,M140="D",L140*0.8,M140="E",L140*0.6,M140="无等级",L140*0),2)} -> 3000 | O140: =ROUND(K140+N140,2) -> 10000 | P140: 0 | Q140: =ROUND(O140+P140,2) -> 10000 | R140: =O140-I140 -> 0
A141: =ROW(A141)-15 -> 126 | B141: 一百二十六 | C141: 南大尚诚 | D141: 45901 | E141: 10000 | F141: =E141-G141 -> 0 | G141: 10000 | H141: =G141-I141 -> 0 | I141: =IF(G141="120元/天",_xlfn.XLOOKUP(B141,'202604考勤'!B:B,'202604考勤'!AI:AI,"无")*120,IF(S141="转正",ROUND(G141/DAY(EOMONTH(T141,0))*(DAY(EOMONTH(T141,0))-DAY(T141)+1)+(G141*0.8)/DAY(EOMONTH(T141,0))*(DAY(T141)-1),2),IF(OR(AND(S141="入职",DAY(T141)=1),AND(S141="离职",T141=EOMONTH(T141,0))),G141,IF(OR(S141="离职",S141="入职"),ROUND(G141/21.75*_xlfn.XLOOKUP(B141,'202604考勤'!B:B,'202604考勤'!AI:AI,0),2),G141)))) -> 10000 | J141: 员工 | K141: {=ROUND(_xlfn.IFS(OR(J141="南京大学",J141="BOSS",J141="实习生",J141="人力劳务"),I141,J141="部门负责人",I141*0.6,J141="员工",I141*0.7),2)} -> 7000 | L141: {=ROUND(_xlfn.IFS(OR(J141="南京大学",J141="BOSS",J141="实习生",J141="人力劳务"),I141*0,J141="部门负责人",I141*0.4,J141="员工",I141*0.3),2)} -> 3000 | M141: C | N141: {=ROUND(_xlfn.IFS(M141="A",L141*1.5,M141="B",L141*1.2,M141="C",L141*1,M141="D",L141*0.8,M141="E",L141*0.6,M141="无等级",L141*0),2)} -> 3000 | O141: =ROUND(K141+N141,2) -> 10000 | P141: 0 | Q141: =ROUND(O141+P141,2) -> 10000 | R141: =O141-I141 -> 0
A142: =ROW(A142)-15 -> 127 | B142: 一百二十七 | C142: 南大尚诚 | D142: 45901 | E142: 10000 | F142: =E142-G142 -> 0 | G142: 10000 | H142: =G142-I142 -> 0 | I142: =IF(G142="120元/天",_xlfn.XLOOKUP(B142,'202604考勤'!B:B,'202604考勤'!AI:AI,"无")*120,IF(S142="转正",ROUND(G142/DAY(EOMONTH(T142,0))*(DAY(EOMONTH(T142,0))-DAY(T142)+1)+(G142*0.8)/DAY(EOMONTH(T142,0))*(DAY(T142)-1),2),IF(OR(AND(S142="入职",DAY(T142)=1),AND(S142="离职",T142=EOMONTH(T142,0))),G142,IF(OR(S142="离职",S142="入职"),ROUND(G142/21.75*_xlfn.XLOOKUP(B142,'202604考勤'!B:B,'202604考勤'!AI:AI,0),2),G142)))) -> 10000 | J142: 员工 | K142: {=ROUND(_xlfn.IFS(OR(J142="南京大学",J142="BOSS",J142="实习生",J142="人力劳务"),I142,J142="部门负责人",I142*0.6,J142="员工",I142*0.7),2)} -> 7000 | L142: {=ROUND(_xlfn.IFS(OR(J142="南京大学",J142="BOSS",J142="实习生",J142="人力劳务"),I142*0,J142="部门负责人",I142*0.4,J142="员工",I142*0.3),2)} -> 3000 | M142: C | N142: {=ROUND(_xlfn.IFS(M142="A",L142*1.5,M142="B",L142*1.2,M142="C",L142*1,M142="D",L142*0.8,M142="E",L142*0.6,M142="无等级",L142*0),2)} -> 3000 | O142: =ROUND(K142+N142,2) -> 10000 | P142: 0 | Q142: =ROUND(O142+P142,2) -> 10000 | R142: =O142-I142 -> 0
A143: =ROW(A143)-15 -> 128 | B143: 一百二十八 | C143: 南大尚诚 | D143: 45901 | E143: 10000 | F143: =E143-G143 -> 0 | G143: 10000 | H143: =G143-I143 -> 0 | I143: =IF(G143="120元/天",_xlfn.XLOOKUP(B143,'202604考勤'!B:B,'202604考勤'!AI:AI,"无")*120,IF(S143="转正",ROUND(G143/DAY(EOMONTH(T143,0))*(DAY(EOMONTH(T143,0))-DAY(T143)+1)+(G143*0.8)/DAY(EOMONTH(T143,0))*(DAY(T143)-1),2),IF(OR(AND(S143="入职",DAY(T143)=1),AND(S143="离职",T143=EOMONTH(T143,0))),G143,IF(OR(S143="离职",S143="入职"),ROUND(G143/21.75*_xlfn.XLOOKUP(B143,'202604考勤'!B:B,'202604考勤'!AI:AI,0),2),G143)))) -> 10000 | J143: 员工 | K143: {=ROUND(_xlfn.IFS(OR(J143="南京大学",J143="BOSS",J143="实习生",J143="人力劳务"),I143,J143="部门负责人",I143*0.6,J143="员工",I143*0.7),2)} -> 7000 | L143: {=ROUND(_xlfn.IFS(OR(J143="南京大学",J143="BOSS",J143="实习生",J143="人力劳务"),I143*0,J143="部门负责人",I143*0.4,J143="员工",I143*0.3),2)} -> 3000 | M143: C | N143: {=ROUND(_xlfn.IFS(M143="A",L143*1.5,M143="B",L143*1.2,M143="C",L143*1,M143="D",L143*0.8,M143="E",L143*0.6,M143="无等级",L143*0),2)} -> 3000 | O143: =ROUND(K143+N143,2) -> 10000 | P143: 0 | Q143: =ROUND(O143+P143,2) -> 10000 | R143: =O143-I143 -> 0
A144: =ROW(A144)-15 -> 129 | B144: 一百二十九 | C144: 南大尚诚 | D144: 45910 | E144: 10000 | F144: =E144-G144 -> 0 | G144: 10000 | H144: =G144-I144 -> 0 | I144: =IF(G144="120元/天",_xlfn.XLOOKUP(B144,'202604考勤'!B:B,'202604考勤'!AI:AI,"无")*120,IF(S144="转正",ROUND(G144/DAY(EOMONTH(T144,0))*(DAY(EOMONTH(T144,0))-DAY(T144)+1)+(G144*0.8)/DAY(EOMONTH(T144,0))*(DAY(T144)-1),2),IF(OR(AND(S144="入职",DAY(T144)=1),AND(S144="离职",T144=EOMONTH(T144,0))),G144,IF(OR(S144="离职",S144="入职"),ROUND(G144/21.75*_xlfn.XLOOKUP(B144,'202604考勤'!B:B,'202604考勤'!AI:AI,0),2),G144)))) -> 10000 | J144: 员工 | K144: {=ROUND(_xlfn.IFS(OR(J144="南京大学",J144="BOSS",J144="实习生",J144="人力劳务"),I144,J144="部门负责人",I144*0.6,J144="员工",I144*0.7),2)} -> 7000 | L144: {=ROUND(_xlfn.IFS(OR(J144="南京大学",J144="BOSS",J144="实习生",J144="人力劳务"),I144*0,J144="部门负责人",I144*0.4,J144="员工",I144*0.3),2)} -> 3000 | M144: C | N144: {=ROUND(_xlfn.IFS(M144="A",L144*1.5,M144="B",L144*1.2,M144="C",L144*1,M144="D",L144*0.8,M144="E",L144*0.6,M144="无等级",L144*0),2)} -> 3000 | O144: =ROUND(K144+N144,2) -> 10000 | P144: 0 | Q144: =ROUND(O144+P144,2) -> 10000 | R144: =O144-I144 -> 0
A145: =ROW(A145)-15 -> 130 | B145: 一百三十 | C145: 南大尚诚 | D145: 45918 | E145: 10000 | F145: =E145-G145 -> 0 | G145: 10000 | H145: =G145-I145 -> 0 | I145: =IF(G145="120元/天",_xlfn.XLOOKUP(B145,'202604考勤'!B:B,'202604考勤'!AI:AI,"无")*120,IF(S145="转正",ROUND(G145/DAY(EOMONTH(T145,0))*(DAY(EOMONTH(T145,0))-DAY(T145)+1)+(G145*0.8)/DAY(EOMONTH(T145,0))*(DAY(T145)-1),2),IF(OR(AND(S145="入职",DAY(T145)=1),AND(S145="离职",T145=EOMONTH(T145,0))),G145,IF(OR(S145="离职",S145="入职"),ROUND(G145/21.75*_xlfn.XLOOKUP(B145,'202604考勤'!B:B,'202604考勤'!AI:AI,0),2),G145)))) -> 10000 | J145: 员工 | K145: {=ROUND(_xlfn.IFS(OR(J145="南京大学",J145="BOSS",J145="实习生",J145="人力劳务"),I145,J145="部门负责人",I145*0.6,J145="员工",I145*0.7),2)} -> 7000 | L145: {=ROUND(_xlfn.IFS(OR(J145="南京大学",J145="BOSS",J145="实习生",J145="人力劳务"),I145*0,J145="部门负责人",I145*0.4,J145="员工",I145*0.3),2)} -> 3000 | M145: C | N145: {=ROUND(_xlfn.IFS(M145="A",L145*1.5,M145="B",L145*1.2,M145="C",L145*1,M145="D",L145*0.8,M145="E",L145*0.6,M145="无等级",L145*0),2)} -> 3000 | O145: =ROUND(K145+N145,2) -> 10000 | P145: 0 | Q145: =ROUND(O145+P145,2) -> 10000 | R145: =O145-I145 -> 0
A146: =ROW(A146)-15 -> 131 | B146: 一百三十一 | C146: 南大尚诚 | D146: 45939 | E146: 10000 | F146: =E146-G146 -> 0 | G146: 10000 | H146: =G146-I146 -> 0 | I146: =IF(G146="120元/天",_xlfn.XLOOKUP(B146,'202604考勤'!B:B,'202604考勤'!AI:AI,"无")*120,IF(S146="转正",ROUND(G146/DAY(EOMONTH(T146,0))*(DAY(EOMONTH(T146,0))-DAY(T146)+1)+(G146*0.8)/DAY(EOMONTH(T146,0))*(DAY(T146)-1),2),IF(OR(AND(S146="入职",DAY(T146)=1),AND(S146="离职",T146=EOMONTH(T146,0))),G146,IF(OR(S146="离职",S146="入职"),ROUND(G146/21.75*_xlfn.XLOOKUP(B146,'202604考勤'!B:B,'202604考勤'!AI:AI,0),2),G146)))) -> 10000 | J146: 员工 | K146: {=ROUND(_xlfn.IFS(OR(J146="南京大学",J146="BOSS",J146="实习生",J146="人力劳务"),I146,J146="部门负责人",I146*0.6,J146="员工",I146*0.7),2)} -> 7000 | L146: {=ROUND(_xlfn.IFS(OR(J146="南京大学",J146="BOSS",J146="实习生",J146="人力劳务"),I146*0,J146="部门负责人",I146*0.4,J146="员工",I146*0.3),2)} -> 3000 | M146: C | N146: {=ROUND(_xlfn.IFS(M146="A",L146*1.5,M146="B",L146*1.2,M146="C",L146*1,M146="D",L146*0.8,M146="E",L146*0.6,M146="无等级",L146*0),2)} -> 3000 | O146: =ROUND(K146+N146,2) -> 10000 | P146: 0 | Q146: =ROUND(O146+P146,2) -> 10000 | R146: =O146-I146 -> 0
A147: =ROW(A147)-15 -> 132 | B147: 一百三十二 | C147: 南大尚诚 | D147: 45992 | E147: 10000 | F147: =E147-G147 -> 0 | G147: 10000 | H147: =G147-I147 -> 6781.61 | I147: =IF(G147="120元/天",_xlfn.XLOOKUP(B147,'202604考勤'!B:B,'202604考勤'!AI:AI,"无")*120,IF(S147="转正",ROUND(G147/DAY(EOMONTH(T147,0))*(DAY(EOMONTH(T147,0))-DAY(T147)+1)+(G147*0.8)/DAY(EOMONTH(T147,0))*(DAY(T147)-1),2),IF(OR(AND(S147="入职",DAY(T147)=1),AND(S147="离职",T147=EOMONTH(T147,0))),G147,IF(OR(S147="离职",S147="入职"),ROUND(G147/21.75*_xlfn.XLOOKUP(B147,'202604考勤'!B:B,'202604考勤'!AI:AI,0),2),G147)))) -> 3218.39 | J147: 员工 | K147: {=ROUND(_xlfn.IFS(OR(J147="南京大学",J147="BOSS",J147="实习生",J147="人力劳务"),I147,J147="部门负责人",I147*0.6,J147="员工",I147*0.7),2)} -> 2252.87 | L147: {=ROUND(_xlfn.IFS(OR(J147="南京大学",J147="BOSS",J147="实习生",J147="人力劳务"),I147*0,J147="部门负责人",I147*0.4,J147="员工",I147*0.3),2)} -> 965.52 | M147: C | N147: {=ROUND(_xlfn.IFS(M147="A",L147*1.5,M147="B",L147*1.2,M147="C",L147*1,M147="D",L147*0.8,M147="E",L147*0.6,M147="无等级",L147*0),2)} -> 965.52 | O147: =ROUND(K147+N147,2) -> 3218.39 | P147: 0 | Q147: =ROUND(O147+P147,2) -> 3218.39 | R147: =O147-I147 -> 0 | S147: 离职 | T147: 46124
A148: =ROW(A148)-15 -> 133 | B148: 一百三十三 | C148: 南大尚诚 | D148: 46009 | E148: 10000 | F148: =E148-G148 -> 0 | G148: 10000 | H148: =G148-I148 -> 0 | I148: =IF(G148="120元/天",_xlfn.XLOOKUP(B148,'202604考勤'!B:B,'202604考勤'!AI:AI,"无")*120,IF(S148="转正",ROUND(G148/DAY(EOMONTH(T148,0))*(DAY(EOMONTH(T148,0))-DAY(T148)+1)+(G148*0.8)/DAY(EOMONTH(T148,0))*(DAY(T148)-1),2),IF(OR(AND(S148="入职",DAY(T148)=1),AND(S148="离职",T148=EOMONTH(T148,0))),G148,IF(OR(S148="离职",S148="入职"),ROUND(G148/21.75*_xlfn.XLOOKUP(B148,'202604考勤'!B:B,'202604考勤'!AI:AI,0),2),G148)))) -> 10000 | J148: 员工 | K148: {=ROUND(_xlfn.IFS(OR(J148="南京大学",J148="BOSS",J148="实习生",J148="人力劳务"),I148,J148="部门负责人",I148*0.6,J148="员工",I148*0.7),2)} -> 7000 | L148: {=ROUND(_xlfn.IFS(OR(J148="南京大学",J148="BOSS",J148="实习生",J148="人力劳务"),I148*0,J148="部门负责人",I148*0.4,J148="员工",I148*0.3),2)} -> 3000 | M148: C | N148: {=ROUND(_xlfn.IFS(M148="A",L148*1.5,M148="B",L148*1.2,M148="C",L148*1,M148="D",L148*0.8,M148="E",L148*0.6,M148="无等级",L148*0),2)} -> 3000 | O148: =ROUND(K148+N148,2) -> 10000 | P148: 0 | Q148: =ROUND(O148+P148,2) -> 10000 | R148: =O148-I148 -> 0
A149: =ROW(A149)-15 -> 134 | B149: 一百三十四 | C149: 南大尚诚 | D149: 46013 | E149: 10000 | F149: =E149-G149 -> 0 | G149: 10000 | H149: =G149-I149 -> 0 | I149: =IF(G149="120元/天",_xlfn.XLOOKUP(B149,'202604考勤'!B:B,'202604考勤'!AI:AI,"无")*120,IF(S149="转正",ROUND(G149/DAY(EOMONTH(T149,0))*(DAY(EOMONTH(T149,0))-DAY(T149)+1)+(G149*0.8)/DAY(EOMONTH(T149,0))*(DAY(T149)-1),2),IF(OR(AND(S149="入职",DAY(T149)=1),AND(S149="离职",T149=EOMONTH(T149,0))),G149,IF(OR(S149="离职",S149="入职"),ROUND(G149/21.75*_xlfn.XLOOKUP(B149,'202604考勤'!B:B,'202604考勤'!AI:AI,0),2),G149)))) -> 10000 | J149: 员工 | K149: {=ROUND(_xlfn.IFS(OR(J149="南京大学",J149="BOSS",J149="实习生",J149="人力劳务"),I149,J149="部门负责人",I149*0.6,J149="员工",I149*0.7),2)} -> 7000 | L149: {=ROUND(_xlfn.IFS(OR(J149="南京大学",J149="BOSS",J149="实习生",J149="人力劳务"),I149*0,J149="部门负责人",I149*0.4,J149="员工",I149*0.3),2)} -> 3000 | M149: C | N149: {=ROUND(_xlfn.IFS(M149="A",L149*1.5,M149="B",L149*1.2,M149="C",L149*1,M149="D",L149*0.8,M149="E",L149*0.6,M149="无等级",L149*0),2)} -> 3000 | O149: =ROUND(K149+N149,2) -> 10000 | P149: 0 | Q149: =ROUND(O149+P149,2) -> 10000 | R149: =O149-I149 -> 0
A150: =ROW(A150)-15 -> 135 | B150: 一百三十五 | C150: 尚诚能源 | D150: 46020 | E150: 120元/天 | F150: 0 | G150: 120元/天 | H150: 0 | I150: =IF(G150="120元/天",_xlfn.XLOOKUP(B150,'202604考勤'!B:B,'202604考勤'!AI:AI,"无")*120,IF(S150="转正",ROUND(G150/DAY(EOMONTH(T150,0))*(DAY(EOMONTH(T150,0))-DAY(T150)+1)+(G150*0.8)/DAY(EOMONTH(T150,0))*(DAY(T150)-1),2),IF(OR(AND(S150="入职",DAY(T150)=1),AND(S150="离职",T150=EOMONTH(T150,0))),G150,IF(OR(S150="离职",S150="入职"),ROUND(G150/21.75*_xlfn.XLOOKUP(B150,'202604考勤'!B:B,'202604考勤'!AI:AI,0),2),G150)))) -> 2520 | J150: 实习生 | K150: {=ROUND(_xlfn.IFS(OR(J150="南京大学",J150="BOSS",J150="实习生",J150="人力劳务"),I150,J150="部门负责人",I150*0.6,J150="员工",I150*0.7),2)} -> 2520 | L150: {=ROUND(_xlfn.IFS(OR(J150="南京大学",J150="BOSS",J150="实习生",J150="人力劳务"),I150*0,J150="部门负责人",I150*0.4,J150="员工",I150*0.3),2)} -> 0 | M150: 无等级 | N150: {=ROUND(_xlfn.IFS(M150="A",L150*1.5,M150="B",L150*1.2,M150="C",L150*1,M150="D",L150*0.8,M150="E",L150*0.6,M150="无等级",L150*0),2)} -> 0 | O150: =ROUND(K150+N150,2) -> 2520 | P150: 0 | Q150: =ROUND(O150+P150,2) -> 2520 | R150: =O150-I150 -> 0 | T150: 21
A151: =ROW(A151)-15 -> 136 | B151: 一百三十六 | C151: 尚诚能源 | D151: 46021 | E151: 120元/天 | F151: 0 | G151: 120元/天 | H151: 0 | I151: =IF(G151="120元/天",_xlfn.XLOOKUP(B151,'202604考勤'!B:B,'202604考勤'!AI:AI,"无")*120,IF(S151="转正",ROUND(G151/DAY(EOMONTH(T151,0))*(DAY(EOMONTH(T151,0))-DAY(T151)+1)+(G151*0.8)/DAY(EOMONTH(T151,0))*(DAY(T151)-1),2),IF(OR(AND(S151="入职",DAY(T151)=1),AND(S151="离职",T151=EOMONTH(T151,0))),G151,IF(OR(S151="离职",S151="入职"),ROUND(G151/21.75*_xlfn.XLOOKUP(B151,'202604考勤'!B:B,'202604考勤'!AI:AI,0),2),G151)))) -> 840 | J151: 实习生 | K151: {=ROUND(_xlfn.IFS(OR(J151="南京大学",J151="BOSS",J151="实习生",J151="人力劳务"),I151,J151="部门负责人",I151*0.6,J151="员工",I151*0.7),2)} -> 840 | L151: {=ROUND(_xlfn.IFS(OR(J151="南京大学",J151="BOSS",J151="实习生",J151="人力劳务"),I151*0,J151="部门负责人",I151*0.4,J151="员工",I151*0.3),2)} -> 0 | M151: 无等级 | N151: {=ROUND(_xlfn.IFS(M151="A",L151*1.5,M151="B",L151*1.2,M151="C",L151*1,M151="D",L151*0.8,M151="E",L151*0.6,M151="无等级",L151*0),2)} -> 0 | O151: =ROUND(K151+N151,2) -> 840 | P151: 0 | Q151: =ROUND(O151+P151,2) -> 840 | R151: =O151-I151 -> 0 | S151: 离职 | T151: 46125
A152: =ROW(A152)-15 -> 137 | B152: 一百三十七 | C152: 南大尚诚 | D152: 46030 | E152: 10000 | F152: =E152-G152 -> 0 | G152: 10000 | H152: =G152-I152 -> 466.67 | I152: =IF(G152="120元/天",_xlfn.XLOOKUP(B152,'202604考勤'!B:B,'202604考勤'!AI:AI,"无")*120,IF(S152="转正",ROUND(G152/DAY(EOMONTH(T152,0))*(DAY(EOMONTH(T152,0))-DAY(T152)+1)+(G152*0.8)/DAY(EOMONTH(T152,0))*(DAY(T152)-1),2),IF(OR(AND(S152="入职",DAY(T152)=1),AND(S152="离职",T152=EOMONTH(T152,0))),G152,IF(OR(S152="离职",S152="入职"),ROUND(G152/21.75*_xlfn.XLOOKUP(B152,'202604考勤'!B:B,'202604考勤'!AI:AI,0),2),G152)))) -> 9533.33 | J152: 员工 | K152: {=ROUND(_xlfn.IFS(OR(J152="南京大学",J152="BOSS",J152="实习生",J152="人力劳务"),I152,J152="部门负责人",I152*0.6,J152="员工",I152*0.7),2)} -> 6673.33 | L152: {=ROUND(_xlfn.IFS(OR(J152="南京大学",J152="BOSS",J152="实习生",J152="人力劳务"),I152*0,J152="部门负责人",I152*0.4,J152="员工",I152*0.3),2)} -> 2860 | M152: C | N152: {=ROUND(_xlfn.IFS(M152="A",L152*1.5,M152="B",L152*1.2,M152="C",L152*1,M152="D",L152*0.8,M152="E",L152*0.6,M152="无等级",L152*0),2)} -> 2860 | O152: =ROUND(K152+N152,2) -> 9533.33 | P152: 0 | Q152: =ROUND(O152+P152,2) -> 9533.33 | R152: =O152-I152 -> 0 | S152: 转正 | T152: 46120
A153: =ROW(A153)-15 -> 138 | B153: 一百三十八 | C153: 南大尚诚 | D153: 46034 | E153: 10000 | F153: =E153-G153 -> 0 | G153: 10000 | H153: =G153-I153 -> 0 | I153: =IF(G153="120元/天",_xlfn.XLOOKUP(B153,'202604考勤'!B:B,'202604考勤'!AI:AI,"无")*120,IF(S153="转正",ROUND(G153/DAY(EOMONTH(T153,0))*(DAY(EOMONTH(T153,0))-DAY(T153)+1)+(G153*0.8)/DAY(EOMONTH(T153,0))*(DAY(T153)-1),2),IF(OR(AND(S153="入职",DAY(T153)=1),AND(S153="离职",T153=EOMONTH(T153,0))),G153,IF(OR(S153="离职",S153="入职"),ROUND(G153/21.75*_xlfn.XLOOKUP(B153,'202604考勤'!B:B,'202604考勤'!AI:AI,0),2),G153)))) -> 10000 | J153: 员工 | K153: {=ROUND(_xlfn.IFS(OR(J153="南京大学",J153="BOSS",J153="实习生",J153="人力劳务"),I153,J153="部门负责人",I153*0.6,J153="员工",I153*0.7),2)} -> 7000 | L153: {=ROUND(_xlfn.IFS(OR(J153="南京大学",J153="BOSS",J153="实习生",J153="人力劳务"),I153*0,J153="部门负责人",I153*0.4,J153="员工",I153*0.3),2)} -> 3000 | M153: D | N153: {=ROUND(_xlfn.IFS(M153="A",L153*1.5,M153="B",L153*1.2,M153="C",L153*1,M153="D",L153*0.8,M153="E",L153*0.6,M153="无等级",L153*0),2)} -> 2400 | O153: =ROUND(K153+N153,2) -> 9400 | P153: 0 | Q153: =ROUND(O153+P153,2) -> 9400 | R153: =O153-I153 -> -600
A154: =ROW(A154)-15 -> 139 | B154: 一百三十九 | C154: 南大尚诚 | D154: 46054 | E154: 10000 | F154: =E154-G154 -> 0 | G154: 10000 | H154: =G154-I154 -> 0 | I154: =IF(G154="120元/天",_xlfn.XLOOKUP(B154,'202604考勤'!B:B,'202604考勤'!AI:AI,"无")*120,IF(S154="转正",ROUND(G154/DAY(EOMONTH(T154,0))*(DAY(EOMONTH(T154,0))-DAY(T154)+1)+(G154*0.8)/DAY(EOMONTH(T154,0))*(DAY(T154)-1),2),IF(OR(AND(S154="入职",DAY(T154)=1),AND(S154="离职",T154=EOMONTH(T154,0))),G154,IF(OR(S154="离职",S154="入职"),ROUND(G154/21.75*_xlfn.XLOOKUP(B154,'202604考勤'!B:B,'202604考勤'!AI:AI,0),2),G154)))) -> 10000 | J154: 员工 | K154: {=ROUND(_xlfn.IFS(OR(J154="南京大学",J154="BOSS",J154="实习生",J154="人力劳务"),I154,J154="部门负责人",I154*0.6,J154="员工",I154*0.7),2)} -> 7000 | L154: {=ROUND(_xlfn.IFS(OR(J154="南京大学",J154="BOSS",J154="实习生",J154="人力劳务"),I154*0,J154="部门负责人",I154*0.4,J154="员工",I154*0.3),2)} -> 3000 | M154: C | N154: {=ROUND(_xlfn.IFS(M154="A",L154*1.5,M154="B",L154*1.2,M154="C",L154*1,M154="D",L154*0.8,M154="E",L154*0.6,M154="无等级",L154*0),2)} -> 3000 | O154: =ROUND(K154+N154,2) -> 10000 | P154: 0 | Q154: =ROUND(O154+P154,2) -> 10000 | R154: =O154-I154 -> 0
A155: =ROW(A155)-15 -> 140 | B155: 一百四十 | C155: 南大尚诚 | D155: 46054 | E155: 10000 | F155: =E155-G155 -> 0 | G155: 10000 | H155: =G155-I155 -> 0 | I155: =IF(G155="120元/天",_xlfn.XLOOKUP(B155,'202604考勤'!B:B,'202604考勤'!AI:AI,"无")*120,IF(S155="转正",ROUND(G155/DAY(EOMONTH(T155,0))*(DAY(EOMONTH(T155,0))-DAY(T155)+1)+(G155*0.8)/DAY(EOMONTH(T155,0))*(DAY(T155)-1),2),IF(OR(AND(S155="入职",DAY(T155)=1),AND(S155="离职",T155=EOMONTH(T155,0))),G155,IF(OR(S155="离职",S155="入职"),ROUND(G155/21.75*_xlfn.XLOOKUP(B155,'202604考勤'!B:B,'202604考勤'!AI:AI,0),2),G155)))) -> 10000 | J155: 员工 | K155: {=ROUND(_xlfn.IFS(OR(J155="南京大学",J155="BOSS",J155="实习生",J155="人力劳务"),I155,J155="部门负责人",I155*0.6,J155="员工",I155*0.7),2)} -> 7000 | L155: {=ROUND(_xlfn.IFS(OR(J155="南京大学",J155="BOSS",J155="实习生",J155="人力劳务"),I155*0,J155="部门负责人",I155*0.4,J155="员工",I155*0.3),2)} -> 3000 | M155: C | N155: {=ROUND(_xlfn.IFS(M155="A",L155*1.5,M155="B",L155*1.2,M155="C",L155*1,M155="D",L155*0.8,M155="E",L155*0.6,M155="无等级",L155*0),2)} -> 3000 | O155: =ROUND(K155+N155,2) -> 10000 | P155: 0 | Q155: =ROUND(O155+P155,2) -> 10000 | R155: =O155-I155 -> 0
A156: =ROW(A156)-15 -> 141 | B156: 一百四十一 | C156: 南大尚诚 | D156: 46054 | E156: 10000 | F156: =E156-G156 -> 0 | G156: 10000 | H156: =G156-I156 -> 0 | I156: =IF(G156="120元/天",_xlfn.XLOOKUP(B156,'202604考勤'!B:B,'202604考勤'!AI:AI,"无")*120,IF(S156="转正",ROUND(G156/DAY(EOMONTH(T156,0))*(DAY(EOMONTH(T156,0))-DAY(T156)+1)+(G156*0.8)/DAY(EOMONTH(T156,0))*(DAY(T156)-1),2),IF(OR(AND(S156="入职",DAY(T156)=1),AND(S156="离职",T156=EOMONTH(T156,0))),G156,IF(OR(S156="离职",S156="入职"),ROUND(G156/21.75*_xlfn.XLOOKUP(B156,'202604考勤'!B:B,'202604考勤'!AI:AI,0),2),G156)))) -> 10000 | J156: 员工 | K156: {=ROUND(_xlfn.IFS(OR(J156="南京大学",J156="BOSS",J156="实习生",J156="人力劳务"),I156,J156="部门负责人",I156*0.6,J156="员工",I156*0.7),2)} -> 7000 | L156: {=ROUND(_xlfn.IFS(OR(J156="南京大学",J156="BOSS",J156="实习生",J156="人力劳务"),I156*0,J156="部门负责人",I156*0.4,J156="员工",I156*0.3),2)} -> 3000 | M156: C | N156: {=ROUND(_xlfn.IFS(M156="A",L156*1.5,M156="B",L156*1.2,M156="C",L156*1,M156="D",L156*0.8,M156="E",L156*0.6,M156="无等级",L156*0),2)} -> 3000 | O156: =ROUND(K156+N156,2) -> 10000 | P156: 0 | Q156: =ROUND(O156+P156,2) -> 10000 | R156: =O156-I156 -> 0
A157: =ROW(A157)-15 -> 142 | B157: 一百四十二 | C157: 南大尚诚 | D157: 46054 | E157: 10000 | F157: =E157-G157 -> 0 | G157: 10000 | H157: =G157-I157 -> 0 | I157: =IF(G157="120元/天",_xlfn.XLOOKUP(B157,'202604考勤'!B:B,'202604考勤'!AI:AI,"无")*120,IF(S157="转正",ROUND(G157/DAY(EOMONTH(T157,0))*(DAY(EOMONTH(T157,0))-DAY(T157)+1)+(G157*0.8)/DAY(EOMONTH(T157,0))*(DAY(T157)-1),2),IF(OR(AND(S157="入职",DAY(T157)=1),AND(S157="离职",T157=EOMONTH(T157,0))),G157,IF(OR(S157="离职",S157="入职"),ROUND(G157/21.75*_xlfn.XLOOKUP(B157,'202604考勤'!B:B,'202604考勤'!AI:AI,0),2),G157)))) -> 10000 | J157: 员工 | K157: {=ROUND(_xlfn.IFS(OR(J157="南京大学",J157="BOSS",J157="实习生",J157="人力劳务"),I157,J157="部门负责人",I157*0.6,J157="员工",I157*0.7),2)} -> 7000 | L157: {=ROUND(_xlfn.IFS(OR(J157="南京大学",J157="BOSS",J157="实习生",J157="人力劳务"),I157*0,J157="部门负责人",I157*0.4,J157="员工",I157*0.3),2)} -> 3000 | M157: C | N157: {=ROUND(_xlfn.IFS(M157="A",L157*1.5,M157="B",L157*1.2,M157="C",L157*1,M157="D",L157*0.8,M157="E",L157*0.6,M157="无等级",L157*0),2)} -> 3000 | O157: =ROUND(K157+N157,2) -> 10000 | P157: 0 | Q157: =ROUND(O157+P157,2) -> 10000 | R157: =O157-I157 -> 0
A158: =ROW(A158)-15 -> 143 | B158: 一百四十三 | C158: 南大尚诚 | D158: 46054 | E158: 10000 | F158: =E158-G158 -> 0 | G158: 10000 | H158: =G158-I158 -> 0 | I158: =IF(G158="120元/天",_xlfn.XLOOKUP(B158,'202604考勤'!B:B,'202604考勤'!AI:AI,"无")*120,IF(S158="转正",ROUND(G158/DAY(EOMONTH(T158,0))*(DAY(EOMONTH(T158,0))-DAY(T158)+1)+(G158*0.8)/DAY(EOMONTH(T158,0))*(DAY(T158)-1),2),IF(OR(AND(S158="入职",DAY(T158)=1),AND(S158="离职",T158=EOMONTH(T158,0))),G158,IF(OR(S158="离职",S158="入职"),ROUND(G158/21.75*_xlfn.XLOOKUP(B158,'202604考勤'!B:B,'202604考勤'!AI:AI,0),2),G158)))) -> 10000 | J158: 员工 | K158: {=ROUND(_xlfn.IFS(OR(J158="南京大学",J158="BOSS",J158="实习生",J158="人力劳务"),I158,J158="部门负责人",I158*0.6,J158="员工",I158*0.7),2)} -> 7000 | L158: {=ROUND(_xlfn.IFS(OR(J158="南京大学",J158="BOSS",J158="实习生",J158="人力劳务"),I158*0,J158="部门负责人",I158*0.4,J158="员工",I158*0.3),2)} -> 3000 | M158: C | N158: {=ROUND(_xlfn.IFS(M158="A",L158*1.5,M158="B",L158*1.2,M158="C",L158*1,M158="D",L158*0.8,M158="E",L158*0.6,M158="无等级",L158*0),2)} -> 3000 | O158: =ROUND(K158+N158,2) -> 10000 | P158: 0 | Q158: =ROUND(O158+P158,2) -> 10000 | R158: =O158-I158 -> 0
A159: =ROW(A159)-15 -> 144 | B159: 一百四十四 | C159: 南大尚诚 | D159: 46054 | E159: 10000 | F159: =E159-G159 -> 0 | G159: 10000 | H159: =G159-I159 -> 0 | I159: =IF(G159="120元/天",_xlfn.XLOOKUP(B159,'202604考勤'!B:B,'202604考勤'!AI:AI,"无")*120,IF(S159="转正",ROUND(G159/DAY(EOMONTH(T159,0))*(DAY(EOMONTH(T159,0))-DAY(T159)+1)+(G159*0.8)/DAY(EOMONTH(T159,0))*(DAY(T159)-1),2),IF(OR(AND(S159="入职",DAY(T159)=1),AND(S159="离职",T159=EOMONTH(T159,0))),G159,IF(OR(S159="离职",S159="入职"),ROUND(G159/21.75*_xlfn.XLOOKUP(B159,'202604考勤'!B:B,'202604考勤'!AI:AI,0),2),G159)))) -> 10000 | J159: 员工 | K159: {=ROUND(_xlfn.IFS(OR(J159="南京大学",J159="BOSS",J159="实习生",J159="人力劳务"),I159,J159="部门负责人",I159*0.6,J159="员工",I159*0.7),2)} -> 7000 | L159: {=ROUND(_xlfn.IFS(OR(J159="南京大学",J159="BOSS",J159="实习生",J159="人力劳务"),I159*0,J159="部门负责人",I159*0.4,J159="员工",I159*0.3),2)} -> 3000 | M159: C | N159: {=ROUND(_xlfn.IFS(M159="A",L159*1.5,M159="B",L159*1.2,M159="C",L159*1,M159="D",L159*0.8,M159="E",L159*0.6,M159="无等级",L159*0),2)} -> 3000 | O159: =ROUND(K159+N159,2) -> 10000 | P159: 0 | Q159: =ROUND(O159+P159,2) -> 10000 | R159: =O159-I159 -> 0
A160: =ROW(A160)-15 -> 145 | B160: 一百四十五 | C160: 南大尚诚 | D160: 46054 | E160: 10000 | F160: =E160-G160 -> 0 | G160: 10000 | H160: =G160-I160 -> 0 | I160: =IF(G160="120元/天",_xlfn.XLOOKUP(B160,'202604考勤'!B:B,'202604考勤'!AI:AI,"无")*120,IF(S160="转正",ROUND(G160/DAY(EOMONTH(T160,0))*(DAY(EOMONTH(T160,0))-DAY(T160)+1)+(G160*0.8)/DAY(EOMONTH(T160,0))*(DAY(T160)-1),2),IF(OR(AND(S160="入职",DAY(T160)=1),AND(S160="离职",T160=EOMONTH(T160,0))),G160,IF(OR(S160="离职",S160="入职"),ROUND(G160/21.75*_xlfn.XLOOKUP(B160,'202604考勤'!B:B,'202604考勤'!AI:AI,0),2),G160)))) -> 10000 | J160: 员工 | K160: {=ROUND(_xlfn.IFS(OR(J160="南京大学",J160="BOSS",J160="实习生",J160="人力劳务"),I160,J160="部门负责人",I160*0.6,J160="员工",I160*0.7),2)} -> 7000 | L160: {=ROUND(_xlfn.IFS(OR(J160="南京大学",J160="BOSS",J160="实习生",J160="人力劳务"),I160*0,J160="部门负责人",I160*0.4,J160="员工",I160*0.3),2)} -> 3000 | M160: C | N160: {=ROUND(_xlfn.IFS(M160="A",L160*1.5,M160="B",L160*1.2,M160="C",L160*1,M160="D",L160*0.8,M160="E",L160*0.6,M160="无等级",L160*0),2)} -> 3000 | O160: =ROUND(K160+N160,2) -> 10000 | P160: 0 | Q160: =ROUND(O160+P160,2) -> 10000 | R160: =O160-I160 -> 0
A161: =ROW(A161)-15 -> 146 | B161: 一百四十六 | C161: 南大尚诚 | D161: 46054 | E161: 10000 | F161: =E161-G161 -> 0 | G161: 10000 | H161: =G161-I161 -> 0 | I161: =IF(G161="120元/天",_xlfn.XLOOKUP(B161,'202604考勤'!B:B,'202604考勤'!AI:AI,"无")*120,IF(S161="转正",ROUND(G161/DAY(EOMONTH(T161,0))*(DAY(EOMONTH(T161,0))-DAY(T161)+1)+(G161*0.8)/DAY(EOMONTH(T161,0))*(DAY(T161)-1),2),IF(OR(AND(S161="入职",DAY(T161)=1),AND(S161="离职",T161=EOMONTH(T161,0))),G161,IF(OR(S161="离职",S161="入职"),ROUND(G161/21.75*_xlfn.XLOOKUP(B161,'202604考勤'!B:B,'202604考勤'!AI:AI,0),2),G161)))) -> 10000 | J161: 员工 | K161: {=ROUND(_xlfn.IFS(OR(J161="南京大学",J161="BOSS",J161="实习生",J161="人力劳务"),I161,J161="部门负责人",I161*0.6,J161="员工",I161*0.7),2)} -> 7000 | L161: {=ROUND(_xlfn.IFS(OR(J161="南京大学",J161="BOSS",J161="实习生",J161="人力劳务"),I161*0,J161="部门负责人",I161*0.4,J161="员工",I161*0.3),2)} -> 3000 | M161: C | N161: {=ROUND(_xlfn.IFS(M161="A",L161*1.5,M161="B",L161*1.2,M161="C",L161*1,M161="D",L161*0.8,M161="E",L161*0.6,M161="无等级",L161*0),2)} -> 3000 | O161: =ROUND(K161+N161,2) -> 10000 | P161: 0 | Q161: =ROUND(O161+P161,2) -> 10000 | R161: =O161-I161 -> 0
A162: =ROW(A162)-15 -> 147 | B162: 一百四十七 | C162: 南大尚诚 | D162: 46054 | E162: 10000 | F162: =E162-G162 -> 0 | G162: 10000 | H162: =G162-I162 -> 0 | I162: =IF(G162="120元/天",_xlfn.XLOOKUP(B162,'202604考勤'!B:B,'202604考勤'!AI:AI,"无")*120,IF(S162="转正",ROUND(G162/DAY(EOMONTH(T162,0))*(DAY(EOMONTH(T162,0))-DAY(T162)+1)+(G162*0.8)/DAY(EOMONTH(T162,0))*(DAY(T162)-1),2),IF(OR(AND(S162="入职",DAY(T162)=1),AND(S162="离职",T162=EOMONTH(T162,0))),G162,IF(OR(S162="离职",S162="入职"),ROUND(G162/21.75*_xlfn.XLOOKUP(B162,'202604考勤'!B:B,'202604考勤'!AI:AI,0),2),G162)))) -> 10000 | J162: 员工 | K162: {=ROUND(_xlfn.IFS(OR(J162="南京大学",J162="BOSS",J162="实习生",J162="人力劳务"),I162,J162="部门负责人",I162*0.6,J162="员工",I162*0.7),2)} -> 7000 | L162: {=ROUND(_xlfn.IFS(OR(J162="南京大学",J162="BOSS",J162="实习生",J162="人力劳务"),I162*0,J162="部门负责人",I162*0.4,J162="员工",I162*0.3),2)} -> 3000 | M162: C | N162: {=ROUND(_xlfn.IFS(M162="A",L162*1.5,M162="B",L162*1.2,M162="C",L162*1,M162="D",L162*0.8,M162="E",L162*0.6,M162="无等级",L162*0),2)} -> 3000 | O162: =ROUND(K162+N162,2) -> 10000 | P162: 0 | Q162: =ROUND(O162+P162,2) -> 10000 | R162: =O162-I162 -> 0
...

Sheet 马骏老师202604
A1: 202604劳务费明细表
A2: 姓名 | B2: 公司 | C2: 含税劳务金额 | D2: 不含税劳务金额 | E2: 税额 | F2: 应纳税所得额 | G2: 代扣劳务个税 | H2: 实发金额 | P2: 起薪时间
A3: 马骏 | B3: 尚诚能源 | C3: 8000 | D3: =C3-E3 -> 7920.79 | E3: 79.21 | F3: =D3*0.8 -> 6336.632 | G3: =F3*0.2 -> 1267.3264 | H3: =C3-G3 -> 6732.6736 | I3: 南大老师税前8000 520102198009074214 18951991733 | P3: 45108
A4: 总经理： 财务负责人： 制表人：

Sheet 202604工资明细表（尚诚能源）
A1: 202604工资表
A2: 序号 | B2: 姓名 | C2: 起薪时间 | D2: 月薪基数 | E2: 系数 | F2: 实际应发工资 | G2: 基本养老保险费 | H2: 失业保险费 | I2: 基本医疗保险费 | J2: 大病保险费 | K2: 社保合计 | L2: 住房公积金 | M2: 专项累计扣除 | N2: 继续教育 | O2: 三岁以下婴幼儿 | P2: 子女教育 | Q2: 住房贷款利息 | R2: 住房租金 | S2: 赡养老人 | T2: 专项附加扣除合计 | U2: 税前扣除项目合计 | V2: 上月累计专项扣除合计 | W2: 累计扣除项目合计 | X2: 上月累计收入 | Y2: 累计收入 | Z2: 减除费用 | AA2: 税前工资 | AB2: 累计计税部分 | AC2: 累计个税 | AD2: 上月累计个税 | AE2: 本月个税 | AF2: 实发工资
A3: =ROW(A3)-2 -> 1 | B3: {=_xlfn.LET(_xlpm.B列,INDIRECT("'"&A1&"'!B3:B190"),_xlpm.C列,INDIRECT("'"&A1&"'!C3:C190"),_xlfn._xlws.FILTER(_xlpm.B列,(_xlpm.C列="尚诚能源")*(_xlpm.B列<>"")))} -> 一 | C3: {=_xlfn.XLOOKUP(B3,INDIRECT("'"&$A$1&"'!B:B"),INDIRECT("'"&$A$1&"'!D:D"),"人员不存在",0,1)} -> 44713 | D3: {=_xlfn.XLOOKUP(B3,INDIRECT("'"&$A$1&"'!B:B"),INDIRECT("'"&$A$1&"'!G:G"),"人员不存在",0,1)} -> 10000 | E3: =IFERROR(F3/D3,0) -> 1 | F3: {=_xlfn.XLOOKUP(B3,INDIRECT("'"&$A$1&"'!B:B"),INDIRECT("'"&$A$1&"'!Q:Q"),"人员不存在",0,1)} -> 10000 | G3: {=SUMIF(INDIRECT("'"&$G$47&"'!C5:C"&IFERROR(MATCH(TRUE,ISBLANK(INDIRECT("'"&$G$47&"'!C5:C500")),0)+4,500)),B3,INDIRECT("'"&$G$47&"'!K5:K"&IFERROR(MATCH(TRUE,ISBLANK(INDIRECT("'"&$G$47&"'!C5:C500")),0)+4,500)))} -> 0 | H3: {=SUMIF(INDIRECT("'"&$G$47&"'!C5:C"&IFERROR(MATCH(TRUE,ISBLANK(INDIRECT("'"&$G$47&"'!C5:C500")),0)+4,500)),B3,INDIRECT("'"&$G$47&"'!L5:L"&IFERROR(MATCH(TRUE,ISBLANK(INDIRECT("'"&$G$47&"'!C5:C500")),0)+4,500)))} -> 0 | I3: {=SUMIF(INDIRECT("'"&$G$47&"'!C5:C"&IFERROR(MATCH(TRUE,ISBLANK(INDIRECT("'"&$G$47&"'!C5:C500")),0)+4,500)),B3,INDIRECT("'"&$G$47&"'!M5:M"&IFERROR(MATCH(TRUE,ISBLANK(INDIRECT("'"&$G$47&"'!C5:C500")),0)+4,500)))} -> 0 | J3: {=SUMIF(INDIRECT("'"&$G$47&"'!C5:C"&IFERROR(MATCH(TRUE,ISBLANK(INDIRECT("'"&$G$47&"'!C5:C500")),0)+4,500)),B3,INDIRECT("'"&$G$47&"'!N5:N"&IFERROR(MATCH(TRUE,ISBLANK(INDIRECT("'"&$G$47&"'!C5:C500")),0)+4,500)))} -> 0 | K3: =SUM(G3:J3) -> 0 | L3: {=IFERROR(_xlfn.XLOOKUP(B3,INDIRECT("'"&$I$47&"'!B:B"),INDIRECT("'"&$I$47&"'!E:E"),0),0)} -> 0 | M3: =ROUND(SUM(K3:L3),2) -> 0 | N3: {=IFERROR(_xlfn.XLOOKUP(B3,INDIRECT("'"&$M$47&"'!B:B"),INDIRECT("'"&$M$47&"'!AC:AC"),0),0)} -> 0 | O3: {=IFERROR(_xlfn.XLOOKUP(B3,INDIRECT("'"&$M$47&"'!B:B"),INDIRECT("'"&$M$47&"'!AG:AG"),0),0)} -> 0 | P3: {=IFERROR(_xlfn.XLOOKUP(B3,INDIRECT("'"&$M$47&"'!B:B"),INDIRECT("'"&$M$47&"'!AB:AB"),0),0)} -> 0 | Q3: {=IFERROR(_xlfn.XLOOKUP(B3,INDIRECT("'"&$M$47&"'!B:B"),INDIRECT("'"&$M$47&"'!AD:AD"),0),0)} -> 0 | R3: {=IFERROR(_xlfn.XLOOKUP(B3,INDIRECT("'"&$M$47&"'!B:B"),INDIRECT("'"&$M$47&"'!AE:AE"),0),0)} -> 0 | S3: {=IFERROR(_xlfn.XLOOKUP(B3,INDIRECT("'"&$M$47&"'!B:B"),INDIRECT("'"&$M$47&"'!AF:AF"),0),0)} -> 0 | T3: =SUM(N3:S3) -> 0 | U3: =ROUND(SUM(M3:S3),2) -> 0 | V3: {=IFERROR(_xlfn.XLOOKUP(B3,INDIRECT("'"&$K$47&"'!B:B"),INDIRECT("'"&$K$47&"'!Y:Y"),0),0)} -> 0 | W3: =U3+V3 -> 0 | X3: {=IFERROR(_xlfn.XLOOKUP(B3,INDIRECT("'"&$K$47&"'!B:B"),INDIRECT("'"&$K$47&"'!Z:Z"),0),0)} -> 0 | Y3: =F3+X3 -> 10000 | Z3: {=IFERROR(_xlfn.LET(_xlpm.v,_xlfn.XLOOKUP(B3,INDIRECT("'"&$K$47&"'!B:B"),INDIRECT("'"&$K$47&"'!AA:AA"),0),IF(_xlpm.v=60000,60000,_xlpm.v+5000)),0)} -> 0 | AA3: =ROUND(F3-M3,2) -> 10000 | AB3: =IF(ROUND(Y3-W3-Z3,2)>0,ROUND(Y3-W3-Z3,2),0) -> 10000 | AC3: =ROUND(IF(AB3>960000,AB3*0.45-181920,IF(AB3>660000,AB3*0.35-85920,IF(AB3>420000,AB3*0.3-52920,IF(AB3>300000,AB3*0.25-31920,IF(AB3>144000,AB3*0.2-16920,IF(AB3>36000,AB3*0.1-2520,IF(AB3>0,AB3*0.03,0))))))),2) -> 300 | AD3: {=IFERROR(_xlfn.XLOOKUP(B3,INDIRECT("'"&$K$47&"'!B:B"),INDIRECT("'"&$K$47&"'!AD:AD"),0),0)} -> 0 | AE3: =ROUND(MAX(AC3-AD3,0),2) -> 300 | AF3: =ROUND(AA3-AE3,2) -> 9700
A4: =ROW(A4)-2 -> 2 | B4: 二 | C4: {=_xlfn.XLOOKUP(B4,INDIRECT("'"&$A$1&"'!B:B"),INDIRECT("'"&$A$1&"'!D:D"),"人员不存在",0,1)} -> 44805 | D4: {=_xlfn.XLOOKUP(B4,INDIRECT("'"&$A$1&"'!B:B"),INDIRECT("'"&$A$1&"'!G:G"),"人员不存在",0,1)} -> 10000 | E4: =IFERROR(F4/D4,0) -> 1 | F4: {=_xlfn.XLOOKUP(B4,INDIRECT("'"&$A$1&"'!B:B"),INDIRECT("'"&$A$1&"'!Q:Q"),"人员不存在",0,1)} -> 10000 | G4: {=SUMIF(INDIRECT("'"&$G$47&"'!C5:C"&IFERROR(MATCH(TRUE,ISBLANK(INDIRECT("'"&$G$47&"'!C5:C500")),0)+4,500)),B4,INDIRECT("'"&$G$47&"'!K5:K"&IFERROR(MATCH(TRUE,ISBLANK(INDIRECT("'"&$G$47&"'!C5:C500")),0)+4,500)))} -> 0 | H4: {=SUMIF(INDIRECT("'"&$G$47&"'!C5:C"&IFERROR(MATCH(TRUE,ISBLANK(INDIRECT("'"&$G$47&"'!C5:C500")),0)+4,500)),B4,INDIRECT("'"&$G$47&"'!L5:L"&IFERROR(MATCH(TRUE,ISBLANK(INDIRECT("'"&$G$47&"'!C5:C500")),0)+4,500)))} -> 0 | I4: {=SUMIF(INDIRECT("'"&$G$47&"'!C5:C"&IFERROR(MATCH(TRUE,ISBLANK(INDIRECT("'"&$G$47&"'!C5:C500")),0)+4,500)),B4,INDIRECT("'"&$G$47&"'!M5:M"&IFERROR(MATCH(TRUE,ISBLANK(INDIRECT("'"&$G$47&"'!C5:C500")),0)+4,500)))} -> 0 | J4: {=SUMIF(INDIRECT("'"&$G$47&"'!C5:C"&IFERROR(MATCH(TRUE,ISBLANK(INDIRECT("'"&$G$47&"'!C5:C500")),0)+4,500)),B4,INDIRECT("'"&$G$47&"'!N5:N"&IFERROR(MATCH(TRUE,ISBLANK(INDIRECT("'"&$G$47&"'!C5:C500")),0)+4,500)))} -> 0 | K4: =SUM(G4:J4) -> 0 | L4: {=IFERROR(_xlfn.XLOOKUP(B4,INDIRECT("'"&$I$47&"'!B:B"),INDIRECT("'"&$I$47&"'!E:E"),0),0)} -> 0 | M4: =ROUND(SUM(K4:L4),2) -> 0 | N4: {=IFERROR(_xlfn.XLOOKUP(B4,INDIRECT("'"&$M$47&"'!B:B"),INDIRECT("'"&$M$47&"'!AC:AC"),0),0)} -> 0 | O4: {=IFERROR(_xlfn.XLOOKUP(B4,INDIRECT("'"&$M$47&"'!B:B"),INDIRECT("'"&$M$47&"'!AG:AG"),0),0)} -> 0 | P4: {=IFERROR(_xlfn.XLOOKUP(B4,INDIRECT("'"&$M$47&"'!B:B"),INDIRECT("'"&$M$47&"'!AB:AB"),0),0)} -> 0 | Q4: {=IFERROR(_xlfn.XLOOKUP(B4,INDIRECT("'"&$M$47&"'!B:B"),INDIRECT("'"&$M$47&"'!AD:AD"),0),0)} -> 0 | R4: {=IFERROR(_xlfn.XLOOKUP(B4,INDIRECT("'"&$M$47&"'!B:B"),INDIRECT("'"&$M$47&"'!AE:AE"),0),0)} -> 0 | S4: {=IFERROR(_xlfn.XLOOKUP(B4,INDIRECT("'"&$M$47&"'!B:B"),INDIRECT("'"&$M$47&"'!AF:AF"),0),0)} -> 0 | T4: =SUM(N4:S4) -> 0 | U4: =ROUND(SUM(M4:S4),2) -> 0 | V4: {=IFERROR(_xlfn.XLOOKUP(B4,INDIRECT("'"&$K$47&"'!B:B"),INDIRECT("'"&$K$47&"'!Y:Y"),0),0)} -> 0 | W4: =U4+V4 -> 0 | X4: {=IFERROR(_xlfn.XLOOKUP(B4,INDIRECT("'"&$K$47&"'!B:B"),INDIRECT("'"&$K$47&"'!Z:Z"),0),0)} -> 0 | Y4: =F4+X4 -> 10000 | Z4: 0 | AA4: =ROUND(F4-M4,2) -> 10000 | AB4: =IF(ROUND(Y4-W4-Z4,2)>0,ROUND(Y4-W4-Z4,2),0) -> 10000 | AC4: =ROUND(IF(AB4>960000,AB4*0.45-181920,IF(AB4>660000,AB4*0.35-85920,IF(AB4>420000,AB4*0.3-52920,IF(AB4>300000,AB4*0.25-31920,IF(AB4>144000,AB4*0.2-16920,IF(AB4>36000,AB4*0.1-2520,IF(AB4>0,AB4*0.03,0))))))),2) -> 300 | AD4: {=IFERROR(_xlfn.XLOOKUP(B4,INDIRECT("'"&$K$47&"'!B:B"),INDIRECT("'"&$K$47&"'!AD:AD"),0),0)} -> 0 | AE4: =ROUND(MAX(AC4-AD4,0),2) -> 300 | AF4: =ROUND(AA4-AE4,2) -> 9700
A5: =ROW(A5)-2 -> 3 | B5: 三 | C5: {=_xlfn.XLOOKUP(B5,INDIRECT("'"&$A$1&"'!B:B"),INDIRECT("'"&$A$1&"'!D:D"),"人员不存在",0,1)} -> 44958 | D5: {=_xlfn.XLOOKUP(B5,INDIRECT("'"&$A$1&"'!B:B"),INDIRECT("'"&$A$1&"'!G:G"),"人员不存在",0,1)} -> 10000 | E5: =IFERROR(F5/D5,0) -> 1 | F5: {=_xlfn.XLOOKUP(B5,INDIRECT("'"&$A$1&"'!B:B"),INDIRECT("'"&$A$1&"'!Q:Q"),"人员不存在",0,1)} -> 10000 | G5: {=SUMIF(INDIRECT("'"&$G$47&"'!C5:C"&IFERROR(MATCH(TRUE,ISBLANK(INDIRECT("'"&$G$47&"'!C5:C500")),0)+4,500)),B5,INDIRECT("'"&$G$47&"'!K5:K"&IFERROR(MATCH(TRUE,ISBLANK(INDIRECT("'"&$G$47&"'!C5:C500")),0)+4,500)))} -> 0 | H5: {=SUMIF(INDIRECT("'"&$G$47&"'!C5:C"&IFERROR(MATCH(TRUE,ISBLANK(INDIRECT("'"&$G$47&"'!C5:C500")),0)+4,500)),B5,INDIRECT("'"&$G$47&"'!L5:L"&IFERROR(MATCH(TRUE,ISBLANK(INDIRECT("'"&$G$47&"'!C5:C500")),0)+4,500)))} -> 0 | I5: {=SUMIF(INDIRECT("'"&$G$47&"'!C5:C"&IFERROR(MATCH(TRUE,ISBLANK(INDIRECT("'"&$G$47&"'!C5:C500")),0)+4,500)),B5,INDIRECT("'"&$G$47&"'!M5:M"&IFERROR(MATCH(TRUE,ISBLANK(INDIRECT("'"&$G$47&"'!C5:C500")),0)+4,500)))} -> 0 | J5: {=SUMIF(INDIRECT("'"&$G$47&"'!C5:C"&IFERROR(MATCH(TRUE,ISBLANK(INDIRECT("'"&$G$47&"'!C5:C500")),0)+4,500)),B5,INDIRECT("'"&$G$47&"'!N5:N"&IFERROR(MATCH(TRUE,ISBLANK(INDIRECT("'"&$G$47&"'!C5:C500")),0)+4,500)))} -> 0 | K5: =SUM(G5:J5) -> 0 | L5: {=IFERROR(_xlfn.XLOOKUP(B5,INDIRECT("'"&$I$47&"'!B:B"),INDIRECT("'"&$I$47&"'!E:E"),0),0)} -> 0 | M5: =ROUND(SUM(K5:L5),2) -> 0 | N5: {=IFERROR(_xlfn.XLOOKUP(B5,INDIRECT("'"&$M$47&"'!B:B"),INDIRECT("'"&$M$47&"'!AC:AC"),0),0)} -> 0 | O5: {=IFERROR(_xlfn.XLOOKUP(B5,INDIRECT("'"&$M$47&"'!B:B"),INDIRECT("'"&$M$47&"'!AG:AG"),0),0)} -> 0 | P5: {=IFERROR(_xlfn.XLOOKUP(B5,INDIRECT("'"&$M$47&"'!B:B"),INDIRECT("'"&$M$47&"'!AB:AB"),0),0)} -> 0 | Q5: {=IFERROR(_xlfn.XLOOKUP(B5,INDIRECT("'"&$M$47&"'!B:B"),INDIRECT("'"&$M$47&"'!AD:AD"),0),0)} -> 0 | R5: {=IFERROR(_xlfn.XLOOKUP(B5,INDIRECT("'"&$M$47&"'!B:B"),INDIRECT("'"&$M$47&"'!AE:AE"),0),0)} -> 0 | S5: {=IFERROR(_xlfn.XLOOKUP(B5,INDIRECT("'"&$M$47&"'!B:B"),INDIRECT("'"&$M$47&"'!AF:AF"),0),0)} -> 0 | T5: =SUM(N5:S5) -> 0 | U5: =ROUND(SUM(M5:S5),2) -> 0 | V5: {=IFERROR(_xlfn.XLOOKUP(B5,INDIRECT("'"&$K$47&"'!B:B"),INDIRECT("'"&$K$47&"'!Y:Y"),0),0)} -> 0 | W5: =U5+V5 -> 0 | X5: {=IFERROR(_xlfn.XLOOKUP(B5,INDIRECT("'"&$K$47&"'!B:B"),INDIRECT("'"&$K$47&"'!Z:Z"),0),0)} -> 0 | Y5: =F5+X5 -> 10000 | Z5: {=IFERROR(_xlfn.LET(_xlpm.v,_xlfn.XLOOKUP(B5,INDIRECT("'"&$K$47&"'!B:B"),INDIRECT("'"&$K$47&"'!AA:AA"),0),IF(_xlpm.v=60000,60000,_xlpm.v+5000)),0)} -> 0 | AA5: =ROUND(F5-M5,2) -> 10000 | AB5: =IF(ROUND(Y5-W5-Z5,2)>0,ROUND(Y5-W5-Z5,2),0) -> 10000 | AC5: =ROUND(IF(AB5>960000,AB5*0.45-181920,IF(AB5>660000,AB5*0.35-85920,IF(AB5>420000,AB5*0.3-52920,IF(AB5>300000,AB5*0.25-31920,IF(AB5>144000,AB5*0.2-16920,IF(AB5>36000,AB5*0.1-2520,IF(AB5>0,AB5*0.03,0))))))),2) -> 300 | AD5: {=IFERROR(_xlfn.XLOOKUP(B5,INDIRECT("'"&$K$47&"'!B:B"),INDIRECT("'"&$K$47&"'!AD:AD"),0),0)} -> 0 | AE5: =ROUND(MAX(AC5-AD5,0),2) -> 300 | AF5: =ROUND(AA5-AE5,2) -> 9700
A6: =ROW(A6)-2 -> 4 | B6: 四 | C6: {=_xlfn.XLOOKUP(B6,INDIRECT("'"&$A$1&"'!B:B"),INDIRECT("'"&$A$1&"'!D:D"),"人员不存在",0,1)} -> 44986 | D6: {=_xlfn.XLOOKUP(B6,INDIRECT("'"&$A$1&"'!B:B"),INDIRECT("'"&$A$1&"'!G:G"),"人员不存在",0,1)} -> 10000 | E6: =IFERROR(F6/D6,0) -> 1 | F6: {=_xlfn.XLOOKUP(B6,INDIRECT("'"&$A$1&"'!B:B"),INDIRECT("'"&$A$1&"'!Q:Q"),"人员不存在",0,1)} -> 10000 | G6: {=SUMIF(INDIRECT("'"&$G$47&"'!C5:C"&IFERROR(MATCH(TRUE,ISBLANK(INDIRECT("'"&$G$47&"'!C5:C500")),0)+4,500)),B6,INDIRECT("'"&$G$47&"'!K5:K"&IFERROR(MATCH(TRUE,ISBLANK(INDIRECT("'"&$G$47&"'!C5:C500")),0)+4,500)))} -> 0 | H6: {=SUMIF(INDIRECT("'"&$G$47&"'!C5:C"&IFERROR(MATCH(TRUE,ISBLANK(INDIRECT("'"&$G$47&"'!C5:C500")),0)+4,500)),B6,INDIRECT("'"&$G$47&"'!L5:L"&IFERROR(MATCH(TRUE,ISBLANK(INDIRECT("'"&$G$47&"'!C5:C500")),0)+4,500)))} -> 0 | I6: {=SUMIF(INDIRECT("'"&$G$47&"'!C5:C"&IFERROR(MATCH(TRUE,ISBLANK(INDIRECT("'"&$G$47&"'!C5:C500")),0)+4,500)),B6,INDIRECT("'"&$G$47&"'!M5:M"&IFERROR(MATCH(TRUE,ISBLANK(INDIRECT("'"&$G$47&"'!C5:C500")),0)+4,500)))} -> 0 | J6: {=SUMIF(INDIRECT("'"&$G$47&"'!C5:C"&IFERROR(MATCH(TRUE,ISBLANK(INDIRECT("'"&$G$47&"'!C5:C500")),0)+4,500)),B6,INDIRECT("'"&$G$47&"'!N5:N"&IFERROR(MATCH(TRUE,ISBLANK(INDIRECT("'"&$G$47&"'!C5:C500")),0)+4,500)))} -> 0 | K6: =SUM(G6:J6) -> 0 | L6: {=IFERROR(_xlfn.XLOOKUP(B6,INDIRECT("'"&$I$47&"'!B:B"),INDIRECT("'"&$I$47&"'!E:E"),0),0)} -> 0 | M6: =ROUND(SUM(K6:L6),2) -> 0 | N6: {=IFERROR(_xlfn.XLOOKUP(B6,INDIRECT("'"&$M$47&"'!B:B"),INDIRECT("'"&$M$47&"'!AC:AC"),0),0)} -> 0 | O6: {=IFERROR(_xlfn.XLOOKUP(B6,INDIRECT("'"&$M$47&"'!B:B"),INDIRECT("'"&$M$47&"'!AG:AG"),0),0)} -> 0 | P6: {=IFERROR(_xlfn.XLOOKUP(B6,INDIRECT("'"&$M$47&"'!B:B"),INDIRECT("'"&$M$47&"'!AB:AB"),0),0)} -> 0 | Q6: {=IFERROR(_xlfn.XLOOKUP(B6,INDIRECT("'"&$M$47&"'!B:B"),INDIRECT("'"&$M$47&"'!AD:AD"),0),0)} -> 0 | R6: {=IFERROR(_xlfn.XLOOKUP(B6,INDIRECT("'"&$M$47&"'!B:B"),INDIRECT("'"&$M$47&"'!AE:AE"),0),0)} -> 0 | S6: {=IFERROR(_xlfn.XLOOKUP(B6,INDIRECT("'"&$M$47&"'!B:B"),INDIRECT("'"&$M$47&"'!AF:AF"),0),0)} -> 0 | T6: =SUM(N6:S6) -> 0 | U6: =ROUND(SUM(M6:S6),2) -> 0 | V6: {=IFERROR(_xlfn.XLOOKUP(B6,INDIRECT("'"&$K$47&"'!B:B"),INDIRECT("'"&$K$47&"'!Y:Y"),0),0)} -> 0 | W6: =U6+V6 -> 0 | X6: {=IFERROR(_xlfn.XLOOKUP(B6,INDIRECT("'"&$K$47&"'!B:B"),INDIRECT("'"&$K$47&"'!Z:Z"),0),0)} -> 0 | Y6: =F6+X6 -> 10000 | Z6: {=IFERROR(_xlfn.LET(_xlpm.v,_xlfn.XLOOKUP(B6,INDIRECT("'"&$K$47&"'!B:B"),INDIRECT("'"&$K$47&"'!AA:AA"),0),IF(_xlpm.v=60000,60000,_xlpm.v+5000)),0)} -> 0 | AA6: =ROUND(F6-M6,2) -> 10000 | AB6: =IF(ROUND(Y6-W6-Z6,2)>0,ROUND(Y6-W6-Z6,2),0) -> 10000 | AC6: =ROUND(IF(AB6>960000,AB6*0.45-181920,IF(AB6>660000,AB6*0.35-85920,IF(AB6>420000,AB6*0.3-52920,IF(AB6>300000,AB6*0.25-31920,IF(AB6>144000,AB6*0.2-16920,IF(AB6>36000,AB6*0.1-2520,IF(AB6>0,AB6*0.03,0))))))),2) -> 300 | AD6: {=IFERROR(_xlfn.XLOOKUP(B6,INDIRECT("'"&$K$47&"'!B:B"),INDIRECT("'"&$K$47&"'!AD:AD"),0),0)} -> 0 | AE6: =ROUND(MAX(AC6-AD6,0),2) -> 300 | AF6: =ROUND(AA6-AE6,2) -> 9700
A7: =ROW(A7)-2 -> 5 | B7: 五 | C7: {=_xlfn.XLOOKUP(B7,INDIRECT("'"&$A$1&"'!B:B"),INDIRECT("'"&$A$1&"'!D:D"),"人员不存在",0,1)} -> 45231 | D7: {=_xlfn.XLOOKUP(B7,INDIRECT("'"&$A$1&"'!B:B"),INDIRECT("'"&$A$1&"'!G:G"),"人员不存在",0,1)} -> 10000 | E7: =IFERROR(F7/D7,0) -> 1 | F7: {=_xlfn.XLOOKUP(B7,INDIRECT("'"&$A$1&"'!B:B"),INDIRECT("'"&$A$1&"'!Q:Q"),"人员不存在",0,1)} -> 10000 | G7: {=SUMIF(INDIRECT("'"&$G$47&"'!C5:C"&IFERROR(MATCH(TRUE,ISBLANK(INDIRECT("'"&$G$47&"'!C5:C500")),0)+4,500)),B7,INDIRECT("'"&$G$47&"'!K5:K"&IFERROR(MATCH(TRUE,ISBLANK(INDIRECT("'"&$G$47&"'!C5:C500")),0)+4,500)))} -> 0 | H7: {=SUMIF(INDIRECT("'"&$G$47&"'!C5:C"&IFERROR(MATCH(TRUE,ISBLANK(INDIRECT("'"&$G$47&"'!C5:C500")),0)+4,500)),B7,INDIRECT("'"&$G$47&"'!L5:L"&IFERROR(MATCH(TRUE,ISBLANK(INDIRECT("'"&$G$47&"'!C5:C500")),0)+4,500)))} -> 0 | I7: {=SUMIF(INDIRECT("'"&$G$47&"'!C5:C"&IFERROR(MATCH(TRUE,ISBLANK(INDIRECT("'"&$G$47&"'!C5:C500")),0)+4,500)),B7,INDIRECT("'"&$G$47&"'!M5:M"&IFERROR(MATCH(TRUE,ISBLANK(INDIRECT("'"&$G$47&"'!C5:C500")),0)+4,500)))} -> 0 | J7: {=SUMIF(INDIRECT("'"&$G$47&"'!C5:C"&IFERROR(MATCH(TRUE,ISBLANK(INDIRECT("'"&$G$47&"'!C5:C500")),0)+4,500)),B7,INDIRECT("'"&$G$47&"'!N5:N"&IFERROR(MATCH(TRUE,ISBLANK(INDIRECT("'"&$G$47&"'!C5:C500")),0)+4,500)))} -> 0 | K7: =SUM(G7:J7) -> 0 | L7: {=IFERROR(_xlfn.XLOOKUP(B7,INDIRECT("'"&$I$47&"'!B:B"),INDIRECT("'"&$I$47&"'!E:E"),0),0)} -> 0 | M7: =ROUND(SUM(K7:L7),2) -> 0 | N7: {=IFERROR(_xlfn.XLOOKUP(B7,INDIRECT("'"&$M$47&"'!B:B"),INDIRECT("'"&$M$47&"'!AC:AC"),0),0)} -> 0 | O7: {=IFERROR(_xlfn.XLOOKUP(B7,INDIRECT("'"&$M$47&"'!B:B"),INDIRECT("'"&$M$47&"'!AG:AG"),0),0)} -> 0 | P7: {=IFERROR(_xlfn.XLOOKUP(B7,INDIRECT("'"&$M$47&"'!B:B"),INDIRECT("'"&$M$47&"'!AB:AB"),0),0)} -> 0 | Q7: {=IFERROR(_xlfn.XLOOKUP(B7,INDIRECT("'"&$M$47&"'!B:B"),INDIRECT("'"&$M$47&"'!AD:AD"),0),0)} -> 0 | R7: {=IFERROR(_xlfn.XLOOKUP(B7,INDIRECT("'"&$M$47&"'!B:B"),INDIRECT("'"&$M$47&"'!AE:AE"),0),0)} -> 0 | S7: {=IFERROR(_xlfn.XLOOKUP(B7,INDIRECT("'"&$M$47&"'!B:B"),INDIRECT("'"&$M$47&"'!AF:AF"),0),0)} -> 0 | T7: =SUM(N7:S7) -> 0 | U7: =ROUND(SUM(M7:S7),2) -> 0 | V7: {=IFERROR(_xlfn.XLOOKUP(B7,INDIRECT("'"&$K$47&"'!B:B"),INDIRECT("'"&$K$47&"'!Y:Y"),0),0)} -> 0 | W7: =U7+V7 -> 0 | X7: {=IFERROR(_xlfn.XLOOKUP(B7,INDIRECT("'"&$K$47&"'!B:B"),INDIRECT("'"&$K$47&"'!Z:Z"),0),0)} -> 0 | Y7: =F7+X7 -> 10000 | Z7: {=IFERROR(_xlfn.LET(_xlpm.v,_xlfn.XLOOKUP(B7,INDIRECT("'"&$K$47&"'!B:B"),INDIRECT("'"&$K$47&"'!AA:AA"),0),IF(_xlpm.v=60000,60000,_xlpm.v+5000)),0)} -> 0 | AA7: =ROUND(F7-M7,2) -> 10000 | AB7: =IF(ROUND(Y7-W7-Z7,2)>0,ROUND(Y7-W7-Z7,2),0) -> 10000 | AC7: =ROUND(IF(AB7>960000,AB7*0.45-181920,IF(AB7>660000,AB7*0.35-85920,IF(AB7>420000,AB7*0.3-52920,IF(AB7>300000,AB7*0.25-31920,IF(AB7>144000,AB7*0.2-16920,IF(AB7>36000,AB7*0.1-2520,IF(AB7>0,AB7*0.03,0))))))),2) -> 300 | AD7: {=IFERROR(_xlfn.XLOOKUP(B7,INDIRECT("'"&$K$47&"'!B:B"),INDIRECT("'"&$K$47&"'!AD:AD"),0),0)} -> 0 | AE7: =ROUND(MAX(AC7-AD7,0),2) -> 300 | AF7: =ROUND(AA7-AE7,2) -> 9700
A8: =ROW(A8)-2 -> 6 | B8: 六 | C8: {=_xlfn.XLOOKUP(B8,INDIRECT("'"&$A$1&"'!B:B"),INDIRECT("'"&$A$1&"'!D:D"),"人员不存在",0,1)} -> 45658 | D8: {=_xlfn.XLOOKUP(B8,INDIRECT("'"&$A$1&"'!B:B"),INDIRECT("'"&$A$1&"'!G:G"),"人员不存在",0,1)} -> 10000 | E8: =IFERROR(F8/D8,0) -> 1 | F8: {=_xlfn.XLOOKUP(B8,INDIRECT("'"&$A$1&"'!B:B"),INDIRECT("'"&$A$1&"'!Q:Q"),"人员不存在",0,1)} -> 10000 | G8: {=SUMIF(INDIRECT("'"&$G$47&"'!C5:C"&IFERROR(MATCH(TRUE,ISBLANK(INDIRECT("'"&$G$47&"'!C5:C500")),0)+4,500)),B8,INDIRECT("'"&$G$47&"'!K5:K"&IFERROR(MATCH(TRUE,ISBLANK(INDIRECT("'"&$G$47&"'!C5:C500")),0)+4,500)))} -> 0 | H8: {=SUMIF(INDIRECT("'"&$G$47&"'!C5:C"&IFERROR(MATCH(TRUE,ISBLANK(INDIRECT("'"&$G$47&"'!C5:C500")),0)+4,500)),B8,INDIRECT("'"&$G$47&"'!L5:L"&IFERROR(MATCH(TRUE,ISBLANK(INDIRECT("'"&$G$47&"'!C5:C500")),0)+4,500)))} -> 0 | I8: {=SUMIF(INDIRECT("'"&$G$47&"'!C5:C"&IFERROR(MATCH(TRUE,ISBLANK(INDIRECT("'"&$G$47&"'!C5:C500")),0)+4,500)),B8,INDIRECT("'"&$G$47&"'!M5:M"&IFERROR(MATCH(TRUE,ISBLANK(INDIRECT("'"&$G$47&"'!C5:C500")),0)+4,500)))} -> 0 | J8: {=SUMIF(INDIRECT("'"&$G$47&"'!C5:C"&IFERROR(MATCH(TRUE,ISBLANK(INDIRECT("'"&$G$47&"'!C5:C500")),0)+4,500)),B8,INDIRECT("'"&$G$47&"'!N5:N"&IFERROR(MATCH(TRUE,ISBLANK(INDIRECT("'"&$G$47&"'!C5:C500")),0)+4,500)))} -> 0 | K8: =SUM(G8:J8) -> 0 | L8: {=IFERROR(_xlfn.XLOOKUP(B8,INDIRECT("'"&$I$47&"'!B:B"),INDIRECT("'"&$I$47&"'!E:E"),0),0)} -> 0 | M8: =ROUND(SUM(K8:L8),2) -> 0 | N8: {=IFERROR(_xlfn.XLOOKUP(B8,INDIRECT("'"&$M$47&"'!B:B"),INDIRECT("'"&$M$47&"'!AC:AC"),0),0)} -> 0 | O8: {=IFERROR(_xlfn.XLOOKUP(B8,INDIRECT("'"&$M$47&"'!B:B"),INDIRECT("'"&$M$47&"'!AG:AG"),0),0)} -> 0 | P8: {=IFERROR(_xlfn.XLOOKUP(B8,INDIRECT("'"&$M$47&"'!B:B"),INDIRECT("'"&$M$47&"'!AB:AB"),0),0)} -> 0 | Q8: {=IFERROR(_xlfn.XLOOKUP(B8,INDIRECT("'"&$M$47&"'!B:B"),INDIRECT("'"&$M$47&"'!AD:AD"),0),0)} -> 0 | R8: {=IFERROR(_xlfn.XLOOKUP(B8,INDIRECT("'"&$M$47&"'!B:B"),INDIRECT("'"&$M$47&"'!AE:AE"),0),0)} -> 0 | S8: {=IFERROR(_xlfn.XLOOKUP(B8,INDIRECT("'"&$M$47&"'!B:B"),INDIRECT("'"&$M$47&"'!AF:AF"),0),0)} -> 0 | T8: =SUM(N8:S8) -> 0 | U8: =ROUND(SUM(M8:S8),2) -> 0 | V8: {=IFERROR(_xlfn.XLOOKUP(B8,INDIRECT("'"&$K$47&"'!B:B"),INDIRECT("'"&$K$47&"'!Y:Y"),0),0)} -> 0 | W8: =U8+V8 -> 0 | X8: {=IFERROR(_xlfn.XLOOKUP(B8,INDIRECT("'"&$K$47&"'!B:B"),INDIRECT("'"&$K$47&"'!Z:Z"),0),0)} -> 0 | Y8: =F8+X8 -> 10000 | Z8: {=IFERROR(_xlfn.LET(_xlpm.v,_xlfn.XLOOKUP(B8,INDIRECT("'"&$K$47&"'!B:B"),INDIRECT("'"&$K$47&"'!AA:AA"),0),IF(_xlpm.v=60000,60000,_xlpm.v+5000)),0)} -> 0 | AA8: =ROUND(F8-M8,2) -> 10000 | AB8: =IF(ROUND(Y8-W8-Z8,2)>0,ROUND(Y8-W8-Z8,2),0) -> 10000 | AC8: =ROUND(IF(AB8>960000,AB8*0.45-181920,IF(AB8>660000,AB8*0.35-85920,IF(AB8>420000,AB8*0.3-52920,IF(AB8>300000,AB8*0.25-31920,IF(AB8>144000,AB8*0.2-16920,IF(AB8>36000,AB8*0.1-2520,IF(AB8>0,AB8*0.03,0))))))),2) -> 300 | AD8: {=IFERROR(_xlfn.XLOOKUP(B8,INDIRECT("'"&$K$47&"'!B:B"),INDIRECT("'"&$K$47&"'!AD:AD"),0),0)} -> 0 | AE8: =ROUND(MAX(AC8-AD8,0),2) -> 300 | AF8: =ROUND(AA8-AE8,2) -> 9700
A9: =ROW(A9)-2 -> 7 | B9: 七 | C9: {=_xlfn.XLOOKUP(B9,INDIRECT("'"&$A$1&"'!B:B"),INDIRECT("'"&$A$1&"'!D:D"),"人员不存在",0,1)} -> 45658 | D9: {=_xlfn.XLOOKUP(B9,INDIRECT("'"&$A$1&"'!B:B"),INDIRECT("'"&$A$1&"'!G:G"),"人员不存在",0,1)} -> 10000 | E9: =IFERROR(F9/D9,0) -> 1 | F9: {=_xlfn.XLOOKUP(B9,INDIRECT("'"&$A$1&"'!B:B"),INDIRECT("'"&$A$1&"'!Q:Q"),"人员不存在",0,1)} -> 10000 | G9: {=SUMIF(INDIRECT("'"&$G$47&"'!C5:C"&IFERROR(MATCH(TRUE,ISBLANK(INDIRECT("'"&$G$47&"'!C5:C500")),0)+4,500)),B9,INDIRECT("'"&$G$47&"'!K5:K"&IFERROR(MATCH(TRUE,ISBLANK(INDIRECT("'"&$G$47&"'!C5:C500")),0)+4,500)))} -> 0 | H9: {=SUMIF(INDIRECT("'"&$G$47&"'!C5:C"&IFERROR(MATCH(TRUE,ISBLANK(INDIRECT("'"&$G$47&"'!C5:C500")),0)+4,500)),B9,INDIRECT("'"&$G$47&"'!L5:L"&IFERROR(MATCH(TRUE,ISBLANK(INDIRECT("'"&$G$47&"'!C5:C500")),0)+4,500)))} -> 0 | I9: {=SUMIF(INDIRECT("'"&$G$47&"'!C5:C"&IFERROR(MATCH(TRUE,ISBLANK(INDIRECT("'"&$G$47&"'!C5:C500")),0)+4,500)),B9,INDIRECT("'"&$G$47&"'!M5:M"&IFERROR(MATCH(TRUE,ISBLANK(INDIRECT("'"&$G$47&"'!C5:C500")),0)+4,500)))} -> 0 | J9: {=SUMIF(INDIRECT("'"&$G$47&"'!C5:C"&IFERROR(MATCH(TRUE,ISBLANK(INDIRECT("'"&$G$47&"'!C5:C500")),0)+4,500)),B9,INDIRECT("'"&$G$47&"'!N5:N"&IFERROR(MATCH(TRUE,ISBLANK(INDIRECT("'"&$G$47&"'!C5:C500")),0)+4,500)))} -> 0 | K9: =SUM(G9:J9) -> 0 | L9: {=IFERROR(_xlfn.XLOOKUP(B9,INDIRECT("'"&$I$47&"'!B:B"),INDIRECT("'"&$I$47&"'!E:E"),0),0)} -> 0 | M9: =ROUND(SUM(K9:L9),2) -> 0 | N9: {=IFERROR(_xlfn.XLOOKUP(B9,INDIRECT("'"&$M$47&"'!B:B"),INDIRECT("'"&$M$47&"'!AC:AC"),0),0)} -> 0 | O9: {=IFERROR(_xlfn.XLOOKUP(B9,INDIRECT("'"&$M$47&"'!B:B"),INDIRECT("'"&$M$47&"'!AG:AG"),0),0)} -> 0 | P9: {=IFERROR(_xlfn.XLOOKUP(B9,INDIRECT("'"&$M$47&"'!B:B"),INDIRECT("'"&$M$47&"'!AB:AB"),0),0)} -> 0 | Q9: {=IFERROR(_xlfn.XLOOKUP(B9,INDIRECT("'"&$M$47&"'!B:B"),INDIRECT("'"&$M$47&"'!AD:AD"),0),0)} -> 0 | R9: {=IFERROR(_xlfn.XLOOKUP(B9,INDIRECT("'"&$M$47&"'!B:B"),INDIRECT("'"&$M$47&"'!AE:AE"),0),0)} -> 0 | S9: {=IFERROR(_xlfn.XLOOKUP(B9,INDIRECT("'"&$M$47&"'!B:B"),INDIRECT("'"&$M$47&"'!AF:AF"),0),0)} -> 0 | T9: =SUM(N9:S9) -> 0 | U9: =ROUND(SUM(M9:S9),2) -> 0 | V9: {=IFERROR(_xlfn.XLOOKUP(B9,INDIRECT("'"&$K$47&"'!B:B"),INDIRECT("'"&$K$47&"'!Y:Y"),0),0)} -> 0 | W9: =U9+V9 -> 0 | X9: {=IFERROR(_xlfn.XLOOKUP(B9,INDIRECT("'"&$K$47&"'!B:B"),INDIRECT("'"&$K$47&"'!Z:Z"),0),0)} -> 0 | Y9: =F9+X9 -> 10000 | Z9: {=IFERROR(_xlfn.LET(_xlpm.v,_xlfn.XLOOKUP(B9,INDIRECT("'"&$K$47&"'!B:B"),INDIRECT("'"&$K$47&"'!AA:AA"),0),IF(_xlpm.v=60000,60000,_xlpm.v+5000)),0)} -> 0 | AA9: =ROUND(F9-M9,2) -> 10000 | AB9: =IF(ROUND(Y9-W9-Z9,2)>0,ROUND(Y9-W9-Z9,2),0) -> 10000 | AC9: =ROUND(IF(AB9>960000,AB9*0.45-181920,IF(AB9>660000,AB9*0.35-85920,IF(AB9>420000,AB9*0.3-52920,IF(AB9>300000,AB9*0.25-31920,IF(AB9>144000,AB9*0.2-16920,IF(AB9>36000,AB9*0.1-2520,IF(AB9>0,AB9*0.03,0))))))),2) -> 300 | AD9: {=IFERROR(_xlfn.XLOOKUP(B9,INDIRECT("'"&$K$47&"'!B:B"),INDIRECT("'"&$K$47&"'!AD:AD"),0),0)} -> 0 | AE9: =ROUND(MAX(AC9-AD9,0),2) -> 300 | AF9: =ROUND(AA9-AE9,2) -> 9700
A10: =ROW(A10)-2 -> 8 | B10: 八 | C10: {=_xlfn.XLOOKUP(B10,INDIRECT("'"&$A$1&"'!B:B"),INDIRECT("'"&$A$1&"'!D:D"),"人员不存在",0,1)} -> 45809 | D10: {=_xlfn.XLOOKUP(B10,INDIRECT("'"&$A$1&"'!B:B"),INDIRECT("'"&$A$1&"'!G:G"),"人员不存在",0,1)} -> 10000 | E10: =IFERROR(F10/D10,0) -> 1 | F10: {=_xlfn.XLOOKUP(B10,INDIRECT("'"&$A$1&"'!B:B"),INDIRECT("'"&$A$1&"'!Q:Q"),"人员不存在",0,1)} -> 10000 | G10: {=SUMIF(INDIRECT("'"&$G$47&"'!C5:C"&IFERROR(MATCH(TRUE,ISBLANK(INDIRECT("'"&$G$47&"'!C5:C500")),0)+4,500)),B10,INDIRECT("'"&$G$47&"'!K5:K"&IFERROR(MATCH(TRUE,ISBLANK(INDIRECT("'"&$G$47&"'!C5:C500")),0)+4,500)))} -> 0 | H10: {=SUMIF(INDIRECT("'"&$G$47&"'!C5:C"&IFERROR(MATCH(TRUE,ISBLANK(INDIRECT("'"&$G$47&"'!C5:C500")),0)+4,500)),B10,INDIRECT("'"&$G$47&"'!L5:L"&IFERROR(MATCH(TRUE,ISBLANK(INDIRECT("'"&$G$47&"'!C5:C500")),0)+4,500)))} -> 0 | I10: {=SUMIF(INDIRECT("'"&$G$47&"'!C5:C"&IFERROR(MATCH(TRUE,ISBLANK(INDIRECT("'"&$G$47&"'!C5:C500")),0)+4,500)),B10,INDIRECT("'"&$G$47&"'!M5:M"&IFERROR(MATCH(TRUE,ISBLANK(INDIRECT("'"&$G$47&"'!C5:C500")),0)+4,500)))} -> 0 | J10: {=SUMIF(INDIRECT("'"&$G$47&"'!C5:C"&IFERROR(MATCH(TRUE,ISBLANK(INDIRECT("'"&$G$47&"'!C5:C500")),0)+4,500)),B10,INDIRECT("'"&$G$47&"'!N5:N"&IFERROR(MATCH(TRUE,ISBLANK(INDIRECT("'"&$G$47&"'!C5:C500")),0)+4,500)))} -> 0 | K10: =SUM(G10:J10) -> 0 | L10: {=IFERROR(_xlfn.XLOOKUP(B10,INDIRECT("'"&$I$47&"'!B:B"),INDIRECT("'"&$I$47&"'!E:E"),0),0)} -> 0 | M10: =ROUND(SUM(K10:L10),2) -> 0 | N10: {=IFERROR(_xlfn.XLOOKUP(B10,INDIRECT("'"&$M$47&"'!B:B"),INDIRECT("'"&$M$47&"'!AC:AC"),0),0)} -> 0 | O10: {=IFERROR(_xlfn.XLOOKUP(B10,INDIRECT("'"&$M$47&"'!B:B"),INDIRECT("'"&$M$47&"'!AG:AG"),0),0)} -> 0 | P10: {=IFERROR(_xlfn.XLOOKUP(B10,INDIRECT("'"&$M$47&"'!B:B"),INDIRECT("'"&$M$47&"'!AB:AB"),0),0)} -> 0 | Q10: {=IFERROR(_xlfn.XLOOKUP(B10,INDIRECT("'"&$M$47&"'!B:B"),INDIRECT("'"&$M$47&"'!AD:AD"),0),0)} -> 0 | R10: {=IFERROR(_xlfn.XLOOKUP(B10,INDIRECT("'"&$M$47&"'!B:B"),INDIRECT("'"&$M$47&"'!AE:AE"),0),0)} -> 0 | S10: {=IFERROR(_xlfn.XLOOKUP(B10,INDIRECT("'"&$M$47&"'!B:B"),INDIRECT("'"&$M$47&"'!AF:AF"),0),0)} -> 0 | T10: =SUM(N10:S10) -> 0 | U10: =ROUND(SUM(M10:S10),2) -> 0 | V10: {=IFERROR(_xlfn.XLOOKUP(B10,INDIRECT("'"&$K$47&"'!B:B"),INDIRECT("'"&$K$47&"'!Y:Y"),0),0)} -> 0 | W10: =U10+V10 -> 0 | X10: {=IFERROR(_xlfn.XLOOKUP(B10,INDIRECT("'"&$K$47&"'!B:B"),INDIRECT("'"&$K$47&"'!Z:Z"),0),0)} -> 0 | Y10: =F10+X10 -> 10000 | Z10: {=IFERROR(_xlfn.LET(_xlpm.v,_xlfn.XLOOKUP(B10,INDIRECT("'"&$K$47&"'!B:B"),INDIRECT("'"&$K$47&"'!AA:AA"),0),IF(_xlpm.v=60000,60000,_xlpm.v+5000)),0)} -> 0 | AA10: =ROUND(F10-M10,2) -> 10000 | AB10: =IF(ROUND(Y10-W10-Z10,2)>0,ROUND(Y10-W10-Z10,2),0) -> 10000 | AC10: =ROUND(IF(AB10>960000,AB10*0.45-181920,IF(AB10>660000,AB10*0.35-85920,IF(AB10>420000,AB10*0.3-52920,IF(AB10>300000,AB10*0.25-31920,IF(AB10>144000,AB10*0.2-16920,IF(AB10>36000,AB10*0.1-2520,IF(AB10>0,AB10*0.03,0))))))),2) -> 300 | AD10: {=IFERROR(_xlfn.XLOOKUP(B10,INDIRECT("'"&$K$47&"'!B:B"),INDIRECT("'"&$K$47&"'!AD:AD"),0),0)} -> 0 | AE10: =ROUND(MAX(AC10-AD10,0),2) -> 300 | AF10: =ROUND(AA10-AE10,2) -> 9700
A11: =ROW(A11)-2 -> 9 | B11: 九 | C11: {=_xlfn.XLOOKUP(B11,INDIRECT("'"&$A$1&"'!B:B"),INDIRECT("'"&$A$1&"'!D:D"),"人员不存在",0,1)} -> 45809 | D11: {=_xlfn.XLOOKUP(B11,INDIRECT("'"&$A$1&"'!B:B"),INDIRECT("'"&$A$1&"'!G:G"),"人员不存在",0,1)} -> 10000 | E11: =IFERROR(F11/D11,0) -> 1 | F11: {=_xlfn.XLOOKUP(B11,INDIRECT("'"&$A$1&"'!B:B"),INDIRECT("'"&$A$1&"'!Q:Q"),"人员不存在",0,1)} -> 10000 | G11: {=SUMIF(INDIRECT("'"&$G$47&"'!C5:C"&IFERROR(MATCH(TRUE,ISBLANK(INDIRECT("'"&$G$47&"'!C5:C500")),0)+4,500)),B11,INDIRECT("'"&$G$47&"'!K5:K"&IFERROR(MATCH(TRUE,ISBLANK(INDIRECT("'"&$G$47&"'!C5:C500")),0)+4,500)))} -> 0 | H11: {=SUMIF(INDIRECT("'"&$G$47&"'!C5:C"&IFERROR(MATCH(TRUE,ISBLANK(INDIRECT("'"&$G$47&"'!C5:C500")),0)+4,500)),B11,INDIRECT("'"&$G$47&"'!L5:L"&IFERROR(MATCH(TRUE,ISBLANK(INDIRECT("'"&$G$47&"'!C5:C500")),0)+4,500)))} -> 0 | I11: {=SUMIF(INDIRECT("'"&$G$47&"'!C5:C"&IFERROR(MATCH(TRUE,ISBLANK(INDIRECT("'"&$G$47&"'!C5:C500")),0)+4,500)),B11,INDIRECT("'"&$G$47&"'!M5:M"&IFERROR(MATCH(TRUE,ISBLANK(INDIRECT("'"&$G$47&"'!C5:C500")),0)+4,500)))} -> 0 | J11: {=SUMIF(INDIRECT("'"&$G$47&"'!C5:C"&IFERROR(MATCH(TRUE,ISBLANK(INDIRECT("'"&$G$47&"'!C5:C500")),0)+4,500)),B11,INDIRECT("'"&$G$47&"'!N5:N"&IFERROR(MATCH(TRUE,ISBLANK(INDIRECT("'"&$G$47&"'!C5:C500")),0)+4,500)))} -> 0 | K11: =SUM(G11:J11) -> 0 | L11: {=IFERROR(_xlfn.XLOOKUP(B11,INDIRECT("'"&$I$47&"'!B:B"),INDIRECT("'"&$I$47&"'!E:E"),0),0)} -> 0 | M11: =ROUND(SUM(K11:L11),2) -> 0 | N11: {=IFERROR(_xlfn.XLOOKUP(B11,INDIRECT("'"&$M$47&"'!B:B"),INDIRECT("'"&$M$47&"'!AC:AC"),0),0)} -> 0 | O11: {=IFERROR(_xlfn.XLOOKUP(B11,INDIRECT("'"&$M$47&"'!B:B"),INDIRECT("'"&$M$47&"'!AG:AG"),0),0)} -> 0 | P11: {=IFERROR(_xlfn.XLOOKUP(B11,INDIRECT("'"&$M$47&"'!B:B"),INDIRECT("'"&$M$47&"'!AB:AB"),0),0)} -> 0 | Q11: {=IFERROR(_xlfn.XLOOKUP(B11,INDIRECT("'"&$M$47&"'!B:B"),INDIRECT("'"&$M$47&"'!AD:AD"),0),0)} -> 0 | R11: {=IFERROR(_xlfn.XLOOKUP(B11,INDIRECT("'"&$M$47&"'!B:B"),INDIRECT("'"&$M$47&"'!AE:AE"),0),0)} -> 0 | S11: {=IFERROR(_xlfn.XLOOKUP(B11,INDIRECT("'"&$M$47&"'!B:B"),INDIRECT("'"&$M$47&"'!AF:AF"),0),0)} -> 0 | T11: =SUM(N11:S11) -> 0 | U11: =ROUND(SUM(M11:S11),2) -> 0 | V11: {=IFERROR(_xlfn.XLOOKUP(B11,INDIRECT("'"&$K$47&"'!B:B"),INDIRECT("'"&$K$47&"'!Y:Y"),0),0)} -> 0 | W11: =U11+V11 -> 0 | X11: {=IFERROR(_xlfn.XLOOKUP(B11,INDIRECT("'"&$K$47&"'!B:B"),INDIRECT("'"&$K$47&"'!Z:Z"),0),0)} -> 0 | Y11: =F11+X11 -> 10000 | Z11: {=IFERROR(_xlfn.LET(_xlpm.v,_xlfn.XLOOKUP(B11,INDIRECT("'"&$K$47&"'!B:B"),INDIRECT("'"&$K$47&"'!AA:AA"),0),IF(_xlpm.v=60000,60000,_xlpm.v+5000)),0)} -> 0 | AA11: =ROUND(F11-M11,2) -> 10000 | AB11: =IF(ROUND(Y11-W11-Z11,2)>0,ROUND(Y11-W11-Z11,2),0) -> 10000 | AC11: =ROUND(IF(AB11>960000,AB11*0.45-181920,IF(AB11>660000,AB11*0.35-85920,IF(AB11>420000,AB11*0.3-52920,IF(AB11>300000,AB11*0.25-31920,IF(AB11>144000,AB11*0.2-16920,IF(AB11>36000,AB11*0.1-2520,IF(AB11>0,AB11*0.03,0))))))),2) -> 300 | AD11: {=IFERROR(_xlfn.XLOOKUP(B11,INDIRECT("'"&$K$47&"'!B:B"),INDIRECT("'"&$K$47&"'!AD:AD"),0),0)} -> 0 | AE11: =ROUND(MAX(AC11-AD11,0),2) -> 300 | AF11: =ROUND(AA11-AE11,2) -> 9700
A12: =ROW(A12)-2 -> 10 | B12: 一十 | C12: {=_xlfn.XLOOKUP(B12,INDIRECT("'"&$A$1&"'!B:B"),INDIRECT("'"&$A$1&"'!D:D"),"人员不存在",0,1)} -> 45870 | D12: {=_xlfn.XLOOKUP(B12,INDIRECT("'"&$A$1&"'!B:B"),INDIRECT("'"&$A$1&"'!G:G"),"人员不存在",0,1)} -> 10000 | E12: =IFERROR(F12/D12,0) -> 1 | F12: {=_xlfn.XLOOKUP(B12,INDIRECT("'"&$A$1&"'!B:B"),INDIRECT("'"&$A$1&"'!Q:Q"),"人员不存在",0,1)} -> 10000 | G12: {=SUMIF(INDIRECT("'"&$G$47&"'!C5:C"&IFERROR(MATCH(TRUE,ISBLANK(INDIRECT("'"&$G$47&"'!C5:C500")),0)+4,500)),B12,INDIRECT("'"&$G$47&"'!K5:K"&IFERROR(MATCH(TRUE,ISBLANK(INDIRECT("'"&$G$47&"'!C5:C500")),0)+4,500)))} -> 0 | H12: {=SUMIF(INDIRECT("'"&$G$47&"'!C5:C"&IFERROR(MATCH(TRUE,ISBLANK(INDIRECT("'"&$G$47&"'!C5:C500")),0)+4,500)),B12,INDIRECT("'"&$G$47&"'!L5:L"&IFERROR(MATCH(TRUE,ISBLANK(INDIRECT("'"&$G$47&"'!C5:C500")),0)+4,500)))} -> 0 | I12: {=SUMIF(INDIRECT("'"&$G$47&"'!C5:C"&IFERROR(MATCH(TRUE,ISBLANK(INDIRECT("'"&$G$47&"'!C5:C500")),0)+4,500)),B12,INDIRECT("'"&$G$47&"'!M5:M"&IFERROR(MATCH(TRUE,ISBLANK(INDIRECT("'"&$G$47&"'!C5:C500")),0)+4,500)))} -> 0 | J12: {=SUMIF(INDIRECT("'"&$G$47&"'!C5:C"&IFERROR(MATCH(TRUE,ISBLANK(INDIRECT("'"&$G$47&"'!C5:C500")),0)+4,500)),B12,INDIRECT("'"&$G$47&"'!N5:N"&IFERROR(MATCH(TRUE,ISBLANK(INDIRECT("'"&$G$47&"'!C5:C500")),0)+4,500)))} -> 0 | K12: =SUM(G12:J12) -> 0 | L12: {=IFERROR(_xlfn.XLOOKUP(B12,INDIRECT("'"&$I$47&"'!B:B"),INDIRECT("'"&$I$47&"'!E:E"),0),0)} -> 0 | M12: =ROUND(SUM(K12:L12),2) -> 0 | N12: {=IFERROR(_xlfn.XLOOKUP(B12,INDIRECT("'"&$M$47&"'!B:B"),INDIRECT("'"&$M$47&"'!AC:AC"),0),0)} -> 0 | O12: {=IFERROR(_xlfn.XLOOKUP(B12,INDIRECT("'"&$M$47&"'!B:B"),INDIRECT("'"&$M$47&"'!AG:AG"),0),0)} -> 0 | P12: {=IFERROR(_xlfn.XLOOKUP(B12,INDIRECT("'"&$M$47&"'!B:B"),INDIRECT("'"&$M$47&"'!AB:AB"),0),0)} -> 0 | Q12: {=IFERROR(_xlfn.XLOOKUP(B12,INDIRECT("'"&$M$47&"'!B:B"),INDIRECT("'"&$M$47&"'!AD:AD"),0),0)} -> 0 | R12: {=IFERROR(_xlfn.XLOOKUP(B12,INDIRECT("'"&$M$47&"'!B:B"),INDIRECT("'"&$M$47&"'!AE:AE"),0),0)} -> 0 | S12: {=IFERROR(_xlfn.XLOOKUP(B12,INDIRECT("'"&$M$47&"'!B:B"),INDIRECT("'"&$M$47&"'!AF:AF"),0),0)} -> 0 | T12: =SUM(N12:S12) -> 0 | U12: =ROUND(SUM(M12:S12),2) -> 0 | V12: {=IFERROR(_xlfn.XLOOKUP(B12,INDIRECT("'"&$K$47&"'!B:B"),INDIRECT("'"&$K$47&"'!Y:Y"),0),0)} -> 0 | W12: =U12+V12 -> 0 | X12: {=IFERROR(_xlfn.XLOOKUP(B12,INDIRECT("'"&$K$47&"'!B:B"),INDIRECT("'"&$K$47&"'!Z:Z"),0),0)} -> 0 | Y12: =F12+X12 -> 10000 | Z12: {=IFERROR(_xlfn.LET(_xlpm.v,_xlfn.XLOOKUP(B12,INDIRECT("'"&$K$47&"'!B:B"),INDIRECT("'"&$K$47&"'!AA:AA"),0),IF(_xlpm.v=60000,60000,_xlpm.v+5000)),0)} -> 0 | AA12: =ROUND(F12-M12,2) -> 10000 | AB12: =IF(ROUND(Y12-W12-Z12,2)>0,ROUND(Y12-W12-Z12,2),0) -> 10000 | AC12: =ROUND(IF(AB12>960000,AB12*0.45-181920,IF(AB12>660000,AB12*0.35-85920,IF(AB12>420000,AB12*0.3-52920,IF(AB12>300000,AB12*0.25-31920,IF(AB12>144000,AB12*0.2-16920,IF(AB12>36000,AB12*0.1-2520,IF(AB12>0,AB12*0.03,0))))))),2) -> 300 | AD12: {=IFERROR(_xlfn.XLOOKUP(B12,INDIRECT("'"&$K$47&"'!B:B"),INDIRECT("'"&$K$47&"'!AD:AD"),0),0)} -> 0 | AE12: =ROUND(MAX(AC12-AD12,0),2) -> 300 | AF12: =ROUND(AA12-AE12,2) -> 9700
A13: =ROW(A13)-2 -> 11 | B13: 一十一 | C13: {=_xlfn.XLOOKUP(B13,INDIRECT("'"&$A$1&"'!B:B"),INDIRECT("'"&$A$1&"'!D:D"),"人员不存在",0,1)} -> 45901 | D13: {=_xlfn.XLOOKUP(B13,INDIRECT("'"&$A$1&"'!B:B"),INDIRECT("'"&$A$1&"'!G:G"),"人员不存在",0,1)} -> 10000 | E13: =IFERROR(F13/D13,0) -> 1 | F13: {=_xlfn.XLOOKUP(B13,INDIRECT("'"&$A$1&"'!B:B"),INDIRECT("'"&$A$1&"'!Q:Q"),"人员不存在",0,1)} -> 10000 | G13: {=SUMIF(INDIRECT("'"&$G$47&"'!C5:C"&IFERROR(MATCH(TRUE,ISBLANK(INDIRECT("'"&$G$47&"'!C5:C500")),0)+4,500)),B13,INDIRECT("'"&$G$47&"'!K5:K"&IFERROR(MATCH(TRUE,ISBLANK(INDIRECT("'"&$G$47&"'!C5:C500")),0)+4,500)))} -> 0 | H13: {=SUMIF(INDIRECT("'"&$G$47&"'!C5:C"&IFERROR(MATCH(TRUE,ISBLANK(INDIRECT("'"&$G$47&"'!C5:C500")),0)+4,500)),B13,INDIRECT("'"&$G$47&"'!L5:L"&IFERROR(MATCH(TRUE,ISBLANK(INDIRECT("'"&$G$47&"'!C5:C500")),0)+4,500)))} -> 0 | I13: {=SUMIF(INDIRECT("'"&$G$47&"'!C5:C"&IFERROR(MATCH(TRUE,ISBLANK(INDIRECT("'"&$G$47&"'!C5:C500")),0)+4,500)),B13,INDIRECT("'"&$G$47&"'!M5:M"&IFERROR(MATCH(TRUE,ISBLANK(INDIRECT("'"&$G$47&"'!C5:C500")),0)+4,500)))} -> 0 | J13: {=SUMIF(INDIRECT("'"&$G$47&"'!C5:C"&IFERROR(MATCH(TRUE,ISBLANK(INDIRECT("'"&$G$47&"'!C5:C500")),0)+4,500)),B13,INDIRECT("'"&$G$47&"'!N5:N"&IFERROR(MATCH(TRUE,ISBLANK(INDIRECT("'"&$G$47&"'!C5:C500")),0)+4,500)))} -> 0 | K13: =SUM(G13:J13) -> 0 | L13: {=IFERROR(_xlfn.XLOOKUP(B13,INDIRECT("'"&$I$47&"'!B:B"),INDIRECT("'"&$I$47&"'!E:E"),0),0)} -> 0 | M13: =ROUND(SUM(K13:L13),2) -> 0 | N13: {=IFERROR(_xlfn.XLOOKUP(B13,INDIRECT("'"&$M$47&"'!B:B"),INDIRECT("'"&$M$47&"'!AC:AC"),0),0)} -> 0 | O13: {=IFERROR(_xlfn.XLOOKUP(B13,INDIRECT("'"&$M$47&"'!B:B"),INDIRECT("'"&$M$47&"'!AG:AG"),0),0)} -> 0 | P13: {=IFERROR(_xlfn.XLOOKUP(B13,INDIRECT("'"&$M$47&"'!B:B"),INDIRECT("'"&$M$47&"'!AB:AB"),0),0)} -> 0 | Q13: {=IFERROR(_xlfn.XLOOKUP(B13,INDIRECT("'"&$M$47&"'!B:B"),INDIRECT("'"&$M$47&"'!AD:AD"),0),0)} -> 0 | R13: {=IFERROR(_xlfn.XLOOKUP(B13,INDIRECT("'"&$M$47&"'!B:B"),INDIRECT("'"&$M$47&"'!AE:AE"),0),0)} -> 0 | S13: {=IFERROR(_xlfn.XLOOKUP(B13,INDIRECT("'"&$M$47&"'!B:B"),INDIRECT("'"&$M$47&"'!AF:AF"),0),0)} -> 0 | T13: =SUM(N13:S13) -> 0 | U13: =ROUND(SUM(M13:S13),2) -> 0 | V13: {=IFERROR(_xlfn.XLOOKUP(B13,INDIRECT("'"&$K$47&"'!B:B"),INDIRECT("'"&$K$47&"'!Y:Y"),0),0)} -> 0 | W13: =U13+V13 -> 0 | X13: {=IFERROR(_xlfn.XLOOKUP(B13,INDIRECT("'"&$K$47&"'!B:B"),INDIRECT("'"&$K$47&"'!Z:Z"),0),0)} -> 0 | Y13: =F13+X13 -> 10000 | Z13: {=IFERROR(_xlfn.LET(_xlpm.v,_xlfn.XLOOKUP(B13,INDIRECT("'"&$K$47&"'!B:B"),INDIRECT("'"&$K$47&"'!AA:AA"),0),IF(_xlpm.v=60000,60000,_xlpm.v+5000)),0)} -> 0 | AA13: =ROUND(F13-M13,2) -> 10000 | AB13: =IF(ROUND(Y13-W13-Z13,2)>0,ROUND(Y13-W13-Z13,2),0) -> 10000 | AC13: =ROUND(IF(AB13>960000,AB13*0.45-181920,IF(AB13>660000,AB13*0.35-85920,IF(AB13>420000,AB13*0.3-52920,IF(AB13>300000,AB13*0.25-31920,IF(AB13>144000,AB13*0.2-16920,IF(AB13>36000,AB13*0.1-2520,IF(AB13>0,AB13*0.03,0))))))),2) -> 300 | AD13: {=IFERROR(_xlfn.XLOOKUP(B13,INDIRECT("'"&$K$47&"'!B:B"),INDIRECT("'"&$K$47&"'!AD:AD"),0),0)} -> 0 | AE13: =ROUND(MAX(AC13-AD13,0),2) -> 300 | AF13: =ROUND(AA13-AE13,2) -> 9700
A14: =ROW(A14)-2 -> 12 | B14: 一十二 | C14: {=_xlfn.XLOOKUP(B14,INDIRECT("'"&$A$1&"'!B:B"),INDIRECT("'"&$A$1&"'!D:D"),"人员不存在",0,1)} -> 46023 | D14: {=_xlfn.XLOOKUP(B14,INDIRECT("'"&$A$1&"'!B:B"),INDIRECT("'"&$A$1&"'!G:G"),"人员不存在",0,1)} -> 10000 | E14: =IFERROR(F14/D14,0) -> 1 | F14: {=_xlfn.XLOOKUP(B14,INDIRECT("'"&$A$1&"'!B:B"),INDIRECT("'"&$A$1&"'!Q:Q"),"人员不存在",0,1)} -> 10000 | G14: {=SUMIF(INDIRECT("'"&$G$47&"'!C5:C"&IFERROR(MATCH(TRUE,ISBLANK(INDIRECT("'"&$G$47&"'!C5:C500")),0)+4,500)),B14,INDIRECT("'"&$G$47&"'!K5:K"&IFERROR(MATCH(TRUE,ISBLANK(INDIRECT("'"&$G$47&"'!C5:C500")),0)+4,500)))} -> 0 | H14: {=SUMIF(INDIRECT("'"&$G$47&"'!C5:C"&IFERROR(MATCH(TRUE,ISBLANK(INDIRECT("'"&$G$47&"'!C5:C500")),0)+4,500)),B14,INDIRECT("'"&$G$47&"'!L5:L"&IFERROR(MATCH(TRUE,ISBLANK(INDIRECT("'"&$G$47&"'!C5:C500")),0)+4,500)))} -> 0 | I14: {=SUMIF(INDIRECT("'"&$G$47&"'!C5:C"&IFERROR(MATCH(TRUE,ISBLANK(INDIRECT("'"&$G$47&"'!C5:C500")),0)+4,500)),B14,INDIRECT("'"&$G$47&"'!M5:M"&IFERROR(MATCH(TRUE,ISBLANK(INDIRECT("'"&$G$47&"'!C5:C500")),0)+4,500)))} -> 0 | J14: {=SUMIF(INDIRECT("'"&$G$47&"'!C5:C"&IFERROR(MATCH(TRUE,ISBLANK(INDIRECT("'"&$G$47&"'!C5:C500")),0)+4,500)),B14,INDIRECT("'"&$G$47&"'!N5:N"&IFERROR(MATCH(TRUE,ISBLANK(INDIRECT("'"&$G$47&"'!C5:C500")),0)+4,500)))} -> 0 | K14: =SUM(G14:J14) -> 0 | L14: {=IFERROR(_xlfn.XLOOKUP(B14,INDIRECT("'"&$I$47&"'!B:B"),INDIRECT("'"&$I$47&"'!E:E"),0),0)} -> 0 | M14: =ROUND(SUM(K14:L14),2) -> 0 | N14: {=IFERROR(_xlfn.XLOOKUP(B14,INDIRECT("'"&$M$47&"'!B:B"),INDIRECT("'"&$M$47&"'!AC:AC"),0),0)} -> 0 | O14: {=IFERROR(_xlfn.XLOOKUP(B14,INDIRECT("'"&$M$47&"'!B:B"),INDIRECT("'"&$M$47&"'!AG:AG"),0),0)} -> 0 | P14: {=IFERROR(_xlfn.XLOOKUP(B14,INDIRECT("'"&$M$47&"'!B:B"),INDIRECT("'"&$M$47&"'!AB:AB"),0),0)} -> 0 | Q14: {=IFERROR(_xlfn.XLOOKUP(B14,INDIRECT("'"&$M$47&"'!B:B"),INDIRECT("'"&$M$47&"'!AD:AD"),0),0)} -> 0 | R14: {=IFERROR(_xlfn.XLOOKUP(B14,INDIRECT("'"&$M$47&"'!B:B"),INDIRECT("'"&$M$47&"'!AE:AE"),0),0)} -> 0 | S14: {=IFERROR(_xlfn.XLOOKUP(B14,INDIRECT("'"&$M$47&"'!B:B"),INDIRECT("'"&$M$47&"'!AF:AF"),0),0)} -> 0 | T14: =SUM(N14:S14) -> 0 | U14: =ROUND(SUM(M14:S14),2) -> 0 | V14: {=IFERROR(_xlfn.XLOOKUP(B14,INDIRECT("'"&$K$47&"'!B:B"),INDIRECT("'"&$K$47&"'!Y:Y"),0),0)} -> 0 | W14: =U14+V14 -> 0 | X14: {=IFERROR(_xlfn.XLOOKUP(B14,INDIRECT("'"&$K$47&"'!B:B"),INDIRECT("'"&$K$47&"'!Z:Z"),0),0)} -> 0 | Y14: =F14+X14 -> 10000 | Z14: {=IFERROR(_xlfn.LET(_xlpm.v,_xlfn.XLOOKUP(B14,INDIRECT("'"&$K$47&"'!B:B"),INDIRECT("'"&$K$47&"'!AA:AA"),0),IF(_xlpm.v=60000,60000,_xlpm.v+5000)),0)} -> 0 | AA14: =ROUND(F14-M14,2) -> 10000 | AB14: =IF(ROUND(Y14-W14-Z14,2)>0,ROUND(Y14-W14-Z14,2),0) -> 10000 | AC14: =ROUND(IF(AB14>960000,AB14*0.45-181920,IF(AB14>660000,AB14*0.35-85920,IF(AB14>420000,AB14*0.3-52920,IF(AB14>300000,AB14*0.25-31920,IF(AB14>144000,AB14*0.2-16920,IF(AB14>36000,AB14*0.1-2520,IF(AB14>0,AB14*0.03,0))))))),2) -> 300 | AD14: 150 | AE14: =ROUND(MAX(AC14-AD14,0),2) -> 150 | AF14: =ROUND(AA14-AE14,2) -> 9850
A15: =ROW(A15)-2 -> 13 | B15: 一十三 | C15: {=_xlfn.XLOOKUP(B15,INDIRECT("'"&$A$1&"'!B:B"),INDIRECT("'"&$A$1&"'!D:D"),"人员不存在",0,1)} -> 46054 | D15: {=_xlfn.XLOOKUP(B15,INDIRECT("'"&$A$1&"'!B:B"),INDIRECT("'"&$A$1&"'!G:G"),"人员不存在",0,1)} -> 10000 | E15: =IFERROR(F15/D15,0) -> 1 | F15: {=_xlfn.XLOOKUP(B15,INDIRECT("'"&$A$1&"'!B:B"),INDIRECT("'"&$A$1&"'!Q:Q"),"人员不存在",0,1)} -> 10000 | G15: {=SUMIF(INDIRECT("'"&$G$47&"'!C5:C"&IFERROR(MATCH(TRUE,ISBLANK(INDIRECT("'"&$G$47&"'!C5:C500")),0)+4,500)),B15,INDIRECT("'"&$G$47&"'!K5:K"&IFERROR(MATCH(TRUE,ISBLANK(INDIRECT("'"&$G$47&"'!C5:C500")),0)+4,500)))} -> 0 | H15: {=SUMIF(INDIRECT("'"&$G$47&"'!C5:C"&IFERROR(MATCH(TRUE,ISBLANK(INDIRECT("'"&$G$47&"'!C5:C500")),0)+4,500)),B15,INDIRECT("'"&$G$47&"'!L5:L"&IFERROR(MATCH(TRUE,ISBLANK(INDIRECT("'"&$G$47&"'!C5:C500")),0)+4,500)))} -> 0 | I15: {=SUMIF(INDIRECT("'"&$G$47&"'!C5:C"&IFERROR(MATCH(TRUE,ISBLANK(INDIRECT("'"&$G$47&"'!C5:C500")),0)+4,500)),B15,INDIRECT("'"&$G$47&"'!M5:M"&IFERROR(MATCH(TRUE,ISBLANK(INDIRECT("'"&$G$47&"'!C5:C500")),0)+4,500)))} -> 0 | J15: {=SUMIF(INDIRECT("'"&$G$47&"'!C5:C"&IFERROR(MATCH(TRUE,ISBLANK(INDIRECT("'"&$G$47&"'!C5:C500")),0)+4,500)),B15,INDIRECT("'"&$G$47&"'!N5:N"&IFERROR(MATCH(TRUE,ISBLANK(INDIRECT("'"&$G$47&"'!C5:C500")),0)+4,500)))} -> 0 | K15: =SUM(G15:J15) -> 0 | L15: {=IFERROR(_xlfn.XLOOKUP(B15,INDIRECT("'"&$I$47&"'!B:B"),INDIRECT("'"&$I$47&"'!E:E"),0),0)} -> 0 | M15: =ROUND(SUM(K15:L15),2) -> 0 | N15: {=IFERROR(_xlfn.XLOOKUP(B15,INDIRECT("'"&$M$47&"'!B:B"),INDIRECT("'"&$M$47&"'!AC:AC"),0),0)} -> 0 | O15: {=IFERROR(_xlfn.XLOOKUP(B15,INDIRECT("'"&$M$47&"'!B:B"),INDIRECT("'"&$M$47&"'!AG:AG"),0),0)} -> 0 | P15: {=IFERROR(_xlfn.XLOOKUP(B15,INDIRECT("'"&$M$47&"'!B:B"),INDIRECT("'"&$M$47&"'!AB:AB"),0),0)} -> 0 | Q15: {=IFERROR(_xlfn.XLOOKUP(B15,INDIRECT("'"&$M$47&"'!B:B"),INDIRECT("'"&$M$47&"'!AD:AD"),0),0)} -> 0 | R15: {=IFERROR(_xlfn.XLOOKUP(B15,INDIRECT("'"&$M$47&"'!B:B"),INDIRECT("'"&$M$47&"'!AE:AE"),0),0)} -> 0 | S15: {=IFERROR(_xlfn.XLOOKUP(B15,INDIRECT("'"&$M$47&"'!B:B"),INDIRECT("'"&$M$47&"'!AF:AF"),0),0)} -> 0 | T15: =SUM(N15:S15) -> 0 | U15: =ROUND(SUM(M15:S15),2) -> 0 | V15: {=IFERROR(_xlfn.XLOOKUP(B15,INDIRECT("'"&$K$47&"'!B:B"),INDIRECT("'"&$K$47&"'!Y:Y"),0),0)} -> 0 | W15: =U15+V15 -> 0 | X15: {=IFERROR(_xlfn.XLOOKUP(B15,INDIRECT("'"&$K$47&"'!B:B"),INDIRECT("'"&$K$47&"'!Z:Z"),0),0)} -> 0 | Y15: =F15+X15 -> 10000 | Z15: {=IFERROR(_xlfn.LET(_xlpm.v,_xlfn.XLOOKUP(B15,INDIRECT("'"&$K$47&"'!B:B"),INDIRECT("'"&$K$47&"'!AA:AA"),0),IF(_xlpm.v=60000,60000,_xlpm.v+5000)),0)} -> 0 | AA15: =ROUND(F15-M15,2) -> 10000 | AB15: =IF(ROUND(Y15-W15-Z15,2)>0,ROUND(Y15-W15-Z15,2),0) -> 10000 | AC15: =ROUND(IF(AB15>960000,AB15*0.45-181920,IF(AB15>660000,AB15*0.35-85920,IF(AB15>420000,AB15*0.3-52920,IF(AB15>300000,AB15*0.25-31920,IF(AB15>144000,AB15*0.2-16920,IF(AB15>36000,AB15*0.1-2520,IF(AB15>0,AB15*0.03,0))))))),2) -> 300 | AD15: {=IFERROR(_xlfn.XLOOKUP(B15,INDIRECT("'"&$K$47&"'!B:B"),INDIRECT("'"&$K$47&"'!AD:AD"),0),0)} -> 0 | AE15: =ROUND(MAX(AC15-AD15,0),2) -> 300 | AF15: =ROUND(AA15-AE15,2) -> 9700
A16: =ROW(A16)-2 -> 14 | B16: 二 | C16: {=_xlfn.XLOOKUP(B16,INDIRECT("'"&$A$1&"'!B:B"),INDIRECT("'"&$A$1&"'!D:D"),"人员不存在",0,1)} -> 44805 | D16: {=_xlfn.XLOOKUP(B16,INDIRECT("'"&$A$1&"'!B:B"),INDIRECT("'"&$A$1&"'!G:G"),"人员不存在",0,1)} -> 10000 | E16: =IFERROR(F16/D16,0) -> 1 | F16: {=_xlfn.XLOOKUP(B16,INDIRECT("'"&$A$1&"'!B:B"),INDIRECT("'"&$A$1&"'!Q:Q"),"人员不存在",0,1)} -> 10000 | G16: {=SUMIF(INDIRECT("'"&$G$47&"'!C5:C"&IFERROR(MATCH(TRUE,ISBLANK(INDIRECT("'"&$G$47&"'!C5:C500")),0)+4,500)),B16,INDIRECT("'"&$G$47&"'!K5:K"&IFERROR(MATCH(TRUE,ISBLANK(INDIRECT("'"&$G$47&"'!C5:C500")),0)+4,500)))} -> 0 | H16: {=SUMIF(INDIRECT("'"&$G$47&"'!C5:C"&IFERROR(MATCH(TRUE,ISBLANK(INDIRECT("'"&$G$47&"'!C5:C500")),0)+4,500)),B16,INDIRECT("'"&$G$47&"'!L5:L"&IFERROR(MATCH(TRUE,ISBLANK(INDIRECT("'"&$G$47&"'!C5:C500")),0)+4,500)))} -> 0 | I16: {=SUMIF(INDIRECT("'"&$G$47&"'!C5:C"&IFERROR(MATCH(TRUE,ISBLANK(INDIRECT("'"&$G$47&"'!C5:C500")),0)+4,500)),B16,INDIRECT("'"&$G$47&"'!M5:M"&IFERROR(MATCH(TRUE,ISBLANK(INDIRECT("'"&$G$47&"'!C5:C500")),0)+4,500)))} -> 0 | J16: {=SUMIF(INDIRECT("'"&$G$47&"'!C5:C"&IFERROR(MATCH(TRUE,ISBLANK(INDIRECT("'"&$G$47&"'!C5:C500")),0)+4,500)),B16,INDIRECT("'"&$G$47&"'!N5:N"&IFERROR(MATCH(TRUE,ISBLANK(INDIRECT("'"&$G$47&"'!C5:C500")),0)+4,500)))} -> 0 | K16: =SUM(G16:J16) -> 0 | L16: {=IFERROR(_xlfn.XLOOKUP(B16,INDIRECT("'"&$I$47&"'!B:B"),INDIRECT("'"&$I$47&"'!E:E"),0),0)} -> 0 | M16: =ROUND(SUM(K16:L16),2) -> 0 | N16: {=IFERROR(_xlfn.XLOOKUP(B16,INDIRECT("'"&$M$47&"'!B:B"),INDIRECT("'"&$M$47&"'!AC:AC"),0),0)} -> 0 | O16: {=IFERROR(_xlfn.XLOOKUP(B16,INDIRECT("'"&$M$47&"'!B:B"),INDIRECT("'"&$M$47&"'!AG:AG"),0),0)} -> 0 | P16: {=IFERROR(_xlfn.XLOOKUP(B16,INDIRECT("'"&$M$47&"'!B:B"),INDIRECT("'"&$M$47&"'!AB:AB"),0),0)} -> 0 | Q16: {=IFERROR(_xlfn.XLOOKUP(B16,INDIRECT("'"&$M$47&"'!B:B"),INDIRECT("'"&$M$47&"'!AD:AD"),0),0)} -> 0 | R16: {=IFERROR(_xlfn.XLOOKUP(B16,INDIRECT("'"&$M$47&"'!B:B"),INDIRECT("'"&$M$47&"'!AE:AE"),0),0)} -> 0 | S16: {=IFERROR(_xlfn.XLOOKUP(B16,INDIRECT("'"&$M$47&"'!B:B"),INDIRECT("'"&$M$47&"'!AF:AF"),0),0)} -> 0 | T16: =SUM(N16:S16) -> 0 | U16: =ROUND(SUM(M16:S16),2) -> 0 | V16: {=IFERROR(_xlfn.XLOOKUP(B16,INDIRECT("'"&$K$47&"'!B:B"),INDIRECT("'"&$K$47&"'!Y:Y"),0),0)} -> 0 | W16: =U16+V16 -> 0 | X16: {=IFERROR(_xlfn.XLOOKUP(B16,INDIRECT("'"&$K$47&"'!B:B"),INDIRECT("'"&$K$47&"'!Z:Z"),0),0)} -> 0 | Y16: =F16+X16 -> 10000 | Z16: {=IFERROR(_xlfn.LET(_xlpm.v,_xlfn.XLOOKUP(B16,INDIRECT("'"&$K$47&"'!B:B"),INDIRECT("'"&$K$47&"'!AA:AA"),0),IF(_xlpm.v=60000,60000,_xlpm.v+5000)),0)} -> 0 | AA16: =ROUND(F16-M16,2) -> 10000 | AB16: =IF(ROUND(Y16-W16-Z16,2)>0,ROUND(Y16-W16-Z16,2),0) -> 10000 | AC16: =ROUND(IF(AB16>960000,AB16*0.45-181920,IF(AB16>660000,AB16*0.35-85920,IF(AB16>420000,AB16*0.3-52920,IF(AB16>300000,AB16*0.25-31920,IF(AB16>144000,AB16*0.2-16920,IF(AB16>36000,AB16*0.1-2520,IF(AB16>0,AB16*0.03,0))))))),2) -> 300 | AD16: {=IFERROR(_xlfn.XLOOKUP(B16,INDIRECT("'"&$K$47&"'!B:B"),INDIRECT("'"&$K$47&"'!AD:AD"),0),0)} -> 0 | AE16: =ROUND(MAX(AC16-AD16,0),2) -> 300 | AF16: =ROUND(AA16-AE16,2) -> 9700
A17: =ROW(A17)-2 -> 15 | B17: 三 | C17: {=_xlfn.XLOOKUP(B17,INDIRECT("'"&$A$1&"'!B:B"),INDIRECT("'"&$A$1&"'!D:D"),"人员不存在",0,1)} -> 44958 | D17: {=_xlfn.XLOOKUP(B17,INDIRECT("'"&$A$1&"'!B:B"),INDIRECT("'"&$A$1&"'!G:G"),"人员不存在",0,1)} -> 10000 | E17: =IFERROR(F17/D17,0) -> 1 | F17: {=_xlfn.XLOOKUP(B17,INDIRECT("'"&$A$1&"'!B:B"),INDIRECT("'"&$A$1&"'!Q:Q"),"人员不存在",0,1)} -> 10000 | G17: {=SUMIF(INDIRECT("'"&$G$47&"'!C5:C"&IFERROR(MATCH(TRUE,ISBLANK(INDIRECT("'"&$G$47&"'!C5:C500")),0)+4,500)),B17,INDIRECT("'"&$G$47&"'!K5:K"&IFERROR(MATCH(TRUE,ISBLANK(INDIRECT("'"&$G$47&"'!C5:C500")),0)+4,500)))} -> 0 | H17: {=SUMIF(INDIRECT("'"&$G$47&"'!C5:C"&IFERROR(MATCH(TRUE,ISBLANK(INDIRECT("'"&$G$47&"'!C5:C500")),0)+4,500)),B17,INDIRECT("'"&$G$47&"'!L5:L"&IFERROR(MATCH(TRUE,ISBLANK(INDIRECT("'"&$G$47&"'!C5:C500")),0)+4,500)))} -> 0 | I17: {=SUMIF(INDIRECT("'"&$G$47&"'!C5:C"&IFERROR(MATCH(TRUE,ISBLANK(INDIRECT("'"&$G$47&"'!C5:C500")),0)+4,500)),B17,INDIRECT("'"&$G$47&"'!M5:M"&IFERROR(MATCH(TRUE,ISBLANK(INDIRECT("'"&$G$47&"'!C5:C500")),0)+4,500)))} -> 0 | J17: {=SUMIF(INDIRECT("'"&$G$47&"'!C5:C"&IFERROR(MATCH(TRUE,ISBLANK(INDIRECT("'"&$G$47&"'!C5:C500")),0)+4,500)),B17,INDIRECT("'"&$G$47&"'!N5:N"&IFERROR(MATCH(TRUE,ISBLANK(INDIRECT("'"&$G$47&"'!C5:C500")),0)+4,500)))} -> 0 | K17: =SUM(G17:J17) -> 0 | L17: {=IFERROR(_xlfn.XLOOKUP(B17,INDIRECT("'"&$I$47&"'!B:B"),INDIRECT("'"&$I$47&"'!E:E"),0),0)} -> 0 | M17: =ROUND(SUM(K17:L17),2) -> 0 | N17: {=IFERROR(_xlfn.XLOOKUP(B17,INDIRECT("'"&$M$47&"'!B:B"),INDIRECT("'"&$M$47&"'!AC:AC"),0),0)} -> 0 | O17: {=IFERROR(_xlfn.XLOOKUP(B17,INDIRECT("'"&$M$47&"'!B:B"),INDIRECT("'"&$M$47&"'!AG:AG"),0),0)} -> 0 | P17: {=IFERROR(_xlfn.XLOOKUP(B17,INDIRECT("'"&$M$47&"'!B:B"),INDIRECT("'"&$M$47&"'!AB:AB"),0),0)} -> 0 | Q17: {=IFERROR(_xlfn.XLOOKUP(B17,INDIRECT("'"&$M$47&"'!B:B"),INDIRECT("'"&$M$47&"'!AD:AD"),0),0)} -> 0 | R17: {=IFERROR(_xlfn.XLOOKUP(B17,INDIRECT("'"&$M$47&"'!B:B"),INDIRECT("'"&$M$47&"'!AE:AE"),0),0)} -> 0 | S17: {=IFERROR(_xlfn.XLOOKUP(B17,INDIRECT("'"&$M$47&"'!B:B"),INDIRECT("'"&$M$47&"'!AF:AF"),0),0)} -> 0 | T17: =SUM(N17:S17) -> 0 | U17: =ROUND(SUM(M17:S17),2) -> 0 | V17: {=IFERROR(_xlfn.XLOOKUP(B17,INDIRECT("'"&$K$47&"'!B:B"),INDIRECT("'"&$K$47&"'!Y:Y"),0),0)} -> 0 | W17: =U17+V17 -> 0 | X17: {=IFERROR(_xlfn.XLOOKUP(B17,INDIRECT("'"&$K$47&"'!B:B"),INDIRECT("'"&$K$47&"'!Z:Z"),0),0)} -> 0 | Y17: =F17+X17 -> 10000 | Z17: {=IFERROR(_xlfn.LET(_xlpm.v,_xlfn.XLOOKUP(B17,INDIRECT("'"&$K$47&"'!B:B"),INDIRECT("'"&$K$47&"'!AA:AA"),0),IF(_xlpm.v=60000,60000,_xlpm.v+5000)),0)} -> 0 | AA17: =ROUND(F17-M17,2) -> 10000 | AB17: =IF(ROUND(Y17-W17-Z17,2)>0,ROUND(Y17-W17-Z17,2),0) -> 10000 | AC17: =ROUND(IF(AB17>960000,AB17*0.45-181920,IF(AB17>660000,AB17*0.35-85920,IF(AB17>420000,AB17*0.3-52920,IF(AB17>300000,AB17*0.25-31920,IF(AB17>144000,AB17*0.2-16920,IF(AB17>36000,AB17*0.1-2520,IF(AB17>0,AB17*0.03,0))))))),2) -> 300 | AD17: {=IFERROR(_xlfn.XLOOKUP(B17,INDIRECT("'"&$K$47&"'!B:B"),INDIRECT("'"&$K$47&"'!AD:AD"),0),0)} -> 0 | AE17: =ROUND(MAX(AC17-AD17,0),2) -> 300 | AF17: =ROUND(AA17-AE17,2) -> 9700
A18: =ROW(A18)-2 -> 16 | B18: 一十二 | C18: {=_xlfn.XLOOKUP(B18,INDIRECT("'"&$A$1&"'!B:B"),INDIRECT("'"&$A$1&"'!D:D"),"人员不存在",0,1)} -> 46023 | D18: {=_xlfn.XLOOKUP(B18,INDIRECT("'"&$A$1&"'!B:B"),INDIRECT("'"&$A$1&"'!G:G"),"人员不存在",0,1)} -> 10000 | E18: =IFERROR(F18/D18,0) -> 1 | F18: {=_xlfn.XLOOKUP(B18,INDIRECT("'"&$A$1&"'!B:B"),INDIRECT("'"&$A$1&"'!Q:Q"),"人员不存在",0,1)} -> 10000 | G18: {=SUMIF(INDIRECT("'"&$G$47&"'!C5:C"&IFERROR(MATCH(TRUE,ISBLANK(INDIRECT("'"&$G$47&"'!C5:C500")),0)+4,500)),B18,INDIRECT("'"&$G$47&"'!K5:K"&IFERROR(MATCH(TRUE,ISBLANK(INDIRECT("'"&$G$47&"'!C5:C500")),0)+4,500)))} -> 0 | H18: {=SUMIF(INDIRECT("'"&$G$47&"'!C5:C"&IFERROR(MATCH(TRUE,ISBLANK(INDIRECT("'"&$G$47&"'!C5:C500")),0)+4,500)),B18,INDIRECT("'"&$G$47&"'!L5:L"&IFERROR(MATCH(TRUE,ISBLANK(INDIRECT("'"&$G$47&"'!C5:C500")),0)+4,500)))} -> 0 | I18: {=SUMIF(INDIRECT("'"&$G$47&"'!C5:C"&IFERROR(MATCH(TRUE,ISBLANK(INDIRECT("'"&$G$47&"'!C5:C500")),0)+4,500)),B18,INDIRECT("'"&$G$47&"'!M5:M"&IFERROR(MATCH(TRUE,ISBLANK(INDIRECT("'"&$G$47&"'!C5:C500")),0)+4,500)))} -> 0 | J18: {=SUMIF(INDIRECT("'"&$G$47&"'!C5:C"&IFERROR(MATCH(TRUE,ISBLANK(INDIRECT("'"&$G$47&"'!C5:C500")),0)+4,500)),B18,INDIRECT("'"&$G$47&"'!N5:N"&IFERROR(MATCH(TRUE,ISBLANK(INDIRECT("'"&$G$47&"'!C5:C500")),0)+4,500)))} -> 0 | K18: =SUM(G18:J18) -> 0 | L18: {=IFERROR(_xlfn.XLOOKUP(B18,INDIRECT("'"&$I$47&"'!B:B"),INDIRECT("'"&$I$47&"'!E:E"),0),0)} -> 0 | M18: =ROUND(SUM(K18:L18),2) -> 0 | N18: {=IFERROR(_xlfn.XLOOKUP(B18,INDIRECT("'"&$M$47&"'!B:B"),INDIRECT("'"&$M$47&"'!AC:AC"),0),0)} -> 0 | O18: {=IFERROR(_xlfn.XLOOKUP(B18,INDIRECT("'"&$M$47&"'!B:B"),INDIRECT("'"&$M$47&"'!AG:AG"),0),0)} -> 0 | P18: {=IFERROR(_xlfn.XLOOKUP(B18,INDIRECT("'"&$M$47&"'!B:B"),INDIRECT("'"&$M$47&"'!AB:AB"),0),0)} -> 0 | Q18: {=IFERROR(_xlfn.XLOOKUP(B18,INDIRECT("'"&$M$47&"'!B:B"),INDIRECT("'"&$M$47&"'!AD:AD"),0),0)} -> 0 | R18: {=IFERROR(_xlfn.XLOOKUP(B18,INDIRECT("'"&$M$47&"'!B:B"),INDIRECT("'"&$M$47&"'!AE:AE"),0),0)} -> 0 | S18: {=IFERROR(_xlfn.XLOOKUP(B18,INDIRECT("'"&$M$47&"'!B:B"),INDIRECT("'"&$M$47&"'!AF:AF"),0),0)} -> 0 | T18: =SUM(N18:S18) -> 0 | U18: =ROUND(SUM(M18:S18),2) -> 0 | V18: {=IFERROR(_xlfn.XLOOKUP(B18,INDIRECT("'"&$K$47&"'!B:B"),INDIRECT("'"&$K$47&"'!Y:Y"),0),0)} -> 0 | W18: =U18+V18 -> 0 | X18: {=IFERROR(_xlfn.XLOOKUP(B18,INDIRECT("'"&$K$47&"'!B:B"),INDIRECT("'"&$K$47&"'!Z:Z"),0),0)} -> 0 | Y18: =F18+X18 -> 10000 | Z18: {=IFERROR(_xlfn.LET(_xlpm.v,_xlfn.XLOOKUP(B18,INDIRECT("'"&$K$47&"'!B:B"),INDIRECT("'"&$K$47&"'!AA:AA"),0),IF(_xlpm.v=60000,60000,_xlpm.v+5000)),0)} -> 0 | AA18: =ROUND(F18-M18,2) -> 10000 | AB18: =IF(ROUND(Y18-W18-Z18,2)>0,ROUND(Y18-W18-Z18,2),0) -> 10000 | AC18: =ROUND(IF(AB18>960000,AB18*0.45-181920,IF(AB18>660000,AB18*0.35-85920,IF(AB18>420000,AB18*0.3-52920,IF(AB18>300000,AB18*0.25-31920,IF(AB18>144000,AB18*0.2-16920,IF(AB18>36000,AB18*0.1-2520,IF(AB18>0,AB18*0.03,0))))))),2) -> 300 | AD18: {=IFERROR(_xlfn.XLOOKUP(B18,INDIRECT("'"&$K$47&"'!B:B"),INDIRECT("'"&$K$47&"'!AD:AD"),0),0)} -> 0 | AE18: =ROUND(MAX(AC18-AD18,0),2) -> 300 | AF18: =ROUND(AA18-AE18,2) -> 9700
A19: =ROW(A19)-2 -> 17 | B19: 一十四 | C19: {=_xlfn.XLOOKUP(B19,INDIRECT("'"&$A$1&"'!B:B"),INDIRECT("'"&$A$1&"'!D:D"),"人员不存在",0,1)} -> 44774 | D19: {=_xlfn.XLOOKUP(B19,INDIRECT("'"&$A$1&"'!B:B"),INDIRECT("'"&$A$1&"'!G:G"),"人员不存在",0,1)} -> 10000 | E19: =IFERROR(F19/D19,0) -> 1 | F19: {=_xlfn.XLOOKUP(B19,INDIRECT("'"&$A$1&"'!B:B"),INDIRECT("'"&$A$1&"'!Q:Q"),"人员不存在",0,1)} -> 10000 | G19: {=SUMIF(INDIRECT("'"&$G$47&"'!C5:C"&IFERROR(MATCH(TRUE,ISBLANK(INDIRECT("'"&$G$47&"'!C5:C500")),0)+4,500)),B19,INDIRECT("'"&$G$47&"'!K5:K"&IFERROR(MATCH(TRUE,ISBLANK(INDIRECT("'"&$G$47&"'!C5:C500")),0)+4,500)))} -> 0 | H19: {=SUMIF(INDIRECT("'"&$G$47&"'!C5:C"&IFERROR(MATCH(TRUE,ISBLANK(INDIRECT("'"&$G$47&"'!C5:C500")),0)+4,500)),B19,INDIRECT("'"&$G$47&"'!L5:L"&IFERROR(MATCH(TRUE,ISBLANK(INDIRECT("'"&$G$47&"'!C5:C500")),0)+4,500)))} -> 0 | I19: {=SUMIF(INDIRECT("'"&$G$47&"'!C5:C"&IFERROR(MATCH(TRUE,ISBLANK(INDIRECT("'"&$G$47&"'!C5:C500")),0)+4,500)),B19,INDIRECT("'"&$G$47&"'!M5:M"&IFERROR(MATCH(TRUE,ISBLANK(INDIRECT("'"&$G$47&"'!C5:C500")),0)+4,500)))} -> 0 | J19: {=SUMIF(INDIRECT("'"&$G$47&"'!C5:C"&IFERROR(MATCH(TRUE,ISBLANK(INDIRECT("'"&$G$47&"'!C5:C500")),0)+4,500)),B19,INDIRECT("'"&$G$47&"'!N5:N"&IFERROR(MATCH(TRUE,ISBLANK(INDIRECT("'"&$G$47&"'!C5:C500")),0)+4,500)))} -> 0 | K19: =SUM(G19:J19) -> 0 | L19: {=IFERROR(_xlfn.XLOOKUP(B19,INDIRECT("'"&$I$47&"'!B:B"),INDIRECT("'"&$I$47&"'!E:E"),0),0)} -> 0 | M19: =ROUND(SUM(K19:L19),2) -> 0 | N19: {=IFERROR(_xlfn.XLOOKUP(B19,INDIRECT("'"&$M$47&"'!B:B"),INDIRECT("'"&$M$47&"'!AC:AC"),0),0)} -> 0 | O19: {=IFERROR(_xlfn.XLOOKUP(B19,INDIRECT("'"&$M$47&"'!B:B"),INDIRECT("'"&$M$47&"'!AG:AG"),0),0)} -> 0 | P19: {=IFERROR(_xlfn.XLOOKUP(B19,INDIRECT("'"&$M$47&"'!B:B"),INDIRECT("'"&$M$47&"'!AB:AB"),0),0)} -> 0 | Q19: {=IFERROR(_xlfn.XLOOKUP(B19,INDIRECT("'"&$M$47&"'!B:B"),INDIRECT("'"&$M$47&"'!AD:AD"),0),0)} -> 0 | R19: {=IFERROR(_xlfn.XLOOKUP(B19,INDIRECT("'"&$M$47&"'!B:B"),INDIRECT("'"&$M$47&"'!AE:AE"),0),0)} -> 0 | S19: {=IFERROR(_xlfn.XLOOKUP(B19,INDIRECT("'"&$M$47&"'!B:B"),INDIRECT("'"&$M$47&"'!AF:AF"),0),0)} -> 0 | T19: =SUM(N19:S19) -> 0 | U19: =ROUND(SUM(M19:S19),2) -> 0 | V19: {=IFERROR(_xlfn.XLOOKUP(B19,INDIRECT("'"&$K$47&"'!B:B"),INDIRECT("'"&$K$47&"'!Y:Y"),0),0)} -> 0 | W19: =U19+V19 -> 0 | X19: {=IFERROR(_xlfn.XLOOKUP(B19,INDIRECT("'"&$K$47&"'!B:B"),INDIRECT("'"&$K$47&"'!Z:Z"),0),0)} -> 0 | Y19: =F19+X19 -> 10000 | Z19: {=IFERROR(_xlfn.LET(_xlpm.v,_xlfn.XLOOKUP(B19,INDIRECT("'"&$K$47&"'!B:B"),INDIRECT("'"&$K$47&"'!AA:AA"),0),IF(_xlpm.v=60000,60000,_xlpm.v+5000)),0)} -> 0 | AA19: =ROUND(F19-M19,2) -> 10000 | AB19: =IF(ROUND(Y19-W19-Z19,2)>0,ROUND(Y19-W19-Z19,2),0) -> 10000 | AC19: =ROUND(IF(AB19>960000,AB19*0.45-181920,IF(AB19>660000,AB19*0.35-85920,IF(AB19>420000,AB19*0.3-52920,IF(AB19>300000,AB19*0.25-31920,IF(AB19>144000,AB19*0.2-16920,IF(AB19>36000,AB19*0.1-2520,IF(AB19>0,AB19*0.03,0))))))),2) -> 300 | AD19: {=IFERROR(_xlfn.XLOOKUP(B19,INDIRECT("'"&$K$47&"'!B:B"),INDIRECT("'"&$K$47&"'!AD:AD"),0),0)} -> 0 | AE19: =ROUND(MAX(AC19-AD19,0),2) -> 300 | AF19: =ROUND(AA19-AE19,2) -> 9700
A20: =ROW(A20)-2 -> 18 | B20: 一十五 | C20: {=_xlfn.XLOOKUP(B20,INDIRECT("'"&$A$1&"'!B:B"),INDIRECT("'"&$A$1&"'!D:D"),"人员不存在",0,1)} -> 44774 | D20: {=_xlfn.XLOOKUP(B20,INDIRECT("'"&$A$1&"'!B:B"),INDIRECT("'"&$A$1&"'!G:G"),"人员不存在",0,1)} -> 10000 | E20: =IFERROR(F20/D20,0) -> 0.967816 | F20: {=_xlfn.XLOOKUP(B20,INDIRECT("'"&$A$1&"'!B:B"),INDIRECT("'"&$A$1&"'!Q:Q"),"人员不存在",0,1)} -> 9678.16 | G20: {=SUMIF(INDIRECT("'"&$G$47&"'!C5:C"&IFERROR(MATCH(TRUE,ISBLANK(INDIRECT("'"&$G$47&"'!C5:C500")),0)+4,500)),B20,INDIRECT("'"&$G$47&"'!K5:K"&IFERROR(MATCH(TRUE,ISBLANK(INDIRECT("'"&$G$47&"'!C5:C500")),0)+4,500)))} -> 0 | H20: {=SUMIF(INDIRECT("'"&$G$47&"'!C5:C"&IFERROR(MATCH(TRUE,ISBLANK(INDIRECT("'"&$G$47&"'!C5:C500")),0)+4,500)),B20,INDIRECT("'"&$G$47&"'!L5:L"&IFERROR(MATCH(TRUE,ISBLANK(INDIRECT("'"&$G$47&"'!C5:C500")),0)+4,500)))} -> 0 | I20: {=SUMIF(INDIRECT("'"&$G$47&"'!C5:C"&IFERROR(MATCH(TRUE,ISBLANK(INDIRECT("'"&$G$47&"'!C5:C500")),0)+4,500)),B20,INDIRECT("'"&$G$47&"'!M5:M"&IFERROR(MATCH(TRUE,ISBLANK(INDIRECT("'"&$G$47&"'!C5:C500")),0)+4,500)))} -> 0 | J20: {=SUMIF(INDIRECT("'"&$G$47&"'!C5:C"&IFERROR(MATCH(TRUE,ISBLANK(INDIRECT("'"&$G$47&"'!C5:C500")),0)+4,500)),B20,INDIRECT("'"&$G$47&"'!N5:N"&IFERROR(MATCH(TRUE,ISBLANK(INDIRECT("'"&$G$47&"'!C5:C500")),0)+4,500)))} -> 0 | K20: =SUM(G20:J20) -> 0 | L20: {=IFERROR(_xlfn.XLOOKUP(B20,INDIRECT("'"&$I$47&"'!B:B"),INDIRECT("'"&$I$47&"'!E:E"),0),0)} -> 0 | M20: =ROUND(SUM(K20:L20),2) -> 0 | N20: {=IFERROR(_xlfn.XLOOKUP(B20,INDIRECT("'"&$M$47&"'!B:B"),INDIRECT("'"&$M$47&"'!AC:AC"),0),0)} -> 0 | O20: {=IFERROR(_xlfn.XLOOKUP(B20,INDIRECT("'"&$M$47&"'!B:B"),INDIRECT("'"&$M$47&"'!AG:AG"),0),0)} -> 0 | P20: {=IFERROR(_xlfn.XLOOKUP(B20,INDIRECT("'"&$M$47&"'!B:B"),INDIRECT("'"&$M$47&"'!AB:AB"),0),0)} -> 0 | Q20: {=IFERROR(_xlfn.XLOOKUP(B20,INDIRECT("'"&$M$47&"'!B:B"),INDIRECT("'"&$M$47&"'!AD:AD"),0),0)} -> 0 | R20: {=IFERROR(_xlfn.XLOOKUP(B20,INDIRECT("'"&$M$47&"'!B:B"),INDIRECT("'"&$M$47&"'!AE:AE"),0),0)} -> 0 | S20: {=IFERROR(_xlfn.XLOOKUP(B20,INDIRECT("'"&$M$47&"'!B:B"),INDIRECT("'"&$M$47&"'!AF:AF"),0),0)} -> 0 | T20: =SUM(N20:S20) -> 0 | U20: =ROUND(SUM(M20:S20),2) -> 0 | V20: {=IFERROR(_xlfn.XLOOKUP(B20,INDIRECT("'"&$K$47&"'!B:B"),INDIRECT("'"&$K$47&"'!Y:Y"),0),0)} -> 0 | W20: =U20+V20 -> 0 | X20: {=IFERROR(_xlfn.XLOOKUP(B20,INDIRECT("'"&$K$47&"'!B:B"),INDIRECT("'"&$K$47&"'!Z:Z"),0),0)} -> 0 | Y20: =F20+X20 -> 9678.16 | Z20: {=IFERROR(_xlfn.LET(_xlpm.v,_xlfn.XLOOKUP(B20,INDIRECT("'"&$K$47&"'!B:B"),INDIRECT("'"&$K$47&"'!AA:AA"),0),IF(_xlpm.v=60000,60000,_xlpm.v+5000)),0)} -> 0 | AA20: =ROUND(F20-M20,2) -> 9678.16 | AB20: =IF(ROUND(Y20-W20-Z20,2)>0,ROUND(Y20-W20-Z20,2),0) -> 9678.16 | AC20: =ROUND(IF(AB20>960000,AB20*0.45-181920,IF(AB20>660000,AB20*0.35-85920,IF(AB20>420000,AB20*0.3-52920,IF(AB20>300000,AB20*0.25-31920,IF(AB20>144000,AB20*0.2-16920,IF(AB20>36000,AB20*0.1-2520,IF(AB20>0,AB20*0.03,0))))))),2) -> 290.34 | AD20: {=IFERROR(_xlfn.XLOOKUP(B20,INDIRECT("'"&$K$47&"'!B:B"),INDIRECT("'"&$K$47&"'!AD:AD"),0),0)} -> 0 | AE20: =ROUND(MAX(AC20-AD20,0),2) -> 290.34 | AF20: =ROUND(AA20-AE20,2) -> 9387.82
A21: =ROW(A21)-2 -> 19 | B21: 二十一 | C21: {=_xlfn.XLOOKUP(B21,INDIRECT("'"&$A$1&"'!B:B"),INDIRECT("'"&$A$1&"'!D:D"),"人员不存在",0,1)} -> 44805 | D21: {=_xlfn.XLOOKUP(B21,INDIRECT("'"&$A$1&"'!B:B"),INDIRECT("'"&$A$1&"'!G:G"),"人员不存在",0,1)} -> 10000 | E21: =IFERROR(F21/D21,0) -> 1 | F21: {=_xlfn.XLOOKUP(B21,INDIRECT("'"&$A$1&"'!B:B"),INDIRECT("'"&$A$1&"'!Q:Q"),"人员不存在",0,1)} -> 10000 | G21: {=SUMIF(INDIRECT("'"&$G$47&"'!C5:C"&IFERROR(MATCH(TRUE,ISBLANK(INDIRECT("'"&$G$47&"'!C5:C500")),0)+4,500)),B21,INDIRECT("'"&$G$47&"'!K5:K"&IFERROR(MATCH(TRUE,ISBLANK(INDIRECT("'"&$G$47&"'!C5:C500")),0)+4,500)))} -> 0 | H21: {=SUMIF(INDIRECT("'"&$G$47&"'!C5:C"&IFERROR(MATCH(TRUE,ISBLANK(INDIRECT("'"&$G$47&"'!C5:C500")),0)+4,500)),B21,INDIRECT("'"&$G$47&"'!L5:L"&IFERROR(MATCH(TRUE,ISBLANK(INDIRECT("'"&$G$47&"'!C5:C500")),0)+4,500)))} -> 0 | I21: {=SUMIF(INDIRECT("'"&$G$47&"'!C5:C"&IFERROR(MATCH(TRUE,ISBLANK(INDIRECT("'"&$G$47&"'!C5:C500")),0)+4,500)),B21,INDIRECT("'"&$G$47&"'!M5:M"&IFERROR(MATCH(TRUE,ISBLANK(INDIRECT("'"&$G$47&"'!C5:C500")),0)+4,500)))} -> 0 | J21: {=SUMIF(INDIRECT("'"&$G$47&"'!C5:C"&IFERROR(MATCH(TRUE,ISBLANK(INDIRECT("'"&$G$47&"'!C5:C500")),0)+4,500)),B21,INDIRECT("'"&$G$47&"'!N5:N"&IFERROR(MATCH(TRUE,ISBLANK(INDIRECT("'"&$G$47&"'!C5:C500")),0)+4,500)))} -> 0 | K21: =SUM(G21:J21) -> 0 | L21: {=IFERROR(_xlfn.XLOOKUP(B21,INDIRECT("'"&$I$47&"'!B:B"),INDIRECT("'"&$I$47&"'!E:E"),0),0)} -> 0 | M21: =ROUND(SUM(K21:L21),2) -> 0 | N21: {=IFERROR(_xlfn.XLOOKUP(B21,INDIRECT("'"&$M$47&"'!B:B"),INDIRECT("'"&$M$47&"'!AC:AC"),0),0)} -> 0 | O21: {=IFERROR(_xlfn.XLOOKUP(B21,INDIRECT("'"&$M$47&"'!B:B"),INDIRECT("'"&$M$47&"'!AG:AG"),0),0)} -> 0 | P21: {=IFERROR(_xlfn.XLOOKUP(B21,INDIRECT("'"&$M$47&"'!B:B"),INDIRECT("'"&$M$47&"'!AB:AB"),0),0)} -> 0 | Q21: {=IFERROR(_xlfn.XLOOKUP(B21,INDIRECT("'"&$M$47&"'!B:B"),INDIRECT("'"&$M$47&"'!AD:AD"),0),0)} -> 0 | R21: {=IFERROR(_xlfn.XLOOKUP(B21,INDIRECT("'"&$M$47&"'!B:B"),INDIRECT("'"&$M$47&"'!AE:AE"),0),0)} -> 0 | S21: {=IFERROR(_xlfn.XLOOKUP(B21,INDIRECT("'"&$M$47&"'!B:B"),INDIRECT("'"&$M$47&"'!AF:AF"),0),0)} -> 0 | T21: =SUM(N21:S21) -> 0 | U21: =ROUND(SUM(M21:S21),2) -> 0 | V21: {=IFERROR(_xlfn.XLOOKUP(B21,INDIRECT("'"&$K$47&"'!B:B"),INDIRECT("'"&$K$47&"'!Y:Y"),0),0)} -> 0 | W21: =U21+V21 -> 0 | X21: {=IFERROR(_xlfn.XLOOKUP(B21,INDIRECT("'"&$K$47&"'!B:B"),INDIRECT("'"&$K$47&"'!Z:Z"),0),0)} -> 0 | Y21: =F21+X21 -> 10000 | Z21: {=IFERROR(_xlfn.LET(_xlpm.v,_xlfn.XLOOKUP(B21,INDIRECT("'"&$K$47&"'!B:B"),INDIRECT("'"&$K$47&"'!AA:AA"),0),IF(_xlpm.v=60000,60000,_xlpm.v+5000)),0)} -> 0 | AA21: =ROUND(F21-M21,2) -> 10000 | AB21: =IF(ROUND(Y21-W21-Z21,2)>0,ROUND(Y21-W21-Z21,2),0) -> 10000 | AC21: =ROUND(IF(AB21>960000,AB21*0.45-181920,IF(AB21>660000,AB21*0.35-85920,IF(AB21>420000,AB21*0.3-52920,IF(AB21>300000,AB21*0.25-31920,IF(AB21>144000,AB21*0.2-16920,IF(AB21>36000,AB21*0.1-2520,IF(AB21>0,AB21*0.03,0))))))),2) -> 300 | AD21: {=IFERROR(_xlfn.XLOOKUP(B21,INDIRECT("'"&$K$47&"'!B:B"),INDIRECT("'"&$K$47&"'!AD:AD"),0),0)} -> 0 | AE21: =ROUND(MAX(AC21-AD21,0),2) -> 300 | AF21: =ROUND(AA21-AE21,2) -> 9700
A22: =ROW(A22)-2 -> 20 | B22: 三十九 | C22: {=_xlfn.XLOOKUP(B22,INDIRECT("'"&$A$1&"'!B:B"),INDIRECT("'"&$A$1&"'!D:D"),"人员不存在",0,1)} -> 45078 | D22: {=_xlfn.XLOOKUP(B22,INDIRECT("'"&$A$1&"'!B:B"),INDIRECT("'"&$A$1&"'!G:G"),"人员不存在",0,1)} -> 10000 | E22: =IFERROR(F22/D22,0) -> 0.85 | F22: {=_xlfn.XLOOKUP(B22,INDIRECT("'"&$A$1&"'!B:B"),INDIRECT("'"&$A$1&"'!Q:Q"),"人员不存在",0,1)} -> 8500 | G22: {=SUMIF(INDIRECT("'"&$G$47&"'!C5:C"&IFERROR(MATCH(TRUE,ISBLANK(INDIRECT("'"&$G$47&"'!C5:C500")),0)+4,500)),B22,INDIRECT("'"&$G$47&"'!K5:K"&IFERROR(MATCH(TRUE,ISBLANK(INDIRECT("'"&$G$47&"'!C5:C500")),0)+4,500)))} -> 0 | H22: {=SUMIF(INDIRECT("'"&$G$47&"'!C5:C"&IFERROR(MATCH(TRUE,ISBLANK(INDIRECT("'"&$G$47&"'!C5:C500")),0)+4,500)),B22,INDIRECT("'"&$G$47&"'!L5:L"&IFERROR(MATCH(TRUE,ISBLANK(INDIRECT("'"&$G$47&"'!C5:C500")),0)+4,500)))} -> 0 | I22: {=SUMIF(INDIRECT("'"&$G$47&"'!C5:C"&IFERROR(MATCH(TRUE,ISBLANK(INDIRECT("'"&$G$47&"'!C5:C500")),0)+4,500)),B22,INDIRECT("'"&$G$47&"'!M5:M"&IFERROR(MATCH(TRUE,ISBLANK(INDIRECT("'"&$G$47&"'!C5:C500")),0)+4,500)))} -> 0 | J22: {=SUMIF(INDIRECT("'"&$G$47&"'!C5:C"&IFERROR(MATCH(TRUE,ISBLANK(INDIRECT("'"&$G$47&"'!C5:C500")),0)+4,500)),B22,INDIRECT("'"&$G$47&"'!N5:N"&IFERROR(MATCH(TRUE,ISBLANK(INDIRECT("'"&$G$47&"'!C5:C500")),0)+4,500)))} -> 0 | K22: =SUM(G22:J22) -> 0 | L22: {=IFERROR(_xlfn.XLOOKUP(B22,INDIRECT("'"&$I$47&"'!B:B"),INDIRECT("'"&$I$47&"'!E:E"),0),0)} -> 0 | M22: =ROUND(SUM(K22:L22),2) -> 0 | N22: {=IFERROR(_xlfn.XLOOKUP(B22,INDIRECT("'"&$M$47&"'!B:B"),INDIRECT("'"&$M$47&"'!AC:AC"),0),0)} -> 0 | O22: {=IFERROR(_xlfn.XLOOKUP(B22,INDIRECT("'"&$M$47&"'!B:B"),INDIRECT("'"&$M$47&"'!AG:AG"),0),0)} -> 0 | P22: {=IFERROR(_xlfn.XLOOKUP(B22,INDIRECT("'"&$M$47&"'!B:B"),INDIRECT("'"&$M$47&"'!AB:AB"),0),0)} -> 0 | Q22: {=IFERROR(_xlfn.XLOOKUP(B22,INDIRECT("'"&$M$47&"'!B:B"),INDIRECT("'"&$M$47&"'!AD:AD"),0),0)} -> 0 | R22: {=IFERROR(_xlfn.XLOOKUP(B22,INDIRECT("'"&$M$47&"'!B:B"),INDIRECT("'"&$M$47&"'!AE:AE"),0),0)} -> 0 | S22: {=IFERROR(_xlfn.XLOOKUP(B22,INDIRECT("'"&$M$47&"'!B:B"),INDIRECT("'"&$M$47&"'!AF:AF"),0),0)} -> 0 | T22: =SUM(N22:S22) -> 0 | U22: =ROUND(SUM(M22:S22),2) -> 0 | V22: {=IFERROR(_xlfn.XLOOKUP(B22,INDIRECT("'"&$K$47&"'!B:B"),INDIRECT("'"&$K$47&"'!Y:Y"),0),0)} -> 0 | W22: =U22+V22 -> 0 | X22: {=IFERROR(_xlfn.XLOOKUP(B22,INDIRECT("'"&$K$47&"'!B:B"),INDIRECT("'"&$K$47&"'!Z:Z"),0),0)} -> 0 | Y22: =F22+X22 -> 8500 | Z22: {=IFERROR(_xlfn.LET(_xlpm.v,_xlfn.XLOOKUP(B22,INDIRECT("'"&$K$47&"'!B:B"),INDIRECT("'"&$K$47&"'!AA:AA"),0),IF(_xlpm.v=60000,60000,_xlpm.v+5000)),0)} -> 0 | AA22: =ROUND(F22-M22,2) -> 8500 | AB22: =IF(ROUND(Y22-W22-Z22,2)>0,ROUND(Y22-W22-Z22,2),0) -> 8500 | AC22: =ROUND(IF(AB22>960000,AB22*0.45-181920,IF(AB22>660000,AB22*0.35-85920,IF(AB22>420000,AB22*0.3-52920,IF(AB22>300000,AB22*0.25-31920,IF(AB22>144000,AB22*0.2-16920,IF(AB22>36000,AB22*0.1-2520,IF(AB22>0,AB22*0.03,0))))))),2) -> 255 | AD22: {=IFERROR(_xlfn.XLOOKUP(B22,INDIRECT("'"&$K$47&"'!B:B"),INDIRECT("'"&$K$47&"'!AD:AD"),0),0)} -> 0 | AE22: =ROUND(MAX(AC22-AD22,0),2) -> 255 | AF22: =ROUND(AA22-AE22,2) -> 8245
A23: =ROW(A23)-2 -> 21 | B23: 四十 | C23: {=_xlfn.XLOOKUP(B23,INDIRECT("'"&$A$1&"'!B:B"),INDIRECT("'"&$A$1&"'!D:D"),"人员不存在",0,1)} -> 45078 | D23: {=_xlfn.XLOOKUP(B23,INDIRECT("'"&$A$1&"'!B:B"),INDIRECT("'"&$A$1&"'!G:G"),"人员不存在",0,1)} -> 10000 | E23: =IFERROR(F23/D23,0) -> 1 | F23: {=_xlfn.XLOOKUP(B23,INDIRECT("'"&$A$1&"'!B:B"),INDIRECT("'"&$A$1&"'!Q:Q"),"人员不存在",0,1)} -> 10000 | G23: {=SUMIF(INDIRECT("'"&$G$47&"'!C5:C"&IFERROR(MATCH(TRUE,ISBLANK(INDIRECT("'"&$G$47&"'!C5:C500")),0)+4,500)),B23,INDIRECT("'"&$G$47&"'!K5:K"&IFERROR(MATCH(TRUE,ISBLANK(INDIRECT("'"&$G$47&"'!C5:C500")),0)+4,500)))} -> 0 | H23: {=SUMIF(INDIRECT("'"&$G$47&"'!C5:C"&IFERROR(MATCH(TRUE,ISBLANK(INDIRECT("'"&$G$47&"'!C5:C500")),0)+4,500)),B23,INDIRECT("'"&$G$47&"'!L5:L"&IFERROR(MATCH(TRUE,ISBLANK(INDIRECT("'"&$G$47&"'!C5:C500")),0)+4,500)))} -> 0 | I23: {=SUMIF(INDIRECT("'"&$G$47&"'!C5:C"&IFERROR(MATCH(TRUE,ISBLANK(INDIRECT("'"&$G$47&"'!C5:C500")),0)+4,500)),B23,INDIRECT("'"&$G$47&"'!M5:M"&IFERROR(MATCH(TRUE,ISBLANK(INDIRECT("'"&$G$47&"'!C5:C500")),0)+4,500)))} -> 0 | J23: {=SUMIF(INDIRECT("'"&$G$47&"'!C5:C"&IFERROR(MATCH(TRUE,ISBLANK(INDIRECT("'"&$G$47&"'!C5:C500")),0)+4,500)),B23,INDIRECT("'"&$G$47&"'!N5:N"&IFERROR(MATCH(TRUE,ISBLANK(INDIRECT("'"&$G$47&"'!C5:C500")),0)+4,500)))} -> 0 | K23: =SUM(G23:J23) -> 0 | L23: {=IFERROR(_xlfn.XLOOKUP(B23,INDIRECT("'"&$I$47&"'!B:B"),INDIRECT("'"&$I$47&"'!E:E"),0),0)} -> 0 | M23: =ROUND(SUM(K23:L23),2) -> 0 | N23: {=IFERROR(_xlfn.XLOOKUP(B23,INDIRECT("'"&$M$47&"'!B:B"),INDIRECT("'"&$M$47&"'!AC:AC"),0),0)} -> 0 | O23: {=IFERROR(_xlfn.XLOOKUP(B23,INDIRECT("'"&$M$47&"'!B:B"),INDIRECT("'"&$M$47&"'!AG:AG"),0),0)} -> 0 | P23: {=IFERROR(_xlfn.XLOOKUP(B23,INDIRECT("'"&$M$47&"'!B:B"),INDIRECT("'"&$M$47&"'!AB:AB"),0),0)} -> 0 | Q23: {=IFERROR(_xlfn.XLOOKUP(B23,INDIRECT("'"&$M$47&"'!B:B"),INDIRECT("'"&$M$47&"'!AD:AD"),0),0)} -> 0 | R23: {=IFERROR(_xlfn.XLOOKUP(B23,INDIRECT("'"&$M$47&"'!B:B"),INDIRECT("'"&$M$47&"'!AE:AE"),0),0)} -> 0 | S23: {=IFERROR(_xlfn.XLOOKUP(B23,INDIRECT("'"&$M$47&"'!B:B"),INDIRECT("'"&$M$47&"'!AF:AF"),0),0)} -> 0 | T23: =SUM(N23:S23) -> 0 | U23: =ROUND(SUM(M23:S23),2) -> 0 | V23: {=IFERROR(_xlfn.XLOOKUP(B23,INDIRECT("'"&$K$47&"'!B:B"),INDIRECT("'"&$K$47&"'!Y:Y"),0),0)} -> 0 | W23: =U23+V23 -> 0 | X23: {=IFERROR(_xlfn.XLOOKUP(B23,INDIRECT("'"&$K$47&"'!B:B"),INDIRECT("'"&$K$47&"'!Z:Z"),0),0)} -> 0 | Y23: =F23+X23 -> 10000 | Z23: {=IFERROR(_xlfn.LET(_xlpm.v,_xlfn.XLOOKUP(B23,INDIRECT("'"&$K$47&"'!B:B"),INDIRECT("'"&$K$47&"'!AA:AA"),0),IF(_xlpm.v=60000,60000,_xlpm.v+5000)),0)} -> 0 | AA23: =ROUND(F23-M23,2) -> 10000 | AB23: =IF(ROUND(Y23-W23-Z23,2)>0,ROUND(Y23-W23-Z23,2),0) -> 10000 | AC23: =ROUND(IF(AB23>960000,AB23*0.45-181920,IF(AB23>660000,AB23*0.35-85920,IF(AB23>420000,AB23*0.3-52920,IF(AB23>300000,AB23*0.25-31920,IF(AB23>144000,AB23*0.2-16920,IF(AB23>36000,AB23*0.1-2520,IF(AB23>0,AB23*0.03,0))))))),2) -> 300 | AD23: {=IFERROR(_xlfn.XLOOKUP(B23,INDIRECT("'"&$K$47&"'!B:B"),INDIRECT("'"&$K$47&"'!AD:AD"),0),0)} -> 0 | AE23: =ROUND(MAX(AC23-AD23,0),2) -> 300 | AF23: =ROUND(AA23-AE23,2) -> 9700
A24: =ROW(A24)-2 -> 22 | B24: 六十九 | C24: {=_xlfn.XLOOKUP(B24,INDIRECT("'"&$A$1&"'!B:B"),INDIRECT("'"&$A$1&"'!D:D"),"人员不存在",0,1)} -> 45474 | D24: {=_xlfn.XLOOKUP(B24,INDIRECT("'"&$A$1&"'!B:B"),INDIRECT("'"&$A$1&"'!G:G"),"人员不存在",0,1)} -> 10000 | E24: =IFERROR(F24/D24,0) -> 1 | F24: {=_xlfn.XLOOKUP(B24,INDIRECT("'"&$A$1&"'!B:B"),INDIRECT("'"&$A$1&"'!Q:Q"),"人员不存在",0,1)} -> 10000 | G24: {=SUMIF(INDIRECT("'"&$G$47&"'!C5:C"&IFERROR(MATCH(TRUE,ISBLANK(INDIRECT("'"&$G$47&"'!C5:C500")),0)+4,500)),B24,INDIRECT("'"&$G$47&"'!K5:K"&IFERROR(MATCH(TRUE,ISBLANK(INDIRECT("'"&$G$47&"'!C5:C500")),0)+4,500)))} -> 0 | H24: {=SUMIF(INDIRECT("'"&$G$47&"'!C5:C"&IFERROR(MATCH(TRUE,ISBLANK(INDIRECT("'"&$G$47&"'!C5:C500")),0)+4,500)),B24,INDIRECT("'"&$G$47&"'!L5:L"&IFERROR(MATCH(TRUE,ISBLANK(INDIRECT("'"&$G$47&"'!C5:C500")),0)+4,500)))} -> 0 | I24: {=SUMIF(INDIRECT("'"&$G$47&"'!C5:C"&IFERROR(MATCH(TRUE,ISBLANK(INDIRECT("'"&$G$47&"'!C5:C500")),0)+4,500)),B24,INDIRECT("'"&$G$47&"'!M5:M"&IFERROR(MATCH(TRUE,ISBLANK(INDIRECT("'"&$G$47&"'!C5:C500")),0)+4,500)))} -> 0 | J24: {=SUMIF(INDIRECT("'"&$G$47&"'!C5:C"&IFERROR(MATCH(TRUE,ISBLANK(INDIRECT("'"&$G$47&"'!C5:C500")),0)+4,500)),B24,INDIRECT("'"&$G$47&"'!N5:N"&IFERROR(MATCH(TRUE,ISBLANK(INDIRECT("'"&$G$47&"'!C5:C500")),0)+4,500)))} -> 0 | K24: =SUM(G24:J24) -> 0 | L24: {=IFERROR(_xlfn.XLOOKUP(B24,INDIRECT("'"&$I$47&"'!B:B"),INDIRECT("'"&$I$47&"'!E:E"),0),0)} -> 0 | M24: =ROUND(SUM(K24:L24),2) -> 0 | N24: {=IFERROR(_xlfn.XLOOKUP(B24,INDIRECT("'"&$M$47&"'!B:B"),INDIRECT("'"&$M$47&"'!AC:AC"),0),0)} -> 0 | O24: {=IFERROR(_xlfn.XLOOKUP(B24,INDIRECT("'"&$M$47&"'!B:B"),INDIRECT("'"&$M$47&"'!AG:AG"),0),0)} -> 0 | P24: {=IFERROR(_xlfn.XLOOKUP(B24,INDIRECT("'"&$M$47&"'!B:B"),INDIRECT("'"&$M$47&"'!AB:AB"),0),0)} -> 0 | Q24: {=IFERROR(_xlfn.XLOOKUP(B24,INDIRECT("'"&$M$47&"'!B:B"),INDIRECT("'"&$M$47&"'!AD:AD"),0),0)} -> 0 | R24: {=IFERROR(_xlfn.XLOOKUP(B24,INDIRECT("'"&$M$47&"'!B:B"),INDIRECT("'"&$M$47&"'!AE:AE"),0),0)} -> 0 | S24: {=IFERROR(_xlfn.XLOOKUP(B24,INDIRECT("'"&$M$47&"'!B:B"),INDIRECT("'"&$M$47&"'!AF:AF"),0),0)} -> 0 | T24: =SUM(N24:S24) -> 0 | U24: =ROUND(SUM(M24:S24),2) -> 0 | V24: {=IFERROR(_xlfn.XLOOKUP(B24,INDIRECT("'"&$K$47&"'!B:B"),INDIRECT("'"&$K$47&"'!Y:Y"),0),0)} -> 0 | W24: =U24+V24 -> 0 | X24: {=IFERROR(_xlfn.XLOOKUP(B24,INDIRECT("'"&$K$47&"'!B:B"),INDIRECT("'"&$K$47&"'!Z:Z"),0),0)} -> 0 | Y24: =F24+X24 -> 10000 | Z24: {=IFERROR(_xlfn.LET(_xlpm.v,_xlfn.XLOOKUP(B24,INDIRECT("'"&$K$47&"'!B:B"),INDIRECT("'"&$K$47&"'!AA:AA"),0),IF(_xlpm.v=60000,60000,_xlpm.v+5000)),0)} -> 0 | AA24: =ROUND(F24-M24,2) -> 10000 | AB24: =IF(ROUND(Y24-W24-Z24,2)>0,ROUND(Y24-W24-Z24,2),0) -> 10000 | AC24: =ROUND(IF(AB24>960000,AB24*0.45-181920,IF(AB24>660000,AB24*0.35-85920,IF(AB24>420000,AB24*0.3-52920,IF(AB24>300000,AB24*0.25-31920,IF(AB24>144000,AB24*0.2-16920,IF(AB24>36000,AB24*0.1-2520,IF(AB24>0,AB24*0.03,0))))))),2) -> 300 | AD24: {=IFERROR(_xlfn.XLOOKUP(B24,INDIRECT("'"&$K$47&"'!B:B"),INDIRECT("'"&$K$47&"'!AD:AD"),0),0)} -> 0 | AE24: =ROUND(MAX(AC24-AD24,0),2) -> 300 | AF24: =ROUND(AA24-AE24,2) -> 9700
A25: =ROW(A25)-2 -> 23 | B25: 七十四 | C25: {=_xlfn.XLOOKUP(B25,INDIRECT("'"&$A$1&"'!B:B"),INDIRECT("'"&$A$1&"'!D:D"),"人员不存在",0,1)} -> 45518 | D25: {=_xlfn.XLOOKUP(B25,INDIRECT("'"&$A$1&"'!B:B"),INDIRECT("'"&$A$1&"'!G:G"),"人员不存在",0,1)} -> 10000 | E25: =IFERROR(F25/D25,0) -> 1 | F25: {=_xlfn.XLOOKUP(B25,INDIRECT("'"&$A$1&"'!B:B"),INDIRECT("'"&$A$1&"'!Q:Q"),"人员不存在",0,1)} -> 10000 | G25: {=SUMIF(INDIRECT("'"&$G$47&"'!C5:C"&IFERROR(MATCH(TRUE,ISBLANK(INDIRECT("'"&$G$47&"'!C5:C500")),0)+4,500)),B25,INDIRECT("'"&$G$47&"'!K5:K"&IFERROR(MATCH(TRUE,ISBLANK(INDIRECT("'"&$G$47&"'!C5:C500")),0)+4,500)))} -> 0 | H25: {=SUMIF(INDIRECT("'"&$G$47&"'!C5:C"&IFERROR(MATCH(TRUE,ISBLANK(INDIRECT("'"&$G$47&"'!C5:C500")),0)+4,500)),B25,INDIRECT("'"&$G$47&"'!L5:L"&IFERROR(MATCH(TRUE,ISBLANK(INDIRECT("'"&$G$47&"'!C5:C500")),0)+4,500)))} -> 0 | I25: {=SUMIF(INDIRECT("'"&$G$47&"'!C5:C"&IFERROR(MATCH(TRUE,ISBLANK(INDIRECT("'"&$G$47&"'!C5:C500")),0)+4,500)),B25,INDIRECT("'"&$G$47&"'!M5:M"&IFERROR(MATCH(TRUE,ISBLANK(INDIRECT("'"&$G$47&"'!C5:C500")),0)+4,500)))} -> 0 | J25: {=SUMIF(INDIRECT("'"&$G$47&"'!C5:C"&IFERROR(MATCH(TRUE,ISBLANK(INDIRECT("'"&$G$47&"'!C5:C500")),0)+4,500)),B25,INDIRECT("'"&$G$47&"'!N5:N"&IFERROR(MATCH(TRUE,ISBLANK(INDIRECT("'"&$G$47&"'!C5:C500")),0)+4,500)))} -> 0 | K25: =SUM(G25:J25) -> 0 | L25: {=IFERROR(_xlfn.XLOOKUP(B25,INDIRECT("'"&$I$47&"'!B:B"),INDIRECT("'"&$I$47&"'!E:E"),0),0)} -> 0 | M25: =ROUND(SUM(K25:L25),2) -> 0 | N25: {=IFERROR(_xlfn.XLOOKUP(B25,INDIRECT("'"&$M$47&"'!B:B"),INDIRECT("'"&$M$47&"'!AC:AC"),0),0)} -> 0 | O25: {=IFERROR(_xlfn.XLOOKUP(B25,INDIRECT("'"&$M$47&"'!B:B"),INDIRECT("'"&$M$47&"'!AG:AG"),0),0)} -> 0 | P25: {=IFERROR(_xlfn.XLOOKUP(B25,INDIRECT("'"&$M$47&"'!B:B"),INDIRECT("'"&$M$47&"'!AB:AB"),0),0)} -> 0 | Q25: {=IFERROR(_xlfn.XLOOKUP(B25,INDIRECT("'"&$M$47&"'!B:B"),INDIRECT("'"&$M$47&"'!AD:AD"),0),0)} -> 0 | R25: {=IFERROR(_xlfn.XLOOKUP(B25,INDIRECT("'"&$M$47&"'!B:B"),INDIRECT("'"&$M$47&"'!AE:AE"),0),0)} -> 0 | S25: {=IFERROR(_xlfn.XLOOKUP(B25,INDIRECT("'"&$M$47&"'!B:B"),INDIRECT("'"&$M$47&"'!AF:AF"),0),0)} -> 0 | T25: =SUM(N25:S25) -> 0 | U25: =ROUND(SUM(M25:S25),2) -> 0 | V25: {=IFERROR(_xlfn.XLOOKUP(B25,INDIRECT("'"&$K$47&"'!B:B"),INDIRECT("'"&$K$47&"'!Y:Y"),0),0)} -> 0 | W25: =U25+V25 -> 0 | X25: {=IFERROR(_xlfn.XLOOKUP(B25,INDIRECT("'"&$K$47&"'!B:B"),INDIRECT("'"&$K$47&"'!Z:Z"),0),0)} -> 0 | Y25: =F25+X25 -> 10000 | Z25: {=IFERROR(_xlfn.LET(_xlpm.v,_xlfn.XLOOKUP(B25,INDIRECT("'"&$K$47&"'!B:B"),INDIRECT("'"&$K$47&"'!AA:AA"),0),IF(_xlpm.v=60000,60000,_xlpm.v+5000)),0)} -> 0 | AA25: =ROUND(F25-M25,2) -> 10000 | AB25: =IF(ROUND(Y25-W25-Z25,2)>0,ROUND(Y25-W25-Z25,2),0) -> 10000 | AC25: =ROUND(IF(AB25>960000,AB25*0.45-181920,IF(AB25>660000,AB25*0.35-85920,IF(AB25>420000,AB25*0.3-52920,IF(AB25>300000,AB25*0.25-31920,IF(AB25>144000,AB25*0.2-16920,IF(AB25>36000,AB25*0.1-2520,IF(AB25>0,AB25*0.03,0))))))),2) -> 300 | AD25: {=IFERROR(_xlfn.XLOOKUP(B25,INDIRECT("'"&$K$47&"'!B:B"),INDIRECT("'"&$K$47&"'!AD:AD"),0),0)} -> 0 | AE25: =ROUND(MAX(AC25-AD25,0),2) -> 300 | AF25: =ROUND(AA25-AE25,2) -> 9700
A26: =ROW(A26)-2 -> 24 | B26: 八十三 | C26: {=_xlfn.XLOOKUP(B26,INDIRECT("'"&$A$1&"'!B:B"),INDIRECT("'"&$A$1&"'!D:D"),"人员不存在",0,1)} -> 45607 | D26: {=_xlfn.XLOOKUP(B26,INDIRECT("'"&$A$1&"'!B:B"),INDIRECT("'"&$A$1&"'!G:G"),"人员不存在",0,1)} -> 10000 | E26: =IFERROR(F26/D26,0) -> 0.983908 | F26: {=_xlfn.XLOOKUP(B26,INDIRECT("'"&$A$1&"'!B:B"),INDIRECT("'"&$A$1&"'!Q:Q"),"人员不存在",0,1)} -> 9839.08 | G26: {=SUMIF(INDIRECT("'"&$G$47&"'!C5:C"&IFERROR(MATCH(TRUE,ISBLANK(INDIRECT("'"&$G$47&"'!C5:C500")),0)+4,500)),B26,INDIRECT("'"&$G$47&"'!K5:K"&IFERROR(MATCH(TRUE,ISBLANK(INDIRECT("'"&$G$47&"'!C5:C500")),0)+4,500)))} -> 0 | H26: {=SUMIF(INDIRECT("'"&$G$47&"'!C5:C"&IFERROR(MATCH(TRUE,ISBLANK(INDIRECT("'"&$G$47&"'!C5:C500")),0)+4,500)),B26,INDIRECT("'"&$G$47&"'!L5:L"&IFERROR(MATCH(TRUE,ISBLANK(INDIRECT("'"&$G$47&"'!C5:C500")),0)+4,500)))} -> 0 | I26: {=SUMIF(INDIRECT("'"&$G$47&"'!C5:C"&IFERROR(MATCH(TRUE,ISBLANK(INDIRECT("'"&$G$47&"'!C5:C500")),0)+4,500)),B26,INDIRECT("'"&$G$47&"'!M5:M"&IFERROR(MATCH(TRUE,ISBLANK(INDIRECT("'"&$G$47&"'!C5:C500")),0)+4,500)))} -> 0 | J26: {=SUMIF(INDIRECT("'"&$G$47&"'!C5:C"&IFERROR(MATCH(TRUE,ISBLANK(INDIRECT("'"&$G$47&"'!C5:C500")),0)+4,500)),B26,INDIRECT("'"&$G$47&"'!N5:N"&IFERROR(MATCH(TRUE,ISBLANK(INDIRECT("'"&$G$47&"'!C5:C500")),0)+4,500)))} -> 0 | K26: =SUM(G26:J26) -> 0 | L26: {=IFERROR(_xlfn.XLOOKUP(B26,INDIRECT("'"&$I$47&"'!B:B"),INDIRECT("'"&$I$47&"'!E:E"),0),0)} -> 0 | M26: =ROUND(SUM(K26:L26),2) -> 0 | N26: {=IFERROR(_xlfn.XLOOKUP(B26,INDIRECT("'"&$M$47&"'!B:B"),INDIRECT("'"&$M$47&"'!AC:AC"),0),0)} -> 0 | O26: {=IFERROR(_xlfn.XLOOKUP(B26,INDIRECT("'"&$M$47&"'!B:B"),INDIRECT("'"&$M$47&"'!AG:AG"),0),0)} -> 0 | P26: {=IFERROR(_xlfn.XLOOKUP(B26,INDIRECT("'"&$M$47&"'!B:B"),INDIRECT("'"&$M$47&"'!AB:AB"),0),0)} -> 0 | Q26: {=IFERROR(_xlfn.XLOOKUP(B26,INDIRECT("'"&$M$47&"'!B:B"),INDIRECT("'"&$M$47&"'!AD:AD"),0),0)} -> 0 | R26: {=IFERROR(_xlfn.XLOOKUP(B26,INDIRECT("'"&$M$47&"'!B:B"),INDIRECT("'"&$M$47&"'!AE:AE"),0),0)} -> 0 | S26: {=IFERROR(_xlfn.XLOOKUP(B26,INDIRECT("'"&$M$47&"'!B:B"),INDIRECT("'"&$M$47&"'!AF:AF"),0),0)} -> 0 | T26: =SUM(N26:S26) -> 0 | U26: =ROUND(SUM(M26:S26),2) -> 0 | V26: {=IFERROR(_xlfn.XLOOKUP(B26,INDIRECT("'"&$K$47&"'!B:B"),INDIRECT("'"&$K$47&"'!Y:Y"),0),0)} -> 0 | W26: =U26+V26 -> 0 | X26: {=IFERROR(_xlfn.XLOOKUP(B26,INDIRECT("'"&$K$47&"'!B:B"),INDIRECT("'"&$K$47&"'!Z:Z"),0),0)} -> 0 | Y26: =F26+X26 -> 9839.08 | Z26: {=IFERROR(_xlfn.LET(_xlpm.v,_xlfn.XLOOKUP(B26,INDIRECT("'"&$K$47&"'!B:B"),INDIRECT("'"&$K$47&"'!AA:AA"),0),IF(_xlpm.v=60000,60000,_xlpm.v+5000)),0)} -> 0 | AA26: =ROUND(F26-M26,2) -> 9839.08 | AB26: =IF(ROUND(Y26-W26-Z26,2)>0,ROUND(Y26-W26-Z26,2),0) -> 9839.08 | AC26: =ROUND(IF(AB26>960000,AB26*0.45-181920,IF(AB26>660000,AB26*0.35-85920,IF(AB26>420000,AB26*0.3-52920,IF(AB26>300000,AB26*0.25-31920,IF(AB26>144000,AB26*0.2-16920,IF(AB26>36000,AB26*0.1-2520,IF(AB26>0,AB26*0.03,0))))))),2) -> 295.17 | AD26: {=IFERROR(_xlfn.XLOOKUP(B26,INDIRECT("'"&$K$47&"'!B:B"),INDIRECT("'"&$K$47&"'!AD:AD"),0),0)} -> 0 | AE26: =ROUND(MAX(AC26-AD26,0),2) -> 295.17 | AF26: =ROUND(AA26-AE26,2) -> 9543.91
... A36: =ROW(A36)-2 -> 34 | B36: 一百五十七 | C36: {=_xlfn.XLOOKUP(B36,INDIRECT("'"&$A$1&"'!B:B"),INDIRECT("'"&$A$1&"'!D:D"),"人员不存在",0,1)} -> 46097 | D36: {=_xlfn.XLOOKUP(B36,INDIRECT("'"&$A$1&"'!B:B"),INDIRECT("'"&$A$1&"'!G:G"),"人员不存在",0,1)} -> 10000 | E36: =IFERROR(F36/D36,0) -> 0.367816 | F36: {=_xlfn.XLOOKUP(B36,INDIRECT("'"&$A$1&"'!B:B"),INDIRECT("'"&$A$1&"'!Q:Q"),"人员不存在",0,1)} -> 3678.16 | G36: {=SUMIF(INDIRECT("'"&$G$47&"'!C5:C"&IFERROR(MATCH(TRUE,ISBLANK(INDIRECT("'"&$G$47&"'!C5:C500")),0)+4,500)),B36,INDIRECT("'"&$G$47&"'!K5:K"&IFERROR(MATCH(TRUE,ISBLANK(INDIRECT("'"&$G$47&"'!C5:C500")),0)+4,500)))} -> 0 | H36: {=SUMIF(INDIRECT("'"&$G$47&"'!C5:C"&IFERROR(MATCH(TRUE,ISBLANK(INDIRECT("'"&$G$47&"'!C5:C500")),0)+4,500)),B36,INDIRECT("'"&$G$47&"'!L5:L"&IFERROR(MATCH(TRUE,ISBLANK(INDIRECT("'"&$G$47&"'!C5:C500")),0)+4,500)))} -> 0 | I36: {=SUMIF(INDIRECT("'"&$G$47&"'!C5:C"&IFERROR(MATCH(TRUE,ISBLANK(INDIRECT("'"&$G$47&"'!C5:C500")),0)+4,500)),B36,INDIRECT("'"&$G$47&"'!M5:M"&IFERROR(MATCH(TRUE,ISBLANK(INDIRECT("'"&$G$47&"'!C5:C500")),0)+4,500)))} -> 0 | J36: {=SUMIF(INDIRECT("'"&$G$47&"'!C5:C"&IFERROR(MATCH(TRUE,ISBLANK(INDIRECT("'"&$G$47&"'!C5:C500")),0)+4,500)),B36,INDIRECT("'"&$G$47&"'!N5:N"&IFERROR(MATCH(TRUE,ISBLANK(INDIRECT("'"&$G$47&"'!C5:C500")),0)+4,500)))} -> 0 | K36: =SUM(G36:J36) -> 0 | L36: {=IFERROR(_xlfn.XLOOKUP(B36,INDIRECT("'"&$I$47&"'!B:B"),INDIRECT("'"&$I$47&"'!E:E"),0),0)} -> 0 | M36: =ROUND(SUM(K36:L36),2) -> 0 | N36: {=IFERROR(_xlfn.XLOOKUP(B36,INDIRECT("'"&$M$47&"'!B:B"),INDIRECT("'"&$M$47&"'!AC:AC"),0),0)} -> 0 | O36: {=IFERROR(_xlfn.XLOOKUP(B36,INDIRECT("'"&$M$47&"'!B:B"),INDIRECT("'"&$M$47&"'!AG:AG"),0),0)} -> 0 | P36: {=IFERROR(_xlfn.XLOOKUP(B36,INDIRECT("'"&$M$47&"'!B:B"),INDIRECT("'"&$M$47&"'!AB:AB"),0),0)} -> 0 | Q36: {=IFERROR(_xlfn.XLOOKUP(B36,INDIRECT("'"&$M$47&"'!B:B"),INDIRECT("'"&$M$47&"'!AD:AD"),0),0)} -> 0 | R36: {=IFERROR(_xlfn.XLOOKUP(B36,INDIRECT("'"&$M$47&"'!B:B"),INDIRECT("'"&$M$47&"'!AE:AE"),0),0)} -> 0 | S36: {=IFERROR(_xlfn.XLOOKUP(B36,INDIRECT("'"&$M$47&"'!B:B"),INDIRECT("'"&$M$47&"'!AF:AF"),0),0)} -> 0 | T36: =SUM(N36:S36) -> 0 | U36: =ROUND(SUM(M36:S36),2) -> 0 | V36: {=IFERROR(_xlfn.XLOOKUP(B36,INDIRECT("'"&$K$47&"'!B:B"),INDIRECT("'"&$K$47&"'!Y:Y"),0),0)} -> 0 | W36: =U36+V36 -> 0 | X36: {=IFERROR(_xlfn.XLOOKUP(B36,INDIRECT("'"&$K$47&"'!B:B"),INDIRECT("'"&$K$47&"'!Z:Z"),0),0)} -> 0 | Y36: =F36+X36 -> 3678.16 | Z36: {=IFERROR(_xlfn.LET(_xlpm.v,_xlfn.XLOOKUP(B36,INDIRECT("'"&$K$47&"'!B:B"),INDIRECT("'"&$K$47&"'!AA:AA"),0),IF(_xlpm.v=60000,60000,_xlpm.v+5000)),0)} -> 0 | AA36: =ROUND(F36-M36,2) -> 3678.16 | AB36: =IF(ROUND(Y36-W36-Z36,2)>0,ROUND(Y36-W36-Z36,2),0) -> 3678.16 | AC36: =ROUND(IF(AB36>960000,AB36*0.45-181920,IF(AB36>660000,AB36*0.35-85920,IF(AB36>420000,AB36*0.3-52920,IF(AB36>300000,AB36*0.25-31920,IF(AB36>144000,AB36*0.2-16920,IF(AB36>36000,AB36*0.1-2520,IF(AB36>0,AB36*0.03,0))))))),2) -> 110.34 | AD36: {=IFERROR(_xlfn.XLOOKUP(B36,INDIRECT("'"&$K$47&"'!B:B"),INDIRECT("'"&$K$47&"'!AD:AD"),0),0)} -> 0 | AE36: =ROUND(MAX(AC36-AD36,0),2) -> 110.34 | AF36: =ROUND(AA36-AE36,2) -> 3567.82
A37: =ROW(A37)-2 -> 35 | B37: 一百五十八 | C37: {=_xlfn.XLOOKUP(B37,INDIRECT("'"&$A$1&"'!B:B"),INDIRECT("'"&$A$1&"'!D:D"),"人员不存在",0,1)} -> 46097 | D37: {=_xlfn.XLOOKUP(B37,INDIRECT("'"&$A$1&"'!B:B"),INDIRECT("'"&$A$1&"'!G:G"),"人员不存在",0,1)} -> 120元/天 | E37: =IFERROR(F37/D37,0) -> 0 | F37: {=_xlfn.XLOOKUP(B37,INDIRECT("'"&$A$1&"'!B:B"),INDIRECT("'"&$A$1&"'!Q:Q"),"人员不存在",0,1)} -> 2160 | G37: {=SUMIF(INDIRECT("'"&$G$47&"'!C5:C"&IFERROR(MATCH(TRUE,ISBLANK(INDIRECT("'"&$G$47&"'!C5:C500")),0)+4,500)),B37,INDIRECT("'"&$G$47&"'!K5:K"&IFERROR(MATCH(TRUE,ISBLANK(INDIRECT("'"&$G$47&"'!C5:C500")),0)+4,500)))*2} -> 0 | H37: {=SUMIF(INDIRECT("'"&$G$47&"'!C5:C"&IFERROR(MATCH(TRUE,ISBLANK(INDIRECT("'"&$G$47&"'!C5:C500")),0)+4,500)),B37,INDIRECT("'"&$G$47&"'!L5:L"&IFERROR(MATCH(TRUE,ISBLANK(INDIRECT("'"&$G$47&"'!C5:C500")),0)+4,500)))*2} -> 0 | I37: {=SUMIF(INDIRECT("'"&$G$47&"'!C5:C"&IFERROR(MATCH(TRUE,ISBLANK(INDIRECT("'"&$G$47&"'!C5:C500")),0)+4,500)),B37,INDIRECT("'"&$G$47&"'!M5:M"&IFERROR(MATCH(TRUE,ISBLANK(INDIRECT("'"&$G$47&"'!C5:C500")),0)+4,500)))*2} -> 0 | J37: {=SUMIF(INDIRECT("'"&$G$47&"'!C5:C"&IFERROR(MATCH(TRUE,ISBLANK(INDIRECT("'"&$G$47&"'!C5:C500")),0)+4,500)),B37,INDIRECT("'"&$G$47&"'!N5:N"&IFERROR(MATCH(TRUE,ISBLANK(INDIRECT("'"&$G$47&"'!C5:C500")),0)+4,500)))*2} -> 0 | K37: =SUM(G37:J37) -> 0 | L37: {=IFERROR(_xlfn.XLOOKUP(B37,INDIRECT("'"&$I$47&"'!B:B"),INDIRECT("'"&$I$47&"'!E:E"),0),0)} -> 0 | M37: =ROUND(SUM(K37:L37),2) -> 0 | N37: {=IFERROR(_xlfn.XLOOKUP(B37,INDIRECT("'"&$M$47&"'!B:B"),INDIRECT("'"&$M$47&"'!AC:AC"),0),0)} -> 0 | O37: {=IFERROR(_xlfn.XLOOKUP(B37,INDIRECT("'"&$M$47&"'!B:B"),INDIRECT("'"&$M$47&"'!AG:AG"),0),0)} -> 0 | P37: {=IFERROR(_xlfn.XLOOKUP(B37,INDIRECT("'"&$M$47&"'!B:B"),INDIRECT("'"&$M$47&"'!AB:AB"),0),0)} -> 0 | Q37: {=IFERROR(_xlfn.XLOOKUP(B37,INDIRECT("'"&$M$47&"'!B:B"),INDIRECT("'"&$M$47&"'!AD:AD"),0),0)} -> 0 | R37: {=IFERROR(_xlfn.XLOOKUP(B37,INDIRECT("'"&$M$47&"'!B:B"),INDIRECT("'"&$M$47&"'!AE:AE"),0),0)} -> 0 | S37: {=IFERROR(_xlfn.XLOOKUP(B37,INDIRECT("'"&$M$47&"'!B:B"),INDIRECT("'"&$M$47&"'!AF:AF"),0),0)} -> 0 | T37: =SUM(N37:S37) -> 0 | U37: =ROUND(SUM(M37:S37),2) -> 0 | V37: {=IFERROR(_xlfn.XLOOKUP(B37,INDIRECT("'"&$K$47&"'!B:B"),INDIRECT("'"&$K$47&"'!Y:Y"),0),0)} -> 0 | W37: =U37+V37 -> 0 | X37: {=IFERROR(_xlfn.XLOOKUP(B37,INDIRECT("'"&$K$47&"'!B:B"),INDIRECT("'"&$K$47&"'!Z:Z"),0),0)} -> 0 | Y37: =F37+X37 -> 2160 | Z37: {=IFERROR(_xlfn.LET(_xlpm.v,_xlfn.XLOOKUP(B37,INDIRECT("'"&$K$47&"'!B:B"),INDIRECT("'"&$K$47&"'!AA:AA"),0),IF(_xlpm.v=60000,60000,_xlpm.v+5000)),0)} -> 0 | AA37: =ROUND(F37-M37,2) -> 2160 | AB37: =IF(ROUND(Y37-W37-Z37,2)>0,ROUND(Y37-W37-Z37,2),0) -> 2160 | AC37: =ROUND(IF(AB37>960000,AB37*0.45-181920,IF(AB37>660000,AB37*0.35-85920,IF(AB37>420000,AB37*0.3-52920,IF(AB37>300000,AB37*0.25-31920,IF(AB37>144000,AB37*0.2-16920,IF(AB37>36000,AB37*0.1-2520,IF(AB37>0,AB37*0.03,0))))))),2) -> 64.8 | AD37: {=IFERROR(_xlfn.XLOOKUP(B37,INDIRECT("'"&$K$47&"'!B:B"),INDIRECT("'"&$K$47&"'!AD:AD"),0),0)} -> 0 | AE37: =ROUND(MAX(AC37-AD37,0),2) -> 64.8 | AF37: =ROUND(AA37-AE37,2) -> 2095.2
A38: =ROW(A38)-2 -> 36 | B38: 一百六十九 | C38: {=_xlfn.XLOOKUP(B38,INDIRECT("'"&$A$1&"'!B:B"),INDIRECT("'"&$A$1&"'!D:D"),"人员不存在",0,1)} -> 46119 | D38: {=_xlfn.XLOOKUP(B38,INDIRECT("'"&$A$1&"'!B:B"),INDIRECT("'"&$A$1&"'!G:G"),"人员不存在",0,1)} -> 10000 | E38: =IFERROR(F38/D38,0) -> 0.827586 | F38: {=_xlfn.XLOOKUP(B38,INDIRECT("'"&$A$1&"'!B:B"),INDIRECT("'"&$A$1&"'!Q:Q"),"人员不存在",0,1)} -> 8275.86 | G38: {=SUMIF(INDIRECT("'"&$G$47&"'!C5:C"&IFERROR(MATCH(TRUE,ISBLANK(INDIRECT("'"&$G$47&"'!C5:C500")),0)+4,500)),B38,INDIRECT("'"&$G$47&"'!K5:K"&IFERROR(MATCH(TRUE,ISBLANK(INDIRECT("'"&$G$47&"'!C5:C500")),0)+4,500)))} -> 0 | H38: {=SUMIF(INDIRECT("'"&$G$47&"'!C5:C"&IFERROR(MATCH(TRUE,ISBLANK(INDIRECT("'"&$G$47&"'!C5:C500")),0)+4,500)),B38,INDIRECT("'"&$G$47&"'!L5:L"&IFERROR(MATCH(TRUE,ISBLANK(INDIRECT("'"&$G$47&"'!C5:C500")),0)+4,500)))} -> 0 | I38: {=SUMIF(INDIRECT("'"&$G$47&"'!C5:C"&IFERROR(MATCH(TRUE,ISBLANK(INDIRECT("'"&$G$47&"'!C5:C500")),0)+4,500)),B38,INDIRECT("'"&$G$47&"'!M5:M"&IFERROR(MATCH(TRUE,ISBLANK(INDIRECT("'"&$G$47&"'!C5:C500")),0)+4,500)))} -> 0 | J38: {=SUMIF(INDIRECT("'"&$G$47&"'!C5:C"&IFERROR(MATCH(TRUE,ISBLANK(INDIRECT("'"&$G$47&"'!C5:C500")),0)+4,500)),B38,INDIRECT("'"&$G$47&"'!N5:N"&IFERROR(MATCH(TRUE,ISBLANK(INDIRECT("'"&$G$47&"'!C5:C500")),0)+4,500)))} -> 0 | K38: =SUM(G38:J38) -> 0 | L38: {=IFERROR(_xlfn.XLOOKUP(B38,INDIRECT("'"&$I$47&"'!B:B"),INDIRECT("'"&$I$47&"'!E:E"),0),0)} -> 0 | M38: =ROUND(SUM(K38:L38),2) -> 0 | N38: {=IFERROR(_xlfn.XLOOKUP(B38,INDIRECT("'"&$M$47&"'!B:B"),INDIRECT("'"&$M$47&"'!AC:AC"),0),0)} -> 0 | O38: {=IFERROR(_xlfn.XLOOKUP(B38,INDIRECT("'"&$M$47&"'!B:B"),INDIRECT("'"&$M$47&"'!AG:AG"),0),0)} -> 0 | P38: {=IFERROR(_xlfn.XLOOKUP(B38,INDIRECT("'"&$M$47&"'!B:B"),INDIRECT("'"&$M$47&"'!AB:AB"),0),0)} -> 0 | Q38: {=IFERROR(_xlfn.XLOOKUP(B38,INDIRECT("'"&$M$47&"'!B:B"),INDIRECT("'"&$M$47&"'!AD:AD"),0),0)} -> 0 | R38: {=IFERROR(_xlfn.XLOOKUP(B38,INDIRECT("'"&$M$47&"'!B:B"),INDIRECT("'"&$M$47&"'!AE:AE"),0),0)} -> 0 | S38: {=IFERROR(_xlfn.XLOOKUP(B38,INDIRECT("'"&$M$47&"'!B:B"),INDIRECT("'"&$M$47&"'!AF:AF"),0),0)} -> 0 | T38: =SUM(N38:S38) -> 0 | U38: =ROUND(SUM(M38:S38),2) -> 0 | V38: {=IFERROR(_xlfn.XLOOKUP(B38,INDIRECT("'"&$K$47&"'!B:B"),INDIRECT("'"&$K$47&"'!Y:Y"),0),0)} -> 0 | W38: =U38+V38 -> 0 | X38: {=IFERROR(_xlfn.XLOOKUP(B38,INDIRECT("'"&$K$47&"'!B:B"),INDIRECT("'"&$K$47&"'!Z:Z"),0),0)} -> 0 | Y38: =F38+X38 -> 8275.86 | Z38: {=IFERROR(_xlfn.LET(_xlpm.v,_xlfn.XLOOKUP(B38,INDIRECT("'"&$K$47&"'!B:B"),INDIRECT("'"&$K$47&"'!AA:AA"),0),IF(_xlpm.v=60000,60000,_xlpm.v+5000)),0)} -> 0 | AA38: =ROUND(F38-M38,2) -> 8275.86 | AB38: =IF(ROUND(Y38-W38-Z38,2)>0,ROUND(Y38-W38-Z38,2),0) -> 8275.86 | AC38: =ROUND(IF(AB38>960000,AB38*0.45-181920,IF(AB38>660000,AB38*0.35-85920,IF(AB38>420000,AB38*0.3-52920,IF(AB38>300000,AB38*0.25-31920,IF(AB38>144000,AB38*0.2-16920,IF(AB38>36000,AB38*0.1-2520,IF(AB38>0,AB38*0.03,0))))))),2) -> 248.28 | AD38: {=IFERROR(_xlfn.XLOOKUP(B38,INDIRECT("'"&$K$47&"'!B:B"),INDIRECT("'"&$K$47&"'!AD:AD"),0),0)} -> 0 | AE38: =ROUND(MAX(AC38-AD38,0),2) -> 248.28 | AF38: =ROUND(AA38-AE38,2) -> 8027.58
A39: =ROW(A39)-2 -> 37 | B39: 一百七十三 | C39: {=_xlfn.XLOOKUP(B39,INDIRECT("'"&$A$1&"'!B:B"),INDIRECT("'"&$A$1&"'!D:D"),"人员不存在",0,1)} -> 46132 | D39: {=_xlfn.XLOOKUP(B39,INDIRECT("'"&$A$1&"'!B:B"),INDIRECT("'"&$A$1&"'!G:G"),"人员不存在",0,1)} -> 10000 | E39: =IFERROR(F39/D39,0) -> 0.413793 | F39: {=_xlfn.XLOOKUP(B39,INDIRECT("'"&$A$1&"'!B:B"),INDIRECT("'"&$A$1&"'!Q:Q"),"人员不存在",0,1)} -> 4137.93 | G39: {=SUMIF(INDIRECT("'"&$G$47&"'!C5:C"&IFERROR(MATCH(TRUE,ISBLANK(INDIRECT("'"&$G$47&"'!C5:C500")),0)+4,500)),B39,INDIRECT("'"&$G$47&"'!K5:K"&IFERROR(MATCH(TRUE,ISBLANK(INDIRECT("'"&$G$47&"'!C5:C500")),0)+4,500)))} -> 0 | H39: {=SUMIF(INDIRECT("'"&$G$47&"'!C5:C"&IFERROR(MATCH(TRUE,ISBLANK(INDIRECT("'"&$G$47&"'!C5:C500")),0)+4,500)),B39,INDIRECT("'"&$G$47&"'!L5:L"&IFERROR(MATCH(TRUE,ISBLANK(INDIRECT("'"&$G$47&"'!C5:C500")),0)+4,500)))} -> 0 | I39: {=SUMIF(INDIRECT("'"&$G$47&"'!C5:C"&IFERROR(MATCH(TRUE,ISBLANK(INDIRECT("'"&$G$47&"'!C5:C500")),0)+4,500)),B39,INDIRECT("'"&$G$47&"'!M5:M"&IFERROR(MATCH(TRUE,ISBLANK(INDIRECT("'"&$G$47&"'!C5:C500")),0)+4,500)))} -> 0 | J39: {=SUMIF(INDIRECT("'"&$G$47&"'!C5:C"&IFERROR(MATCH(TRUE,ISBLANK(INDIRECT("'"&$G$47&"'!C5:C500")),0)+4,500)),B39,INDIRECT("'"&$G$47&"'!N5:N"&IFERROR(MATCH(TRUE,ISBLANK(INDIRECT("'"&$G$47&"'!C5:C500")),0)+4,500)))} -> 0 | K39: =SUM(G39:J39) -> 0 | L39: {=IFERROR(_xlfn.XLOOKUP(B39,INDIRECT("'"&$I$47&"'!B:B"),INDIRECT("'"&$I$47&"'!E:E"),0),0)} -> 0 | M39: =ROUND(SUM(K39:L39),2) -> 0 | N39: {=IFERROR(_xlfn.XLOOKUP(B39,INDIRECT("'"&$M$47&"'!B:B"),INDIRECT("'"&$M$47&"'!AC:AC"),0),0)} -> 0 | O39: {=IFERROR(_xlfn.XLOOKUP(B39,INDIRECT("'"&$M$47&"'!B:B"),INDIRECT("'"&$M$47&"'!AG:AG"),0),0)} -> 0 | P39: {=IFERROR(_xlfn.XLOOKUP(B39,INDIRECT("'"&$M$47&"'!B:B"),INDIRECT("'"&$M$47&"'!AB:AB"),0),0)} -> 0 | Q39: {=IFERROR(_xlfn.XLOOKUP(B39,INDIRECT("'"&$M$47&"'!B:B"),INDIRECT("'"&$M$47&"'!AD:AD"),0),0)} -> 0 | R39: {=IFERROR(_xlfn.XLOOKUP(B39,INDIRECT("'"&$M$47&"'!B:B"),INDIRECT("'"&$M$47&"'!AE:AE"),0),0)} -> 0 | S39: {=IFERROR(_xlfn.XLOOKUP(B39,INDIRECT("'"&$M$47&"'!B:B"),INDIRECT("'"&$M$47&"'!AF:AF"),0),0)} -> 0 | T39: =SUM(N39:S39) -> 0 | U39: =ROUND(SUM(M39:S39),2) -> 0 | V39: {=IFERROR(_xlfn.XLOOKUP(B39,INDIRECT("'"&$K$47&"'!B:B"),INDIRECT("'"&$K$47&"'!Y:Y"),0),0)} -> 0 | W39: =U39+V39 -> 0 | X39: {=IFERROR(_xlfn.XLOOKUP(B39,INDIRECT("'"&$K$47&"'!B:B"),INDIRECT("'"&$K$47&"'!Z:Z"),0),0)} -> 0 | Y39: =F39+X39 -> 4137.93 | Z39: {=IFERROR(_xlfn.LET(_xlpm.v,_xlfn.XLOOKUP(B39,INDIRECT("'"&$K$47&"'!B:B"),INDIRECT("'"&$K$47&"'!AA:AA"),0),IF(_xlpm.v=60000,60000,_xlpm.v+5000)),0)} -> 0 | AA39: =ROUND(F39-M39,2) -> 4137.93 | AB39: =IF(ROUND(Y39-W39-Z39,2)>0,ROUND(Y39-W39-Z39,2),0) -> 4137.93 | AC39: =ROUND(IF(AB39>960000,AB39*0.45-181920,IF(AB39>660000,AB39*0.35-85920,IF(AB39>420000,AB39*0.3-52920,IF(AB39>300000,AB39*0.25-31920,IF(AB39>144000,AB39*0.2-16920,IF(AB39>36000,AB39*0.1-2520,IF(AB39>0,AB39*0.03,0))))))),2) -> 124.14 | AD39: {=IFERROR(_xlfn.XLOOKUP(B39,INDIRECT("'"&$K$47&"'!B:B"),INDIRECT("'"&$K$47&"'!AD:AD"),0),0)} -> 0 | AE39: =ROUND(MAX(AC39-AD39,0),2) -> 124.14 | AF39: =ROUND(AA39-AE39,2) -> 4013.79
A40: =ROW(A40)-2 -> 38 | B40: 一百七十五 | C40: {=_xlfn.XLOOKUP(B40,INDIRECT("'"&$A$1&"'!B:B"),INDIRECT("'"&$A$1&"'!D:D"),"人员不存在",0,1)} -> 46113 | D40: {=_xlfn.XLOOKUP(B40,INDIRECT("'"&$A$1&"'!B:B"),INDIRECT("'"&$A$1&"'!G:G"),"人员不存在",0,1)} -> 10000 | E40: =IFERROR(F40/D40,0) -> 1 | F40: {=_xlfn.XLOOKUP(B40,INDIRECT("'"&$A$1&"'!B:B"),INDIRECT("'"&$A$1&"'!Q:Q"),"人员不存在",0,1)} -> 10000 | G40: {=SUMIF(INDIRECT("'"&$G$47&"'!C5:C"&IFERROR(MATCH(TRUE,ISBLANK(INDIRECT("'"&$G$47&"'!C5:C500")),0)+4,500)),B40,INDIRECT("'"&$G$47&"'!K5:K"&IFERROR(MATCH(TRUE,ISBLANK(INDIRECT("'"&$G$47&"'!C5:C500")),0)+4,500)))} -> 0 | H40: {=SUMIF(INDIRECT("'"&$G$47&"'!C5:C"&IFERROR(MATCH(TRUE,ISBLANK(INDIRECT("'"&$G$47&"'!C5:C500")),0)+4,500)),B40,INDIRECT("'"&$G$47&"'!L5:L"&IFERROR(MATCH(TRUE,ISBLANK(INDIRECT("'"&$G$47&"'!C5:C500")),0)+4,500)))} -> 0 | I40: {=SUMIF(INDIRECT("'"&$G$47&"'!C5:C"&IFERROR(MATCH(TRUE,ISBLANK(INDIRECT("'"&$G$47&"'!C5:C500")),0)+4,500)),B40,INDIRECT("'"&$G$47&"'!M5:M"&IFERROR(MATCH(TRUE,ISBLANK(INDIRECT("'"&$G$47&"'!C5:C500")),0)+4,500)))} -> 0 | J40: {=SUMIF(INDIRECT("'"&$G$47&"'!C5:C"&IFERROR(MATCH(TRUE,ISBLANK(INDIRECT("'"&$G$47&"'!C5:C500")),0)+4,500)),B40,INDIRECT("'"&$G$47&"'!N5:N"&IFERROR(MATCH(TRUE,ISBLANK(INDIRECT("'"&$G$47&"'!C5:C500")),0)+4,500)))} -> 0 | K40: =SUM(G40:J40) -> 0 | L40: {=IFERROR(_xlfn.XLOOKUP(B40,INDIRECT("'"&$I$47&"'!B:B"),INDIRECT("'"&$I$47&"'!E:E"),0),0)} -> 0 | M40: =ROUND(SUM(K40:L40),2) -> 0 | N40: {=IFERROR(_xlfn.XLOOKUP(B40,INDIRECT("'"&$M$47&"'!B:B"),INDIRECT("'"&$M$47&"'!AC:AC"),0),0)} -> 0 | O40: {=IFERROR(_xlfn.XLOOKUP(B40,INDIRECT("'"&$M$47&"'!B:B"),INDIRECT("'"&$M$47&"'!AG:AG"),0),0)} -> 0 | P40: {=IFERROR(_xlfn.XLOOKUP(B40,INDIRECT("'"&$M$47&"'!B:B"),INDIRECT("'"&$M$47&"'!AB:AB"),0),0)} -> 0 | Q40: {=IFERROR(_xlfn.XLOOKUP(B40,INDIRECT("'"&$M$47&"'!B:B"),INDIRECT("'"&$M$47&"'!AD:AD"),0),0)} -> 0 | R40: {=IFERROR(_xlfn.XLOOKUP(B40,INDIRECT("'"&$M$47&"'!B:B"),INDIRECT("'"&$M$47&"'!AE:AE"),0),0)} -> 0 | S40: {=IFERROR(_xlfn.XLOOKUP(B40,INDIRECT("'"&$M$47&"'!B:B"),INDIRECT("'"&$M$47&"'!AF:AF"),0),0)} -> 0 | T40: =SUM(N40:S40) -> 0 | U40: =ROUND(SUM(M40:S40),2) -> 0 | V40: {=IFERROR(_xlfn.XLOOKUP(B40,INDIRECT("'"&$K$47&"'!B:B"),INDIRECT("'"&$K$47&"'!Y:Y"),0),0)} -> 0 | W40: =U40+V40 -> 0 | X40: {=IFERROR(_xlfn.XLOOKUP(B40,INDIRECT("'"&$K$47&"'!B:B"),INDIRECT("'"&$K$47&"'!Z:Z"),0),0)} -> 0 | Y40: =F40+X40 -> 10000 | Z40: {=IFERROR(_xlfn.LET(_xlpm.v,_xlfn.XLOOKUP(B40,INDIRECT("'"&$K$47&"'!B:B"),INDIRECT("'"&$K$47&"'!AA:AA"),0),IF(_xlpm.v=60000,60000,_xlpm.v+5000)),0)} -> 0 | AA40: =ROUND(F40-M40,2) -> 10000 | AB40: =IF(ROUND(Y40-W40-Z40,2)>0,ROUND(Y40-W40-Z40,2),0) -> 10000 | AC40: =ROUND(IF(AB40>960000,AB40*0.45-181920,IF(AB40>660000,AB40*0.35-85920,IF(AB40>420000,AB40*0.3-52920,IF(AB40>300000,AB40*0.25-31920,IF(AB40>144000,AB40*0.2-16920,IF(AB40>36000,AB40*0.1-2520,IF(AB40>0,AB40*0.03,0))))))),2) -> 300 | AD40: {=IFERROR(_xlfn.XLOOKUP(B40,INDIRECT("'"&$K$47&"'!B:B"),INDIRECT("'"&$K$47&"'!AD:AD"),0),0)} -> 0 | AE40: =ROUND(MAX(AC40-AD40,0),2) -> 300 | AF40: =ROUND(AA40-AE40,2) -> 9700
A41: 合计 | D41: =SUM(D3:D40) -> 340000 | E41: =SUM(E3:E40) -> 32.410919 | F41: =SUM(F3:F40) -> 330589.19 | G41: =SUM(G3:G40) -> 0 | H41: =SUM(H3:H40) -> 0 | I41: =SUM(I3:I40) -> 0 | J41: =SUM(J3:J40) -> 0 | K41: =SUM(K3:K40) -> 0 | ... AF41: =SUM(AF3:AF40) -> 320821.52
A43: 总经理： 财务负责人： 制表人：
G47: 202604社保 (尚诚能源) | I47: 202604公积金(尚诚能源) | K47: 202603工资明细表（尚诚能源） | M47: 202604综合所得申报税款计算(尚诚能源)

Sheet 202604社保 (尚诚能源)
A1: 社会保险费征缴明细 | S1: 上限标准：24,762元/月，下限标准：4,952元/月
A2: 单位名称： | C2: 江苏尚诚能源科技有限公司 | G2: 社保代码： | H2: 60545906 | K2: 所属月份： | L2: 46154
A3: 编号 | B3: 个人代码 | C3: 姓名 | D3: 缴费基数 | G3: 单位缴纳 | H3: （元/月） | L3: 个人缴纳 | M3: （元/月） | P3: 备注
D4: 元/月 | E4: 养 老 | F4: 工伤 | G4: 失 业 | H4: 医疗 | I4: 生 育 | J4: 合 计 | K4: 养 老 | L4: 失业 | M4: 医疗 | N4: 大 病 | O4: 合 计
A5: =ROW(A5)-4 -> 1 | B5: 1880832781 | C5: 崔晓艳 | D5: 10000 | E5: =ROUND(D5*0.16,2) -> 1600 | F5: =ROUND(D5*0.0032,2) -> 32 | G5: =ROUND(D5*0.005,2) -> 50 | H5: =ROUND(D5*0.07,2) -> 700 | I5: =ROUND(D5*0.008,2) -> 80 | J5: =SUM(E5:I5) -> 2462 | K5: =ROUND(D5*0.08,2) -> 800 | L5: =ROUND(D5*0.005,2) -> 50 | M5: =ROUND(D5*0.02,2) -> 200 | N5: 10 | O5: =SUM(K5:N5) -> 1060
A6: =ROW(A6)-4 -> 2 | B6: 1883005797 | C6: 张旭 | D6: 10000 | E6: =ROUND(D6*0.16,2) -> 1600 | F6: =ROUND(D6*0.0032,2) -> 32 | G6: =ROUND(D6*0.005,2) -> 50 | H6: =ROUND(D6*0.07,2) -> 700 | I6: =ROUND(D6*0.008,2) -> 80 | J6: =SUM(E6:I6) -> 2462 | K6: =ROUND(D6*0.08,2) -> 800 | L6: =ROUND(D6*0.005,2) -> 50 | M6: =ROUND(D6*0.02,2) -> 200 | N6: 10 | O6: =SUM(K6:N6) -> 1060
A7: =ROW(A7)-4 -> 3 | B7: 1880745209 | C7: 丁玉靓 | D7: 10000 | E7: =ROUND(D7*0.16,2) -> 1600 | F7: =ROUND(D7*0.0032,2) -> 32 | G7: =ROUND(D7*0.005,2) -> 50 | H7: =ROUND(D7*0.07,2) -> 700 | I7: =ROUND(D7*0.008,2) -> 80 | J7: =SUM(E7:I7) -> 2462 | K7: =ROUND(D7*0.08,2) -> 800 | L7: =ROUND(D7*0.005,2) -> 50 | M7: =ROUND(D7*0.02,2) -> 200 | N7: 10 | O7: =SUM(K7:N7) -> 1060
A8: =ROW(A8)-4 -> 4 | B8: 1000814047 | C8: 王进辉 | D8: 10000 | E8: =ROUND(D8*0.16,2) -> 1600 | F8: =ROUND(D8*0.0032,2) -> 32 | G8: =ROUND(D8*0.005,2) -> 50 | H8: =ROUND(D8*0.07,2) -> 700 | I8: =ROUND(D8*0.008,2) -> 80 | J8: =SUM(E8:I8) -> 2462 | K8: =ROUND(D8*0.08,2) -> 800 | L8: =ROUND(D8*0.005,2) -> 50 | M8: =ROUND(D8*0.02,2) -> 200 | N8: 10 | O8: =SUM(K8:N8) -> 1060
A9: =ROW(A9)-4 -> 5 | B9: 1884195189 | C9: 陈瀚 | D9: 10000 | E9: =ROUND(D9*0.16,2) -> 1600 | F9: =ROUND(D9*0.0032,2) -> 32 | G9: =ROUND(D9*0.005,2) -> 50 | H9: =ROUND(D9*0.07,2) -> 700 | I9: =ROUND(D9*0.008,2) -> 80 | J9: =SUM(E9:I9) -> 2462 | K9: =ROUND(D9*0.08,2) -> 800 | L9: =ROUND(D9*0.005,2) -> 50 | M9: =ROUND(D9*0.02,2) -> 200 | N9: 10 | O9: =SUM(K9:N9) -> 1060
A10: =ROW(A10)-4 -> 6 | B10: 1888480210 | C10: 卢少阳 | D10: 10000 | E10: =ROUND(D10*0.16,2) -> 1600 | F10: =ROUND(D10*0.0032,2) -> 32 | G10: =ROUND(D10*0.005,2) -> 50 | H10: =ROUND(D10*0.07,2) -> 700 | I10: =ROUND(D10*0.008,2) -> 80 | J10: =SUM(E10:I10) -> 2462 | K10: =ROUND(D10*0.08,2) -> 800 | L10: =ROUND(D10*0.005,2) -> 50 | M10: =ROUND(D10*0.02,2) -> 200 | N10: 10 | O10: =SUM(K10:N10) -> 1060
A11: =ROW(A11)-4 -> 7 | B11: 1881698817 | C11: 莫晓慧 | D11: 10000 | E11: =ROUND(D11*0.16,2) -> 1600 | F11: =ROUND(D11*0.0032,2) -> 32 | G11: =ROUND(D11*0.005,2) -> 50 | H11: =ROUND(D11*0.07,2) -> 700 | I11: =ROUND(D11*0.008,2) -> 80 | J11: =SUM(E11:I11) -> 2462 | K11: =ROUND(D11*0.08,2) -> 800 | L11: =ROUND(D11*0.005,2) -> 50 | M11: =ROUND(D11*0.02,2) -> 200 | N11: 10 | O11: =SUM(K11:N11) -> 1060
A12: =ROW(A12)-4 -> 8 | B12: 1895561547 | C12: 王灿 | D12: 10000 | E12: =ROUND(D12*0.16,2) -> 1600 | F12: =ROUND(D12*0.0032,2) -> 32 | G12: =ROUND(D12*0.005,2) -> 50 | H12: =ROUND(D12*0.07,2) -> 700 | I12: =ROUND(D12*0.008,2) -> 80 | J12: =SUM(E12:I12) -> 2462 | K12: =ROUND(D12*0.08,2) -> 800 | L12: =ROUND(D12*0.005,2) -> 50 | M12: =ROUND(D12*0.02,2) -> 200 | N12: 10 | O12: =SUM(K12:N12) -> 1060
A13: =ROW(A13)-4 -> 9 | B13: 1000323907 | C13: 马思雨 | D13: 10000 | E13: =ROUND(D13*0.16,2) -> 1600 | F13: =ROUND(D13*0.0032,2) -> 32 | G13: =ROUND(D13*0.005,2) -> 50 | H13: =ROUND(D13*0.07,2) -> 700 | I13: =ROUND(D13*0.008,2) -> 80 | J13: =SUM(E13:I13) -> 2462 | K13: =ROUND(D13*0.08,2) -> 800 | L13: =ROUND(D13*0.005,2) -> 50 | M13: =ROUND(D13*0.02,2) -> 200 | N13: 10 | O13: =SUM(K13:N13) -> 1060
A14: =ROW(A14)-4 -> 10 | B14: 1889554867 | C14: 于姝雅 | D14: 10000 | E14: =ROUND(D14*0.16,2) -> 1600 | F14: =ROUND(D14*0.0032,2) -> 32 | G14: =ROUND(D14*0.005,2) -> 50 | H14: =ROUND(D14*0.07,2) -> 700 | I14: =ROUND(D14*0.008,2) -> 80 | J14: =SUM(E14:I14) -> 2462 | K14: =ROUND(D14*0.08,2) -> 800 | L14: =ROUND(D14*0.005,2) -> 50 | M14: =ROUND(D14*0.02,2) -> 200 | N14: 10 | O14: =SUM(K14:N14) -> 1060
A15: =ROW(A15)-4 -> 11 | B15: 1895467502 | C15: 王宇佳 | D15: 10000 | E15: =ROUND(D15*0.16,2) -> 1600 | F15: =ROUND(D15*0.0032,2) -> 32 | G15: =ROUND(D15*0.005,2) -> 50 | H15: =ROUND(D15*0.07,2) -> 700 | I15: =ROUND(D15*0.008,2) -> 80 | J15: =SUM(E15:I15) -> 2462 | K15: =ROUND(D15*0.08,2) -> 800 | L15: =ROUND(D15*0.005,2) -> 50 | M15: =ROUND(D15*0.02,2) -> 200 | N15: 10 | O15: =SUM(K15:N15) -> 1060
A16: =ROW(A16)-4 -> 12 | B16: 1188747255 | C16: 潘渐 | D16: 10000 | E16: =ROUND(D16*0.16,2) -> 1600 | F16: =ROUND(D16*0.0032,2) -> 32 | G16: =ROUND(D16*0.005,2) -> 50 | H16: =ROUND(D16*0.07,2) -> 700 | I16: =ROUND(D16*0.008,2) -> 80 | J16: =SUM(E16:I16) -> 2462 | K16: =ROUND(D16*0.08,2) -> 800 | L16: =ROUND(D16*0.005,2) -> 50 | M16: =ROUND(D16*0.02,2) -> 200 | N16: 10 | O16: =SUM(K16:N16) -> 1060
A17: =ROW(A17)-4 -> 13 | B17: 1888711045 | C17: 高俊杰 | D17: 10000 | E17: =ROUND(D17*0.16,2) -> 1600 | F17: =ROUND(D17*0.0032,2) -> 32 | G17: =ROUND(D17*0.005,2) -> 50 | H17: =ROUND(D17*0.07,2) -> 700 | I17: =ROUND(D17*0.008,2) -> 80 | J17: =SUM(E17:I17) -> 2462 | K17: =ROUND(D17*0.08,2) -> 800 | L17: =ROUND(D17*0.005,2) -> 50 | M17: =ROUND(D17*0.02,2) -> 200 | N17: 10 | O17: =SUM(K17:N17) -> 1060
A18: =ROW(A18)-4 -> 14 | B18: 1893708088 | C18: 郭梦杰 | D18: 10000 | E18: =ROUND(D18*0.16,2) -> 1600 | F18: =ROUND(D18*0.0032,2) -> 32 | G18: =ROUND(D18*0.005,2) -> 50 | H18: =ROUND(D18*0.07,2) -> 700 | I18: =ROUND(D18*0.008,2) -> 80 | J18: =SUM(E18:I18) -> 2462 | K18: =ROUND(D18*0.08,2) -> 800 | L18: =ROUND(D18*0.005,2) -> 50 | M18: =ROUND(D18*0.02,2) -> 200 | N18: 10 | O18: =SUM(K18:N18) -> 1060
A19: =ROW(A19)-4 -> 15 | B19: 1000545280 | C19: 宣明 | D19: 10000 | E19: =ROUND(D19*0.16,2) -> 1600 | F19: =ROUND(D19*0.0032,2) -> 32 | G19: =ROUND(D19*0.005,2) -> 50 | H19: =ROUND(D19*0.07,2) -> 700 | I19: =ROUND(D19*0.008,2) -> 80 | J19: =SUM(E19:I19) -> 2462 | K19: =ROUND(D19*0.08,2) -> 800 | L19: =ROUND(D19*0.005,2) -> 50 | M19: =ROUND(D19*0.02,2) -> 200 | N19: 10 | O19: =SUM(K19:N19) -> 1060
A20: =ROW(A20)-4 -> 16 | C20: 钱晓武 | D20: 10000 | E20: =ROUND(D20*0.16,2) -> 1600 | F20: =ROUND(D20*0.0032,2) -> 32 | G20: =ROUND(D20*0.005,2) -> 50 | H20: =ROUND(D20*0.07,2) -> 700 | I20: =ROUND(D20*0.008,2) -> 80 | J20: =SUM(E20:I20) -> 2462 | K20: =ROUND(D20*0.08,2) -> 800 | L20: =ROUND(D20*0.005,2) -> 50 | M20: =ROUND(D20*0.02,2) -> 200 | N20: 10 | O20: =SUM(K20:N20) -> 1060
A21: =ROW(A21)-4 -> 17 | C21: 邢春燕 | D21: 10000 | E21: =ROUND(D21*0.16,2) -> 1600 | F21: =ROUND(D21*0.0032,2) -> 32 | G21: =ROUND(D21*0.005,2) -> 50 | H21: =ROUND(D21*0.07,2) -> 700 | I21: =ROUND(D21*0.008,2) -> 80 | J21: =SUM(E21:I21) -> 2462 | K21: =ROUND(D21*0.08,2) -> 800 | L21: =ROUND(D21*0.005,2) -> 50 | M21: =ROUND(D21*0.02,2) -> 200 | N21: 10 | O21: =SUM(K21:N21) -> 1060
A22: =ROW(A22)-4 -> 18 | C22: 潘立兴 | D22: 10000 | E22: =ROUND(D22*0.16,2) -> 1600 | F22: =ROUND(D22*0.0032,2) -> 32 | G22: =ROUND(D22*0.005,2) -> 50 | H22: =ROUND(D22*0.07,2) -> 700 | I22: =ROUND(D22*0.008,2) -> 80 | J22: =SUM(E22:I22) -> 2462 | K22: =ROUND(D22*0.08,2) -> 800 | L22: =ROUND(D22*0.005,2) -> 50 | M22: =ROUND(D22*0.02,2) -> 200 | N22: 10 | O22: =SUM(K22:N22) -> 1060
A23: 补缴4月 | C23: 潘立兴 | D23: 10000 | E23: 0 | F23: =ROUND(D23*0.0032,2) -> 32 | G23: 0 | H23: 0 | I23: 0 | J23: =SUM(E23:I23) -> 32 | K23: 0 | L23: 0 | M23: 0 | N23: 0 | O23: =SUM(K23:N23) -> 0
D24: =SUM(D5:D23) -> 190000 | E24: =SUM(E5:E23) -> 28800 | F24: =SUM(F5:F23) -> 608 | G24: =SUM(G5:G23) -> 900 | H24: =SUM(H5:H23) -> 12600 | I24: =SUM(I5:I23) -> 1440 | J24: =SUM(J5:J23) -> 44348 | K24: =SUM(K5:K23) -> 14400 | ... O24: =SUM(O5:O23) -> 19080
C27: 本月应缴纳的总数： | E27: =J24+O24 -> 63428 | F27: 调整基数： | G27: 0 | K27: 滞纳金 | L27: 0
C28: 退费： | D28: 0 | E28: 差额：0 | F28: 0 | G28: 本月实际缴纳总额： | I28: =J24+O24 -> 63428
A31: 本月终止参加社会保险名单 | H31: 缴费截止时间：2026年05月
A32: 序号 | B32: 个人代码 | C32: 姓名 | D32: 缴费基数 | G32: 单位缴纳 | H32: （元/月） | L32: 个人缴纳 | M32: （元/月） | P32: 备注
D33: 元/月 | E33: 养 老 | F33: 工伤 | G33: 失 业 | H33: 医疗 | I33: 生 育 | J33: 合 计 | K33: 养 老 | L33: 失业 | M33: 医疗 | N33: 大 病 | O33: 合 计
A34: 1 | C34: 牛畅 | D34: 10000 | E34: =ROUND(D34*0.16,2) -> 1600 | F34: =ROUND(D34*0.0032,2) -> 32 | G34: =ROUND(D34*0.005,2) -> 50 | H34: =ROUND(D34*0.07,2) -> 700 | I34: =ROUND(D34*0.008,2) -> 80 | J34: =ROUND(SUM(E34:I34),2) -> 2462 | K34: =ROUND(D34*0.08,2) -> 800 | L34: =ROUND(D34*0.005,2) -> 50 | M34: =ROUND(D34*0.02,2) -> 200 | N34: 10 | O34: =SUM(K34:N34) -> 1060
A37: 合计 | J37: =SUM(J34:J36) -> 2462 | K37: 合计 | O37: =SUM(O34:O36) -> 1060
A39: 序号 | C39: 险种名称 | D39: 本期结算征缴人数 | E39: 本期结算征缴缴费基数 | F39: 本期结算征缴比例 | G39: 本期结算征缴应缴 | H39: 退费 | I39: 补缴 | J39: 利息 | K39: 滞纳金 | L39: 差额调整 | M39: 应收合计
A40: 1 | C40: 企业养老保险 | D40: =COUNTA($E$5:$E$22) -> 18 | E40: =SUM($D$5:$D$22) -> 180000 | F40: 0.24 | G40: =SUM(E5:E22,K5:K22) -> 43200 | I40: =SUM(E23:E23,K23:K23) -> 0 | M40: =G40+I40 -> 43200
A41: 2 | C41: 工伤保险 | D41: =COUNTA($F$5:$F$22) -> 18 | E41: =SUM($D$5:$D$22) -> 180000 | F41: 0.0032 | G41: =SUM(F5:F22) -> 576 | I41: =SUM(F23:F23) -> 32 | M41: =G41+I41 -> 608
A42: 3 | C42: 失业保险 | D42: =COUNTA($G$5:$G$22) -> 18 | E42: =SUM($D$5:$D$22) -> 180000 | F42: 0.01 | G42: =SUM(G5:G22,L5:L22) -> 1800 | I42: =SUM(G23:G23,L23:L23) -> 0 | M42: =G42+I42 -> 1800
A43: 4 | C43: 基本医疗保险 | D43: =COUNTA($H$5:$H$22) -> 18 | E43: =SUM($D$5:$D$22) -> 180000 | F43: 0.09 | G43: =SUM(H5:H22,M5:M22) -> 16200 | I43: =SUM(H23:H23,M23:M23) -> 0 | M43: =G43+I43 -> 16200
A44: 5 | C44: 医疗保险(生育) | D44: =COUNTA($I$5:$I$22) -> 18 | E44: =SUM($D$5:$D$22) -> 180000 | F44: 0.008 | G44: =SUM(I5:I22) -> 1440 | I44: =SUM(I23:I23) -> 0 | M44: =G44+I44 -> 1440
A45: 6 | C45: 大病医疗保险 | D45: =COUNTA($N$5:$N$22) -> 18 | E45: =SUM(N5:N22) -> 180 | F45: 0 | G45: =SUM(N5:N22) -> 180 | I45: =SUM(N23:N23) -> 0 | M45: =G45+I45 -> 180
M46: =SUM(M40:M45) -> 63428
A49: 总经理： | E49: 财务负责人： | K49: 制表人：

Sheet 202604公积金(尚诚能源)
A1: 2026年05月份代扣代缴住房公积金明细
A3: 单位：江苏尚诚能源科技有限公司 | F3: 单位：元
A4: 序号 | B4: 姓名 | C4: 基数 | D4: 单位（10％） | E4: 个人（10％） | F4: 合计
A5: =ROW(A5)-4 -> 1 | B5: 崔晓艳 | C5: 10000 | D5: =ROUND(C5*0.1,0) -> 1000 | E5: =ROUND(C5*0.1,0) -> 1000 | F5: =SUM(D5:E5) -> 2000
A6: =ROW(A6)-4 -> 2 | B6: 张旭 | C6: 10000 | D6: =ROUND(C6*0.1,0) -> 1000 | E6: =ROUND(C6*0.1,0) -> 1000 | F6: =SUM(D6:E6) -> 2000
A7: =ROW(A7)-4 -> 3 | B7: 丁玉靓 | C7: 10000 | D7: =ROUND(C7*0.1,0) -> 1000 | E7: =ROUND(C7*0.1,0) -> 1000 | F7: =SUM(D7:E7) -> 2000
A8: =ROW(A8)-4 -> 4 | B8: 王进辉 | C8: 10000 | D8: =ROUND(C8*0.1,0) -> 1000 | E8: =ROUND(C8*0.1,0) -> 1000 | F8: =SUM(D8:E8) -> 2000
A9: =ROW(A9)-4 -> 5 | B9: 陈瀚 | C9: 10000 | D9: =ROUND(C9*0.1,0) -> 1000 | E9: =ROUND(C9*0.1,0) -> 1000 | F9: =SUM(D9:E9) -> 2000
A10: =ROW(A10)-4 -> 6 | B10: 卢少阳 | C10: 10000 | D10: =ROUND(C10*0.1,0) -> 1000 | E10: =ROUND(C10*0.1,0) -> 1000 | F10: =SUM(D10:E10) -> 2000
A11: =ROW(A11)-4 -> 7 | B11: 莫晓慧 | C11: 10000 | D11: =ROUND(C11*0.1,0) -> 1000 | E11: =ROUND(C11*0.1,0) -> 1000 | F11: =SUM(D11:E11) -> 2000
A12: =ROW(A12)-4 -> 8 | B12: 王灿 | C12: 10000 | D12: =ROUND(C12*0.1,0) -> 1000 | E12: =ROUND(C12*0.1,0) -> 1000 | F12: =SUM(D12:E12) -> 2000
A13: =ROW(A13)-4 -> 9 | B13: 马思雨 | C13: 10000 | D13: =ROUND(C13*0.1,0) -> 1000 | E13: =ROUND(C13*0.1,0) -> 1000 | F13: =SUM(D13:E13) -> 2000
